Workbook

Sheet ÍNDICE
B2: Tabela de Preços Vivo (Índice)
B4: DOCUMENTO CONFIDENCIAL
B5: No pós pago a orientação é de sempre utilizarmos a tabela “Mais Vivo” nos precificadores, para nos mantermos atrativos frente a concorrência e em linha com as mídias cooperadas.
D7: Vigência a partir de | F7: 46280
B9: Diretoria | F9: Gerência
B10: Dir Marketing Consumer Electronics | F10: Gerência Pricing Estratégico
B11: Diretor Responsável | F11: Gerente Responsável
B12: Arnaud Jean Dusaintpere | F12: Eric Kikuti
B13: Documento Elaborado por | F13: Classificação do Documento
B14: Bruna Marques | F14: Sempre Confidencial
B16: ATENÇÃO
B17: As informações existentes neste documento são para conhecimento e uso confidencial dos destinatários abaixo, sendo seu sigilo protegido por lei e seu uso regulado por política interna específica da VIVO.
B20: TABELAS
B22: RESUMO DAS ALTERAÇÕES | F22: ELETRÔNICOS_LP_Conectados
B24: LISTA DE PLANOS | F24: ELETRÔNICOS_LP_Não Conectados
B26: LISTA DE PRODUTOS | F26: VITRINE
B28: SMARTPHONES e WATCHES CONECTADOS | F28: SMARTPHONES_Demo
B30: INFORMAÇÕES ADICIONAIS
F32: PVP aparelho NÃO inclui Chip, cujo valor é R$13
F34: Revendas utilizam o mesmo preço de lojas proprias.
F36: Preço referência 2x a 12x para pagamentos no Crédito a vista, débito, dinheiro e Vivo Pay.

Sheet ALTERAÇÕES
A1: RESUMO DE ALTERAÇÕES
A2: SMARTPHONES E WATCHES | C2: SMARTPHONES E WATCHES Renova | E2: ELETRÔNICOS_LP_Não Conectados | G2: ELETRÔNICOS_LP_Conectados | I2: ELETRÔNICOS_LP_Conectados RENOVA | K2: VITRINE | M2: SMARTPHONES_Demo
A3: {=IFERROR(_xlfn._xlws.SORT(_xlfn._xlws.FILTER(SMARTPHONES!E:E,SMARTPHONES!OL:OL=1)),"Sem alterações")} -> iPhone 15 256GB | C3: {=IFERROR(_xlfn._xlws.SORT(_xlfn._xlws.FILTER(SMARTPHONES!E:E,SMARTPHONES!OM:OM=1)),"Sem alterações")} -> Samsung Galaxy S26 FE 256GB | E3: {=IFERROR(_xlfn._xlws.SORT(_xlfn._xlws.FILTER('ELETRÔNICOS_LP_Não Conectados'!D:D,'ELETRÔNICOS_LP_Não Conectados'!AB:AB=1)),"Sem alterações")} -> Cabo Magnetico Lightning|C 1,2M I2GO | G3: {=IFERROR(_xlfn._xlws.SORT(_xlfn._xlws.FILTER(ELETRÔNICOS_LP_Conectados!E:E,ELETRÔNICOS_LP_Conectados!KX:KX=1)),"Sem alterações")} -> Samsung Galaxy Tab A11+ 5G 128GB | I3: {=IFERROR(_xlfn._xlws.SORT(_xlfn._xlws.FILTER(ELETRÔNICOS_LP_Conectados!E:E,ELETRÔNICOS_LP_Conectados!KY:KY=1)),"Sem alterações")} -> Sem alterações | K3: {=IFERROR(_xlfn._xlws.SORT(_xlfn._xlws.FILTER(VITRINE!D:D,VITRINE!AC:AC=1)),"Sem alterações")} -> Sem alterações | M3: {=IFERROR(_xlfn._xlws.SORT(_xlfn._xlws.FILTER(SMARTPHONES_Demo!D:D,SMARTPHONES_Demo!H:H=1)),"Sem alterações")} -> Sem alterações
A4: JOVI V70 5G 512GB | E4: Cabo Magnético USB-C/C 1,2M I2GO | G4: Samsung Galaxy Tab S10 FE 5G 128GB
A5: Moto G Max 5G 256GB | E5: Carregador Parede Universal 45W Ovvi
A6: Motorola Edge 70 512GB | E6: Console PS5 Slim Digital Com Astro Bot e Gran Turismo 7
A7: Oppo A6X 5G 256GB | E7: Console PS5 Slim Disk Com Astro Bot e Gran Turismo 7
A8: Samsung Galaxy A37 5G 256GB | E8: Controle sem fio DualSense™ Midnight Black
A9: Samsung Galaxy S26 Ultra 256GB | E9: Estojo P/ Acessórios I2GO
A10: Samsung Galaxy Z Fold 8 256GB | E10: Galaxy Buds 3 FE
E11: Kit Creator 5 em 1 I2GO
E12: Monitor Portátil Acer PM161Q 15.6 Pol
E13: Nintendo Switch 2 com Mario Kart World
E14: Nintendo Switch Oled
E15: Nintendo Switch Oled com Mario Bros Wonder
E16: Nintendo Switch V2 com Super Mario Bros Wonder
E17: Powerbank 20.000 MAH 12W I2GO
E18: Powerbank 5000 Pocket Lightning I2GO
E19: Powerbank Pocket 5.000 USB-C I2GO
E20: Powerbank 5000MAH Magsafe Slim Ovvi
E21: Robô Aspirador W90 WAP
E22: Samsung Galaxy Tab S10 FE Wi-Fi 128GB
... E31: Smart TV Samsung Vision AI QLED 4K QEF1 2025 50Pol

Sheet PLANOS
A1: PRODUTO | B1: TIPO DE PLANO | C1: NOME DO PLANO CLIENTE SISTEMA | D1: NOME DO BUNDLE (PLANOS VIVO TOTAL) | E1: SISTEMA | F1: GRUPAMENTO ATUAL | G1: COD SISTEMA | H1: COD SAP (USAR PARA VENDA MANUAL) | I1: NOME PLANO SAP (VENDA MANUAL) | J1: RENOVA COD SAP (VENDA MANUAL) | K1: RENOVA NOME PLANO SAP (VENDA MANUAL) | L1: GRUPAMENTO ANTERIOR | M1: OBSERVAÇÃO
A2: SMARTPHONE_SMARTWATCH | B2: Disponível para ALTA/MIGRAÇÃO | C2: VIVO CONTROLE 15GB VIII | D2: - | E2: NEXT | F2: CONTROLE ENTRADA | G2: 44640499 | H2: =_xlfn.XLOOKUP(F2,'AUXILIAR SAP'!E:E,'AUXILIAR SAP'!B:B) -> BC4 | I2: =_xlfn.XLOOKUP(F2,'AUXILIAR SAP'!E:E,'AUXILIAR SAP'!D:D) -> CONTROLE_ENT | J2: =IFERROR(_xlfn.XLOOKUP(F2,'AUXILIAR SAP'!J:J,'AUXILIAR SAP'!G:G),"-") -> BE4 | K2: =IFERROR(_xlfn.XLOOKUP(F2,'AUXILIAR SAP'!J:J,'AUXILIAR SAP'!I:I),"-") -> REN_CONTROLE_ENT | L2: CONTROLE ENTRADA | M2: Alteração de nomenclatura 26/03/26
A3: SMARTPHONE_SMARTWATCH | B3: Disponível para ALTA/MIGRAÇÃO | C3: VIVO CONTROLE 20GB IX | D3: - | E3: NEXT | F3: CONTROLE ALTO VALOR | G3: 44640509 | H3: =_xlfn.XLOOKUP(F3,'AUXILIAR SAP'!E:E,'AUXILIAR SAP'!B:B) -> CU6 | I3: =_xlfn.XLOOKUP(F3,'AUXILIAR SAP'!E:E,'AUXILIAR SAP'!D:D) -> CONTROLE_AV | J3: =IFERROR(_xlfn.XLOOKUP(F3,'AUXILIAR SAP'!J:J,'AUXILIAR SAP'!G:G),"-") -> CY2 | K3: =IFERROR(_xlfn.XLOOKUP(F3,'AUXILIAR SAP'!J:J,'AUXILIAR SAP'!I:I),"-") -> REN_CONTROLE_AV | L3: CONTROLE ALTO VALOR | M3: Alteração de nomenclatura 26/03/26
A4: SMARTPHONE_SMARTWATCH | B4: Disponível para ALTA/MIGRAÇÃO | C4: VIVO CONTROLE 20GB X | D4: - | E4: NEXT | F4: CONTROLE ALTO VALOR | G4: 44640529 | H4: =_xlfn.XLOOKUP(F4,'AUXILIAR SAP'!E:E,'AUXILIAR SAP'!B:B) -> CU6 | I4: =_xlfn.XLOOKUP(F4,'AUXILIAR SAP'!E:E,'AUXILIAR SAP'!D:D) -> CONTROLE_AV | J4: =IFERROR(_xlfn.XLOOKUP(F4,'AUXILIAR SAP'!J:J,'AUXILIAR SAP'!G:G),"-") -> CY2 | K4: =IFERROR(_xlfn.XLOOKUP(F4,'AUXILIAR SAP'!J:J,'AUXILIAR SAP'!I:I),"-") -> REN_CONTROLE_AV | L4: CONTROLE ALTO VALOR | M4: Alteração de nomenclatura 26/03/26
A5: SMARTPHONE_SMARTWATCH | B5: Disponível para ALTA/MIGRAÇÃO | C5: VIVO CONTROLE VANTAGENS 20GB | D5: - | E5: NEXT | F5: CONTROLE ALTO VALOR | G5: 44640549 | H5: =_xlfn.XLOOKUP(F5,'AUXILIAR SAP'!E:E,'AUXILIAR SAP'!B:B) -> CU6 | I5: =_xlfn.XLOOKUP(F5,'AUXILIAR SAP'!E:E,'AUXILIAR SAP'!D:D) -> CONTROLE_AV | J5: =IFERROR(_xlfn.XLOOKUP(F5,'AUXILIAR SAP'!J:J,'AUXILIAR SAP'!G:G),"-") -> CY2 | K5: =IFERROR(_xlfn.XLOOKUP(F5,'AUXILIAR SAP'!J:J,'AUXILIAR SAP'!I:I),"-") -> REN_CONTROLE_AV | L5: CONTROLE ALTO VALOR | M5: Alteração de nomenclatura 26/03/26
A6: SMARTPHONE_SMARTWATCH | B6: Disponível para ALTA/MIGRAÇÃO | C6: VIVO CONTROLE MÚSICA 20GB | D6: - | E6: NEXT | F6: CONTROLE ALTO VALOR | G6: 44640559 | H6: =_xlfn.XLOOKUP(F6,'AUXILIAR SAP'!E:E,'AUXILIAR SAP'!B:B) -> CU6 | I6: =_xlfn.XLOOKUP(F6,'AUXILIAR SAP'!E:E,'AUXILIAR SAP'!D:D) -> CONTROLE_AV | J6: =IFERROR(_xlfn.XLOOKUP(F6,'AUXILIAR SAP'!J:J,'AUXILIAR SAP'!G:G),"-") -> CY2 | K6: =IFERROR(_xlfn.XLOOKUP(F6,'AUXILIAR SAP'!J:J,'AUXILIAR SAP'!I:I),"-") -> REN_CONTROLE_AV | L6: CONTROLE ALTO VALOR | M6: Alteração de nomenclatura 26/03/26
A7: SMARTPHONE_SMARTWATCH | B7: Disponível para ALTA/MIGRAÇÃO | C7: VIVO CONTROLE 20GB PLN | D7: - | E7: NEXT | F7: CONTROLE ALTO VALOR | G7: 44640569 | H7: =_xlfn.XLOOKUP(F7,'AUXILIAR SAP'!E:E,'AUXILIAR SAP'!B:B) -> CU6 | I7: =_xlfn.XLOOKUP(F7,'AUXILIAR SAP'!E:E,'AUXILIAR SAP'!D:D) -> CONTROLE_AV | J7: =IFERROR(_xlfn.XLOOKUP(F7,'AUXILIAR SAP'!J:J,'AUXILIAR SAP'!G:G),"-") -> CY2 | K7: =IFERROR(_xlfn.XLOOKUP(F7,'AUXILIAR SAP'!J:J,'AUXILIAR SAP'!I:I),"-") -> REN_CONTROLE_AV | L7: CONTROLE ALTO VALOR | M7: Alteração de nomenclatura 26/03/26
A8: SMARTPHONE_SMARTWATCH | B8: Não disponível para ALTA/MIGRAÇÃO | C8: VIVO CONTROLE 9GB II | D8: - | E8: NEXT | F8: CONTROLE BTL | G8: 105008282 | H8: =_xlfn.XLOOKUP(F8,'AUXILIAR SAP'!E:E,'AUXILIAR SAP'!B:B) -> ZF4 | I8: =_xlfn.XLOOKUP(F8,'AUXILIAR SAP'!E:E,'AUXILIAR SAP'!D:D) -> CONTROLE_BTL | J8: =IFERROR(_xlfn.XLOOKUP(F8,'AUXILIAR SAP'!J:J,'AUXILIAR SAP'!G:G),"-") -> ZF7 | K8: =IFERROR(_xlfn.XLOOKUP(F8,'AUXILIAR SAP'!J:J,'AUXILIAR SAP'!I:I),"-") -> REN_CONTROLE_BTL | L8: PRÉ | M8: Alteração de nomenclatura 26/03/26
A9: SMARTPHONE_SMARTWATCH | B9: Não disponível para ALTA/MIGRAÇÃO | C9: VIVO CONTROLE 6GB II | D9: - | E9: NEXT | F9: CONTROLE BTL | G9: 483298854 | H9: =_xlfn.XLOOKUP(F9,'AUXILIAR SAP'!E:E,'AUXILIAR SAP'!B:B) -> ZF4 | I9: =_xlfn.XLOOKUP(F9,'AUXILIAR SAP'!E:E,'AUXILIAR SAP'!D:D) -> CONTROLE_BTL | J9: =IFERROR(_xlfn.XLOOKUP(F9,'AUXILIAR SAP'!J:J,'AUXILIAR SAP'!G:G),"-") -> ZF7 | K9: =IFERROR(_xlfn.XLOOKUP(F9,'AUXILIAR SAP'!J:J,'AUXILIAR SAP'!I:I),"-") -> REN_CONTROLE_BTL | L9: PRÉ | M9: Alteração de nome do Grupamento 28/08
A10: SMARTPHONE_SMARTWATCH | B10: Não disponível para ALTA/MIGRAÇÃO | C10: VIVO CONTROLE 7GB III | D10: - | E10: NEXT | F10: CONTROLE BTL | G10: 483298914 | H10: =_xlfn.XLOOKUP(F10,'AUXILIAR SAP'!E:E,'AUXILIAR SAP'!B:B) -> ZF4 | I10: =_xlfn.XLOOKUP(F10,'AUXILIAR SAP'!E:E,'AUXILIAR SAP'!D:D) -> CONTROLE_BTL | J10: =IFERROR(_xlfn.XLOOKUP(F10,'AUXILIAR SAP'!J:J,'AUXILIAR SAP'!G:G),"-") -> ZF7 | K10: =IFERROR(_xlfn.XLOOKUP(F10,'AUXILIAR SAP'!J:J,'AUXILIAR SAP'!I:I),"-") -> REN_CONTROLE_BTL | L10: PRÉ | M10: Alteração de nome do Grupamento 28/08
A11: SMARTPHONE_SMARTWATCH | B11: Não disponível para ALTA/MIGRAÇÃO | C11: VIVO CONTROLE 6GB V | D11: - | E11: NEXT | F11: CONTROLE BTL | G11: 483298864 | H11: =_xlfn.XLOOKUP(F11,'AUXILIAR SAP'!E:E,'AUXILIAR SAP'!B:B) -> ZF4 | I11: =_xlfn.XLOOKUP(F11,'AUXILIAR SAP'!E:E,'AUXILIAR SAP'!D:D) -> CONTROLE_BTL | J11: =IFERROR(_xlfn.XLOOKUP(F11,'AUXILIAR SAP'!J:J,'AUXILIAR SAP'!G:G),"-") -> ZF7 | K11: =IFERROR(_xlfn.XLOOKUP(F11,'AUXILIAR SAP'!J:J,'AUXILIAR SAP'!I:I),"-") -> REN_CONTROLE_BTL | L11: PRÉ | M11: Alteração de nome do Grupamento 28/08
A12: SMARTPHONE_SMARTWATCH | B12: Não disponível para ALTA/MIGRAÇÃO | C12: VIVO CONTROLE BÁSICO 13GB | D12: - | E12: NEXT | F12: CONTROLE BTL | G12: 484085673 | H12: =_xlfn.XLOOKUP(F12,'AUXILIAR SAP'!E:E,'AUXILIAR SAP'!B:B) -> ZF4 | I12: =_xlfn.XLOOKUP(F12,'AUXILIAR SAP'!E:E,'AUXILIAR SAP'!D:D) -> CONTROLE_BTL | J12: =IFERROR(_xlfn.XLOOKUP(F12,'AUXILIAR SAP'!J:J,'AUXILIAR SAP'!G:G),"-") -> ZF7 | K12: =IFERROR(_xlfn.XLOOKUP(F12,'AUXILIAR SAP'!J:J,'AUXILIAR SAP'!I:I),"-") -> REN_CONTROLE_BTL | L12: PRÉ | M12: Alteração de nomenclatura 26/03/26
A13: SMARTPHONE_SMARTWATCH | B13: Não disponível para ALTA/MIGRAÇÃO | C13: VIVO CONTROLE 10GB_V | D13: - | E13: NEXT | F13: CONTROLE ALTO VALOR | G13: 104564912 | H13: =_xlfn.XLOOKUP(F13,'AUXILIAR SAP'!E:E,'AUXILIAR SAP'!B:B) -> CU6 | I13: =_xlfn.XLOOKUP(F13,'AUXILIAR SAP'!E:E,'AUXILIAR SAP'!D:D) -> CONTROLE_AV | J13: =IFERROR(_xlfn.XLOOKUP(F13,'AUXILIAR SAP'!J:J,'AUXILIAR SAP'!G:G),"-") -> CY2 | K13: =IFERROR(_xlfn.XLOOKUP(F13,'AUXILIAR SAP'!J:J,'AUXILIAR SAP'!I:I),"-") -> REN_CONTROLE_AV | L13: CONTROLE ALTO VALOR | M13: Alteração de nomenclatura 26/03/26
... A19: SMARTPHONE_SMARTWATCH | B19: Não disponível para ALTA/MIGRAÇÃO | C19: VIVO CONTROLE 8GB | D19: - | E19: NEXT | F19: CONTROLE ENTRADA | G19: 435224237 | H19: =_xlfn.XLOOKUP(F19,'AUXILIAR SAP'!E:E,'AUXILIAR SAP'!B:B) -> BC4 | I19: =_xlfn.XLOOKUP(F19,'AUXILIAR SAP'!E:E,'AUXILIAR SAP'!D:D) -> CONTROLE_ENT | J19: =IFERROR(_xlfn.XLOOKUP(F19,'AUXILIAR SAP'!J:J,'AUXILIAR SAP'!G:G),"-") -> BE4 | K19: =IFERROR(_xlfn.XLOOKUP(F19,'AUXILIAR SAP'!J:J,'AUXILIAR SAP'!I:I),"-") -> REN_CONTROLE_ENT | L19: CONTROLE ENTRADA | M19: Alteração de grupamento
A20: SMARTPHONE_SMARTWATCH | B20: Não disponível para ALTA/MIGRAÇÃO | C20: VIVO CTRL NOVO 14GB | D20: - | E20: NEXT | F20: CONTROLE ALTO VALOR | G20: 104564922 | H20: =_xlfn.XLOOKUP(F20,'AUXILIAR SAP'!E:E,'AUXILIAR SAP'!B:B) -> CU6 | I20: =_xlfn.XLOOKUP(F20,'AUXILIAR SAP'!E:E,'AUXILIAR SAP'!D:D) -> CONTROLE_AV | J20: =IFERROR(_xlfn.XLOOKUP(F20,'AUXILIAR SAP'!J:J,'AUXILIAR SAP'!G:G),"-") -> CY2 | K20: =IFERROR(_xlfn.XLOOKUP(F20,'AUXILIAR SAP'!J:J,'AUXILIAR SAP'!I:I),"-") -> REN_CONTROLE_AV | L20: CONTROLE ALTO VALOR
A21: SMARTPHONE_SMARTWATCH | B21: Não disponível para ALTA/MIGRAÇÃO | C21: VIVO CONTROLE 6GB VIII | D21: - | E21: NEXT | F21: CONTROLE BTL | G21: 483298904 | H21: =_xlfn.XLOOKUP(F21,'AUXILIAR SAP'!E:E,'AUXILIAR SAP'!B:B) -> ZF4 | I21: =_xlfn.XLOOKUP(F21,'AUXILIAR SAP'!E:E,'AUXILIAR SAP'!D:D) -> CONTROLE_BTL | J21: =IFERROR(_xlfn.XLOOKUP(F21,'AUXILIAR SAP'!J:J,'AUXILIAR SAP'!G:G),"-") -> ZF7 | K21: =IFERROR(_xlfn.XLOOKUP(F21,'AUXILIAR SAP'!J:J,'AUXILIAR SAP'!I:I),"-") -> REN_CONTROLE_BTL | L21: PRÉ | M21: Alteração de nome do Grupamento 28/08
A22: SMARTPHONE_SMARTWATCH | B22: Não disponível para ALTA/MIGRAÇÃO | C22: VIVO CONTROLE 14GB I | D22: - | E22: NEXT | F22: CONTROLE ALTO VALOR | G22: 104564932 | H22: =_xlfn.XLOOKUP(F22,'AUXILIAR SAP'!E:E,'AUXILIAR SAP'!B:B) -> CU6 | I22: =_xlfn.XLOOKUP(F22,'AUXILIAR SAP'!E:E,'AUXILIAR SAP'!D:D) -> CONTROLE_AV | J22: =IFERROR(_xlfn.XLOOKUP(F22,'AUXILIAR SAP'!J:J,'AUXILIAR SAP'!G:G),"-") -> CY2 | K22: =IFERROR(_xlfn.XLOOKUP(F22,'AUXILIAR SAP'!J:J,'AUXILIAR SAP'!I:I),"-") -> REN_CONTROLE_AV | L22: CONTROLE ALTO VALOR
A23: SMARTPHONE_SMARTWATCH | B23: Não disponível para ALTA/MIGRAÇÃO | C23: VIVO CONTROLE 7GB V | D23: - | E23: NEXT | F23: CONTROLE BTL | G23: 434823532 | H23: =_xlfn.XLOOKUP(F23,'AUXILIAR SAP'!E:E,'AUXILIAR SAP'!B:B) -> ZF4 | I23: =_xlfn.XLOOKUP(F23,'AUXILIAR SAP'!E:E,'AUXILIAR SAP'!D:D) -> CONTROLE_BTL | J23: =IFERROR(_xlfn.XLOOKUP(F23,'AUXILIAR SAP'!J:J,'AUXILIAR SAP'!G:G),"-") -> ZF7 | K23: =IFERROR(_xlfn.XLOOKUP(F23,'AUXILIAR SAP'!J:J,'AUXILIAR SAP'!I:I),"-") -> REN_CONTROLE_BTL | L23: PRÉ | M23: Alteração de nome do Grupamento 28/08
A24: SMARTPHONE_SMARTWATCH | B24: Não disponível para ALTA/MIGRAÇÃO | C24: VIVO CONTROLE BÁSICO 15GB | D24: - | E24: NEXT | F24: CONTROLE BTL | G24: 484085683 | H24: =_xlfn.XLOOKUP(F24,'AUXILIAR SAP'!E:E,'AUXILIAR SAP'!B:B) -> ZF4 | I24: =_xlfn.XLOOKUP(F24,'AUXILIAR SAP'!E:E,'AUXILIAR SAP'!D:D) -> CONTROLE_BTL | J24: =IFERROR(_xlfn.XLOOKUP(F24,'AUXILIAR SAP'!J:J,'AUXILIAR SAP'!G:G),"-") -> ZF7 | K24: =IFERROR(_xlfn.XLOOKUP(F24,'AUXILIAR SAP'!J:J,'AUXILIAR SAP'!I:I),"-") -> REN_CONTROLE_BTL | L24: PRÉ | M24: Alteração de nomenclatura 26/03/26
A25: SMARTPHONE_SMARTWATCH | B25: Não disponível para ALTA/MIGRAÇÃO | C25: VIVO CONTROLE 9GB - 25MIN_ | D25: - | E25: NEXT | F25: CONTROLE ENTRADA | G25: 434823522 | H25: =_xlfn.XLOOKUP(F25,'AUXILIAR SAP'!E:E,'AUXILIAR SAP'!B:B) -> BC4 | I25: =_xlfn.XLOOKUP(F25,'AUXILIAR SAP'!E:E,'AUXILIAR SAP'!D:D) -> CONTROLE_ENT | J25: =IFERROR(_xlfn.XLOOKUP(F25,'AUXILIAR SAP'!J:J,'AUXILIAR SAP'!G:G),"-") -> BE4 | K25: =IFERROR(_xlfn.XLOOKUP(F25,'AUXILIAR SAP'!J:J,'AUXILIAR SAP'!I:I),"-") -> REN_CONTROLE_ENT | L25: CONTROLE ENTRADA | M25: Alteração de grupamento
A26: SMARTPHONE_SMARTWATCH | B26: Não disponível para ALTA/MIGRAÇÃO | C26: VIVO CONTROLE 14GB XI | D26: - | E26: NEXT | F26: CONTROLE ENTRADA | G26: 104285068 | H26: =_xlfn.XLOOKUP(F26,'AUXILIAR SAP'!E:E,'AUXILIAR SAP'!B:B) -> BC4 | I26: =_xlfn.XLOOKUP(F26,'AUXILIAR SAP'!E:E,'AUXILIAR SAP'!D:D) -> CONTROLE_ENT | J26: =IFERROR(_xlfn.XLOOKUP(F26,'AUXILIAR SAP'!J:J,'AUXILIAR SAP'!G:G),"-") -> BE4 | K26: =IFERROR(_xlfn.XLOOKUP(F26,'AUXILIAR SAP'!J:J,'AUXILIAR SAP'!I:I),"-") -> REN_CONTROLE_ENT | L26: CONTROLE ENTRADA | M26: Alteração de nomenclatura 26/03/26
A27: SMARTPHONE_SMARTWATCH | B27: Não disponível para ALTA/MIGRAÇÃO | C27: VIVO CONTROLE 7GB VII | D27: - | E27: NEXT | F27: CONTROLE BTL | G27: 434823542 | H27: =_xlfn.XLOOKUP(F27,'AUXILIAR SAP'!E:E,'AUXILIAR SAP'!B:B) -> ZF4 | I27: =_xlfn.XLOOKUP(F27,'AUXILIAR SAP'!E:E,'AUXILIAR SAP'!D:D) -> CONTROLE_BTL | J27: =IFERROR(_xlfn.XLOOKUP(F27,'AUXILIAR SAP'!J:J,'AUXILIAR SAP'!G:G),"-") -> ZF7 | K27: =IFERROR(_xlfn.XLOOKUP(F27,'AUXILIAR SAP'!J:J,'AUXILIAR SAP'!I:I),"-") -> REN_CONTROLE_BTL | L27: PRÉ | M27: Alteração de nome do Grupamento 28/08
A28: SMARTPHONE_SMARTWATCH | B28: Não disponível para ALTA/MIGRAÇÃO | C28: VIVO CONTROLE 7GB VI | D28: - | E28: NEXT | F28: CONTROLE BTL | G28: 434823552 | H28: =_xlfn.XLOOKUP(F28,'AUXILIAR SAP'!E:E,'AUXILIAR SAP'!B:B) -> ZF4 | I28: =_xlfn.XLOOKUP(F28,'AUXILIAR SAP'!E:E,'AUXILIAR SAP'!D:D) -> CONTROLE_BTL | J28: =IFERROR(_xlfn.XLOOKUP(F28,'AUXILIAR SAP'!J:J,'AUXILIAR SAP'!G:G),"-") -> ZF7 | K28: =IFERROR(_xlfn.XLOOKUP(F28,'AUXILIAR SAP'!J:J,'AUXILIAR SAP'!I:I),"-") -> REN_CONTROLE_BTL | L28: PRÉ | M28: Alteração de nome do Grupamento 28/08
A29: SMARTPHONE_SMARTWATCH | B29: Não disponível para ALTA/MIGRAÇÃO | C29: VIVO CONTROLE 10GB VII | D29: - | E29: NEXT | F29: CONTROLE ALTO VALOR | G29: 104285088 | H29: =_xlfn.XLOOKUP(F29,'AUXILIAR SAP'!E:E,'AUXILIAR SAP'!B:B) -> CU6 | I29: =_xlfn.XLOOKUP(F29,'AUXILIAR SAP'!E:E,'AUXILIAR SAP'!D:D) -> CONTROLE_AV | J29: =IFERROR(_xlfn.XLOOKUP(F29,'AUXILIAR SAP'!J:J,'AUXILIAR SAP'!G:G),"-") -> CY2 | K29: =IFERROR(_xlfn.XLOOKUP(F29,'AUXILIAR SAP'!J:J,'AUXILIAR SAP'!I:I),"-") -> REN_CONTROLE_AV | L29: CONTROLE ALTO VALOR | M29: Alteração de grupamento
A30: SMARTPHONE_SMARTWATCH | B30: Não disponível para ALTA/MIGRAÇÃO | C30: VIVO CONTROLE 14GB IV | D30: - | E30: NEXT | F30: CONTROLE ALTO VALOR | G30: 104285098 | H30: =_xlfn.XLOOKUP(F30,'AUXILIAR SAP'!E:E,'AUXILIAR SAP'!B:B) -> CU6 | I30: =_xlfn.XLOOKUP(F30,'AUXILIAR SAP'!E:E,'AUXILIAR SAP'!D:D) -> CONTROLE_AV | J30: =IFERROR(_xlfn.XLOOKUP(F30,'AUXILIAR SAP'!J:J,'AUXILIAR SAP'!G:G),"-") -> CY2 | K30: =IFERROR(_xlfn.XLOOKUP(F30,'AUXILIAR SAP'!J:J,'AUXILIAR SAP'!I:I),"-") -> REN_CONTROLE_AV | L30: CONTROLE ALTO VALOR
A31: SMARTPHONE_SMARTWATCH | B31: Disponível para ALTA | C31: VIVO CONTROLE 16GB X | D31: - | E31: NEXT | F31: CONTROLE ALTO VALOR | G31: 104285078 | H31: =_xlfn.XLOOKUP(F31,'AUXILIAR SAP'!E:E,'AUXILIAR SAP'!B:B) -> CU6 | I31: =_xlfn.XLOOKUP(F31,'AUXILIAR SAP'!E:E,'AUXILIAR SAP'!D:D) -> CONTROLE_AV | J31: =IFERROR(_xlfn.XLOOKUP(F31,'AUXILIAR SAP'!J:J,'AUXILIAR SAP'!G:G),"-") -> CY2 | K31: =IFERROR(_xlfn.XLOOKUP(F31,'AUXILIAR SAP'!J:J,'AUXILIAR SAP'!I:I),"-") -> REN_CONTROLE_AV | L31: CONTROLE ALTO VALOR | M31: Alteração de nomenclatura 26/03/26
A32: SMARTPHONE_SMARTWATCH | B32: Não disponível para ALTA/MIGRAÇÃO | C32: VIVO CONTROLE 10GB VIII | D32: - | E32: NEXT | F32: CONTROLE ALTO VALOR | G32: 435224247 | H32: =_xlfn.XLOOKUP(F32,'AUXILIAR SAP'!E:E,'AUXILIAR SAP'!B:B) -> CU6 | I32: =_xlfn.XLOOKUP(F32,'AUXILIAR SAP'!E:E,'AUXILIAR SAP'!D:D) -> CONTROLE_AV | J32: =IFERROR(_xlfn.XLOOKUP(F32,'AUXILIAR SAP'!J:J,'AUXILIAR SAP'!G:G),"-") -> CY2 | K32: =IFERROR(_xlfn.XLOOKUP(F32,'AUXILIAR SAP'!J:J,'AUXILIAR SAP'!I:I),"-") -> REN_CONTROLE_AV | L32: CONTROLE ALTO VALOR | M32: Alteração de grupamento
A33: SMARTPHONE_SMARTWATCH | B33: Não disponível para ALTA/MIGRAÇÃO | C33: VIVO CONTROLE 10GB III | D33: - | E33: NEXT | F33: CONTROLE BTL | G33: 105008302 | H33: =_xlfn.XLOOKUP(F33,'AUXILIAR SAP'!E:E,'AUXILIAR SAP'!B:B) -> ZF4 | I33: =_xlfn.XLOOKUP(F33,'AUXILIAR SAP'!E:E,'AUXILIAR SAP'!D:D) -> CONTROLE_BTL | J33: =IFERROR(_xlfn.XLOOKUP(F33,'AUXILIAR SAP'!J:J,'AUXILIAR SAP'!G:G),"-") -> ZF7 | K33: =IFERROR(_xlfn.XLOOKUP(F33,'AUXILIAR SAP'!J:J,'AUXILIAR SAP'!I:I),"-") -> REN_CONTROLE_BTL | L33: PRÉ | M33: Alteração de nomenclatura 26/03/26
A34: SMARTPHONE_SMARTWATCH | B34: Disponível para ALTA/MIGRAÇÃO | C34: TITULAR VIVO POS ESSENCIAL 40GB PLN | D34: - | E34: NEXT | F34: PÓS INDIVIDUAL | G34: 104375982 | H34: =_xlfn.XLOOKUP(F34,'AUXILIAR SAP'!E:E,'AUXILIAR SAP'!B:B) -> ZF2 | I34: =_xlfn.XLOOKUP(F34,'AUXILIAR SAP'!E:E,'AUXILIAR SAP'!D:D) -> PÓS_IND | J34: =IFERROR(_xlfn.XLOOKUP(F34,'AUXILIAR SAP'!J:J,'AUXILIAR SAP'!G:G),"-") -> ZF5 | K34: =IFERROR(_xlfn.XLOOKUP(F34,'AUXILIAR SAP'!J:J,'AUXILIAR SAP'!I:I),"-") -> REN_PÓS_IND | L34: PÓS INDIVIDUAL | M34: Alteração do Plano
A35: SMARTPHONE_SMARTWATCH | B35: Não disponível para ALTA/MIGRAÇÃO | C35: TITULAR VIVO PÓS 35GB II PLN | D35: - | E35: NEXT | F35: PÓS INDIVIDUAL | G35: 104376112 | H35: =_xlfn.XLOOKUP(F35,'AUXILIAR SAP'!E:E,'AUXILIAR SAP'!B:B) -> ZF2 | I35: =_xlfn.XLOOKUP(F35,'AUXILIAR SAP'!E:E,'AUXILIAR SAP'!D:D) -> PÓS_IND | J35: =IFERROR(_xlfn.XLOOKUP(F35,'AUXILIAR SAP'!J:J,'AUXILIAR SAP'!G:G),"-") -> ZF5 | K35: =IFERROR(_xlfn.XLOOKUP(F35,'AUXILIAR SAP'!J:J,'AUXILIAR SAP'!I:I),"-") -> REN_PÓS_IND | L35: PÓS INDIVIDUAL | M35: Alteração de nomenclatura 26/03/26
A36: SMARTPHONE_SMARTWATCH | B36: Não disponível para ALTA/MIGRAÇÃO | C36: TITULAR VIVO PÓS_40GB | D36: - | E36: NEXT | F36: PÓS INDIVIDUAL | G36: 104376172 | H36: =_xlfn.XLOOKUP(F36,'AUXILIAR SAP'!E:E,'AUXILIAR SAP'!B:B) -> ZF2 | I36: =_xlfn.XLOOKUP(F36,'AUXILIAR SAP'!E:E,'AUXILIAR SAP'!D:D) -> PÓS_IND | J36: =IFERROR(_xlfn.XLOOKUP(F36,'AUXILIAR SAP'!J:J,'AUXILIAR SAP'!G:G),"-") -> ZF5 | K36: =IFERROR(_xlfn.XLOOKUP(F36,'AUXILIAR SAP'!J:J,'AUXILIAR SAP'!I:I),"-") -> REN_PÓS_IND | L36: PÓS INDIVIDUAL | M36: Alteração de nomenclatura 26/03/26
A37: SMARTPHONE_SMARTWATCH | B37: Disponível para ALTA/MIGRAÇÃO | C37: TITULAR VIVO PÓS 35GB PLN | D37: - | E37: NEXT | F37: PÓS INDIVIDUAL | G37: 104376022 | H37: =_xlfn.XLOOKUP(F37,'AUXILIAR SAP'!E:E,'AUXILIAR SAP'!B:B) -> ZF2 | I37: =_xlfn.XLOOKUP(F37,'AUXILIAR SAP'!E:E,'AUXILIAR SAP'!D:D) -> PÓS_IND | J37: =IFERROR(_xlfn.XLOOKUP(F37,'AUXILIAR SAP'!J:J,'AUXILIAR SAP'!G:G),"-") -> ZF5 | K37: =IFERROR(_xlfn.XLOOKUP(F37,'AUXILIAR SAP'!J:J,'AUXILIAR SAP'!I:I),"-") -> REN_PÓS_IND | L37: PÓS INDIVIDUAL | M37: Alteração de nomenclatura 26/03/26
A38: SMARTPHONE_SMARTWATCH | B38: Não disponível para ALTA/MIGRAÇÃO | C38: TITULAR VIVO PÓS 35GB+ | D38: - | E38: NEXT | F38: PÓS INDIVIDUAL | G38: 104330938 | H38: =_xlfn.XLOOKUP(F38,'AUXILIAR SAP'!E:E,'AUXILIAR SAP'!B:B) -> ZF2 | I38: =_xlfn.XLOOKUP(F38,'AUXILIAR SAP'!E:E,'AUXILIAR SAP'!D:D) -> PÓS_IND | J38: =IFERROR(_xlfn.XLOOKUP(F38,'AUXILIAR SAP'!J:J,'AUXILIAR SAP'!G:G),"-") -> ZF5 | K38: =IFERROR(_xlfn.XLOOKUP(F38,'AUXILIAR SAP'!J:J,'AUXILIAR SAP'!I:I),"-") -> REN_PÓS_IND | L38: PÓS INDIVIDUAL | M38: Alteração de nomenclatura 26/03/26
A39: SMARTPHONE_SMARTWATCH | B39: Não disponível para ALTA/MIGRAÇÃO | C39: TITULAR VIVO PÓS 60GB | D39: - | E39: NEXT | F39: PÓS INDIVIDUAL | G39: 104376212 | H39: =_xlfn.XLOOKUP(F39,'AUXILIAR SAP'!E:E,'AUXILIAR SAP'!B:B) -> ZF2 | I39: =_xlfn.XLOOKUP(F39,'AUXILIAR SAP'!E:E,'AUXILIAR SAP'!D:D) -> PÓS_IND | J39: =IFERROR(_xlfn.XLOOKUP(F39,'AUXILIAR SAP'!J:J,'AUXILIAR SAP'!G:G),"-") -> ZF5 | K39: =IFERROR(_xlfn.XLOOKUP(F39,'AUXILIAR SAP'!J:J,'AUXILIAR SAP'!I:I),"-") -> REN_PÓS_IND | L39: PÓS INDIVIDUAL | M39: Alteração de nomenclatura 26/03/26
A40: SMARTPHONE_SMARTWATCH | B40: Disponível para ALTA/MIGRAÇÃO | C40: TITULAR VIVO POS TRAVEL 60GB PLN | D40: - | E40: NEXT | F40: PÓS INDIVIDUAL | G40: 104376062 | H40: =_xlfn.XLOOKUP(F40,'AUXILIAR SAP'!E:E,'AUXILIAR SAP'!B:B) -> ZF2 | I40: =_xlfn.XLOOKUP(F40,'AUXILIAR SAP'!E:E,'AUXILIAR SAP'!D:D) -> PÓS_IND | J40: =IFERROR(_xlfn.XLOOKUP(F40,'AUXILIAR SAP'!J:J,'AUXILIAR SAP'!G:G),"-") -> ZF5 | K40: =IFERROR(_xlfn.XLOOKUP(F40,'AUXILIAR SAP'!J:J,'AUXILIAR SAP'!I:I),"-") -> REN_PÓS_IND | L40: PÓS INDIVIDUAL | M40: Alteração do Plano 22/08
A41: SMARTPHONE_SMARTWATCH | B41: Não disponível para ALTA/MIGRAÇÃO | C41: TITULAR VIVO PÓS 60GB PLN | D41: - | E41: NEXT | F41: PÓS INDIVIDUAL | G41: 104376192 | H41: =_xlfn.XLOOKUP(F41,'AUXILIAR SAP'!E:E,'AUXILIAR SAP'!B:B) -> ZF2 | I41: =_xlfn.XLOOKUP(F41,'AUXILIAR SAP'!E:E,'AUXILIAR SAP'!D:D) -> PÓS_IND | J41: =IFERROR(_xlfn.XLOOKUP(F41,'AUXILIAR SAP'!J:J,'AUXILIAR SAP'!G:G),"-") -> ZF5 | K41: =IFERROR(_xlfn.XLOOKUP(F41,'AUXILIAR SAP'!J:J,'AUXILIAR SAP'!I:I),"-") -> REN_PÓS_IND | L41: PÓS INDIVIDUAL | M41: Alteração de nomenclatura 26/03/26
A42: SMARTPHONE_SMARTWATCH | B42: Não disponível para ALTA/MIGRAÇÃO | C42: TITULAR VIVO FAMÍLIA 105GB I | D42: - | E42: NEXT | F42: FAMILIA 3 | G42: 483901419 | H42: =_xlfn.XLOOKUP(F42,'AUXILIAR SAP'!E:E,'AUXILIAR SAP'!B:B) -> CU9 | I42: =_xlfn.XLOOKUP(F42,'AUXILIAR SAP'!E:E,'AUXILIAR SAP'!D:D) -> FAM_3 | J42: =IFERROR(_xlfn.XLOOKUP(F42,'AUXILIAR SAP'!J:J,'AUXILIAR SAP'!G:G),"-") -> CY5 | K42: =IFERROR(_xlfn.XLOOKUP(F42,'AUXILIAR SAP'!J:J,'AUXILIAR SAP'!I:I),"-") -> REN_FAM_3 | L42: FAMILIA 2 | M42: Alteração de nomenclatura 26/03/26
... A53: SMARTPHONE_SMARTWATCH | B53: Disponível para ALTA/MIGRAÇÃO | C53: TITULAR VIVO FAMÍLIA 205GB I PLN | D53: - | E53: NEXT | F53: FAMILIA 4/5 | G53: 104564642 | H53: =_xlfn.XLOOKUP(F53,'AUXILIAR SAP'!E:E,'AUXILIAR SAP'!B:B) -> CV2 | I53: =_xlfn.XLOOKUP(F53,'AUXILIAR SAP'!E:E,'AUXILIAR SAP'!D:D) -> FAM_4/5 | J53: =IFERROR(_xlfn.XLOOKUP(F53,'AUXILIAR SAP'!J:J,'AUXILIAR SAP'!G:G),"-") -> CY7 | K53: =IFERROR(_xlfn.XLOOKUP(F53,'AUXILIAR SAP'!J:J,'AUXILIAR SAP'!I:I),"-") -> REN_FAM_4/5 | L53: FAMILIA 4 | M53: Alteração de nomenclatura 26/03/26
A54: SMARTPHONE_SMARTWATCH | B54: Disponível para ALTA/MIGRAÇÃO | C54: TITULAR VIVO V PLN. | D54: - | E54: NEXT | F54: VIVO V | G54: 104564692 | H54: =_xlfn.XLOOKUP(F54,'AUXILIAR SAP'!E:E,'AUXILIAR SAP'!B:B) -> 28Y | I54: =_xlfn.XLOOKUP(F54,'AUXILIAR SAP'!E:E,'AUXILIAR SAP'!D:D) -> VIVO_V | J54: =IFERROR(_xlfn.XLOOKUP(F54,'AUXILIAR SAP'!J:J,'AUXILIAR SAP'!G:G),"-") -> 08Y | K54: =IFERROR(_xlfn.XLOOKUP(F54,'AUXILIAR SAP'!J:J,'AUXILIAR SAP'!I:I),"-") -> REN_VIVO_V | L54: VIVO V
A55: SMARTPHONE_SMARTWATCH | B55: Não disponível para ALTA/MIGRAÇÃO | C55: LINHA ADICIONAL VIVO FAMÍLIA 105GB I | D55: - | E55: NEXT | F55: CONTROLE ALTO VALOR | G55: 483907419 | H55: =_xlfn.XLOOKUP(F55,'AUXILIAR SAP'!E:E,'AUXILIAR SAP'!B:B) -> CU6 | I55: =_xlfn.XLOOKUP(F55,'AUXILIAR SAP'!E:E,'AUXILIAR SAP'!D:D) -> CONTROLE_AV | J55: =IFERROR(_xlfn.XLOOKUP(F55,'AUXILIAR SAP'!J:J,'AUXILIAR SAP'!G:G),"-") -> CY2 | K55: =IFERROR(_xlfn.XLOOKUP(F55,'AUXILIAR SAP'!J:J,'AUXILIAR SAP'!I:I),"-") -> REN_CONTROLE_AV | L55: CONTROLE ALTO VALOR | M55: Alteração de nomenclatura 26/03/26
A56: SMARTPHONE_SMARTWATCH | B56: Não disponível para ALTA/MIGRAÇÃO | C56: LINHA ADICIONAL VIVO FAMÍLIA 155GB I | D56: - | E56: NEXT | F56: PÓS INDIVIDUAL | G56: 483913419 | H56: =_xlfn.XLOOKUP(F56,'AUXILIAR SAP'!E:E,'AUXILIAR SAP'!B:B) -> ZF2 | I56: =_xlfn.XLOOKUP(F56,'AUXILIAR SAP'!E:E,'AUXILIAR SAP'!D:D) -> PÓS_IND | J56: =IFERROR(_xlfn.XLOOKUP(F56,'AUXILIAR SAP'!J:J,'AUXILIAR SAP'!G:G),"-") -> ZF5 | K56: =IFERROR(_xlfn.XLOOKUP(F56,'AUXILIAR SAP'!J:J,'AUXILIAR SAP'!I:I),"-") -> REN_PÓS_IND | L56: PÓS INDIVIDUAL | M56: Alteração de nomenclatura 26/03/26
A57: SMARTPHONE_SMARTWATCH | B57: Não disponível para ALTA/MIGRAÇÃO | C57: LINHA ADICIONAL VIVO FAMÍLIA 205GB | D57: - | E57: NEXT | F57: PÓS INDIVIDUAL | G57: 435110542 | H57: =_xlfn.XLOOKUP(F57,'AUXILIAR SAP'!E:E,'AUXILIAR SAP'!B:B) -> ZF2 | I57: =_xlfn.XLOOKUP(F57,'AUXILIAR SAP'!E:E,'AUXILIAR SAP'!D:D) -> PÓS_IND | J57: =IFERROR(_xlfn.XLOOKUP(F57,'AUXILIAR SAP'!J:J,'AUXILIAR SAP'!G:G),"-") -> ZF5 | K57: =IFERROR(_xlfn.XLOOKUP(F57,'AUXILIAR SAP'!J:J,'AUXILIAR SAP'!I:I),"-") -> REN_PÓS_IND | L57: PÓS INDIVIDUAL | M57: Alteração de nomenclatura 26/03/26
A58: SMARTPHONE_SMARTWATCH | B58: Não disponível para ALTA/MIGRAÇÃO | C58: LINHA ADICIONAL VIVO FAMÍLIA 205GB I | D58: - | E58: NEXT | F58: PÓS INDIVIDUAL | G58: 435110612 | H58: =_xlfn.XLOOKUP(F58,'AUXILIAR SAP'!E:E,'AUXILIAR SAP'!B:B) -> ZF2 | I58: =_xlfn.XLOOKUP(F58,'AUXILIAR SAP'!E:E,'AUXILIAR SAP'!D:D) -> PÓS_IND | J58: =IFERROR(_xlfn.XLOOKUP(F58,'AUXILIAR SAP'!J:J,'AUXILIAR SAP'!G:G),"-") -> ZF5 | K58: =IFERROR(_xlfn.XLOOKUP(F58,'AUXILIAR SAP'!J:J,'AUXILIAR SAP'!I:I),"-") -> REN_PÓS_IND | L58: PÓS INDIVIDUAL | M58: Alteração de nomenclatura 26/03/26
A59: SMARTPHONE_SMARTWATCH | B59: Não disponível para ALTA/MIGRAÇÃO | C59: LINHA ADICIONAL VIVO V | D59: - | E59: NEXT | F59: PÓS INDIVIDUAL | G59: 434625622 | H59: =_xlfn.XLOOKUP(F59,'AUXILIAR SAP'!E:E,'AUXILIAR SAP'!B:B) -> ZF2 | I59: =_xlfn.XLOOKUP(F59,'AUXILIAR SAP'!E:E,'AUXILIAR SAP'!D:D) -> PÓS_IND | J59: =IFERROR(_xlfn.XLOOKUP(F59,'AUXILIAR SAP'!J:J,'AUXILIAR SAP'!G:G),"-") -> ZF5 | K59: =IFERROR(_xlfn.XLOOKUP(F59,'AUXILIAR SAP'!J:J,'AUXILIAR SAP'!I:I),"-") -> REN_PÓS_IND | L59: PÓS INDIVIDUAL
A60: SMARTPHONE_SMARTWATCH | B60: Não disponível para ALTA/MIGRAÇÃO | C60: LINHA ADICIONAL VIVO PÓS 25GB PLN | D60: - | E60: NEXT | F60: CONTROLE ALTO VALOR | G60: 104376012 | H60: =_xlfn.XLOOKUP(F60,'AUXILIAR SAP'!E:E,'AUXILIAR SAP'!B:B) -> CU6 | I60: =_xlfn.XLOOKUP(F60,'AUXILIAR SAP'!E:E,'AUXILIAR SAP'!D:D) -> CONTROLE_AV | J60: =IFERROR(_xlfn.XLOOKUP(F60,'AUXILIAR SAP'!J:J,'AUXILIAR SAP'!G:G),"-") -> CY2 | K60: =IFERROR(_xlfn.XLOOKUP(F60,'AUXILIAR SAP'!J:J,'AUXILIAR SAP'!I:I),"-") -> REN_CONTROLE_AV | L60: CONTROLE ALTO VALOR | M60: Alteração de nomenclatura 26/03/26
A61: SMARTPHONE_SMARTWATCH | B61: Não disponível para ALTA/MIGRAÇÃO | C61: LINHA ADICIONAL VIVO PÓS 35GB | D61: - | E61: NEXT | F61: CONTROLE ALTO VALOR | G61: 104376052 | H61: =_xlfn.XLOOKUP(F61,'AUXILIAR SAP'!E:E,'AUXILIAR SAP'!B:B) -> CU6 | I61: =_xlfn.XLOOKUP(F61,'AUXILIAR SAP'!E:E,'AUXILIAR SAP'!D:D) -> CONTROLE_AV | J61: =IFERROR(_xlfn.XLOOKUP(F61,'AUXILIAR SAP'!J:J,'AUXILIAR SAP'!G:G),"-") -> CY2 | K61: =IFERROR(_xlfn.XLOOKUP(F61,'AUXILIAR SAP'!J:J,'AUXILIAR SAP'!I:I),"-") -> REN_CONTROLE_AV | L61: CONTROLE ALTO VALOR | M61: Alteração de nomenclatura 26/03/26
A62: SMARTPHONE_SMARTWATCH | B62: Não disponível para ALTA/MIGRAÇÃO | C62: LINHA ADICIONAL VIVO POS TRAVEL | D62: - | E62: NEXT | F62: CONTROLE ALTO VALOR | G62: 104376092 | H62: =_xlfn.XLOOKUP(F62,'AUXILIAR SAP'!E:E,'AUXILIAR SAP'!B:B) -> CU6 | I62: =_xlfn.XLOOKUP(F62,'AUXILIAR SAP'!E:E,'AUXILIAR SAP'!D:D) -> CONTROLE_AV | J62: =IFERROR(_xlfn.XLOOKUP(F62,'AUXILIAR SAP'!J:J,'AUXILIAR SAP'!G:G),"-") -> CY2 | K62: =IFERROR(_xlfn.XLOOKUP(F62,'AUXILIAR SAP'!J:J,'AUXILIAR SAP'!I:I),"-") -> REN_CONTROLE_AV | L62: CONTROLE ALTO VALOR | M62: Alteração do Plano 22/08
A63: SMARTPHONE_SMARTWATCH | B63: Não disponível para ALTA/MIGRAÇÃO | C63: LINHA ADICIONAL VIVO FAMÍLIA 65GB | D63: - | E63: NEXT | F63: CONTROLE ALTO VALOR | G63: 104375872 | H63: =_xlfn.XLOOKUP(F63,'AUXILIAR SAP'!E:E,'AUXILIAR SAP'!B:B) -> CU6 | I63: =_xlfn.XLOOKUP(F63,'AUXILIAR SAP'!E:E,'AUXILIAR SAP'!D:D) -> CONTROLE_AV | J63: =IFERROR(_xlfn.XLOOKUP(F63,'AUXILIAR SAP'!J:J,'AUXILIAR SAP'!G:G),"-") -> CY2 | K63: =IFERROR(_xlfn.XLOOKUP(F63,'AUXILIAR SAP'!J:J,'AUXILIAR SAP'!I:I),"-") -> REN_CONTROLE_AV | L63: CONTROLE ALTO VALOR | M63: Alteração de nomenclatura 26/03/26
A64: SMARTPHONE_SMARTWATCH | B64: Não disponível para ALTA/MIGRAÇÃO | C64: LINHA ADICIONAL VIVO FAMILIA 3 | D64: - | E64: NEXT | F64: CONTROLE ALTO VALOR | G64: 104375902 | H64: =_xlfn.XLOOKUP(F64,'AUXILIAR SAP'!E:E,'AUXILIAR SAP'!B:B) -> CU6 | I64: =_xlfn.XLOOKUP(F64,'AUXILIAR SAP'!E:E,'AUXILIAR SAP'!D:D) -> CONTROLE_AV | J64: =IFERROR(_xlfn.XLOOKUP(F64,'AUXILIAR SAP'!J:J,'AUXILIAR SAP'!G:G),"-") -> CY2 | K64: =IFERROR(_xlfn.XLOOKUP(F64,'AUXILIAR SAP'!J:J,'AUXILIAR SAP'!I:I),"-") -> REN_CONTROLE_AV | L64: CONTROLE ALTO VALOR | M64: Alteração do Plano 22/08
A65: SMARTPHONE_SMARTWATCH | B65: Não disponível para ALTA/MIGRAÇÃO | C65: LINHA ADICIONAL VIVO FAMILIA 4 | D65: - | E65: NEXT | F65: PÓS INDIVIDUAL | G65: 104375932 | H65: =_xlfn.XLOOKUP(F65,'AUXILIAR SAP'!E:E,'AUXILIAR SAP'!B:B) -> ZF2 | I65: =_xlfn.XLOOKUP(F65,'AUXILIAR SAP'!E:E,'AUXILIAR SAP'!D:D) -> PÓS_IND | J65: =IFERROR(_xlfn.XLOOKUP(F65,'AUXILIAR SAP'!J:J,'AUXILIAR SAP'!G:G),"-") -> ZF5 | K65: =IFERROR(_xlfn.XLOOKUP(F65,'AUXILIAR SAP'!J:J,'AUXILIAR SAP'!I:I),"-") -> REN_PÓS_IND | L65: PÓS INDIVIDUAL | M65: Alteração do Plano 22/08
A66: SMARTPHONE_SMARTWATCH | B66: Não disponível para ALTA/MIGRAÇÃO | C66: LINHA ADICIONAL VIVO FAMILIA 5 | D66: - | E66: NEXT | F66: PÓS INDIVIDUAL | G66: 104375962 | H66: =_xlfn.XLOOKUP(F66,'AUXILIAR SAP'!E:E,'AUXILIAR SAP'!B:B) -> ZF2 | I66: =_xlfn.XLOOKUP(F66,'AUXILIAR SAP'!E:E,'AUXILIAR SAP'!D:D) -> PÓS_IND | J66: =IFERROR(_xlfn.XLOOKUP(F66,'AUXILIAR SAP'!J:J,'AUXILIAR SAP'!G:G),"-") -> ZF5 | K66: =IFERROR(_xlfn.XLOOKUP(F66,'AUXILIAR SAP'!J:J,'AUXILIAR SAP'!I:I),"-") -> REN_PÓS_IND | L66: PÓS INDIVIDUAL | M66: Alteração do Plano 22/08
A67: SMARTPHONE_SMARTWATCH | B67: Não disponível para ALTA/MIGRAÇÃO | C67: LINHA ADICIONAL VIVO PÓS 35GB I | D67: - | E67: NEXT | F67: CONTROLE ALTO VALOR | G67: 104376122 | H67: =_xlfn.XLOOKUP(F67,'AUXILIAR SAP'!E:E,'AUXILIAR SAP'!B:B) -> CU6 | I67: =_xlfn.XLOOKUP(F67,'AUXILIAR SAP'!E:E,'AUXILIAR SAP'!D:D) -> CONTROLE_AV | J67: =IFERROR(_xlfn.XLOOKUP(F67,'AUXILIAR SAP'!J:J,'AUXILIAR SAP'!G:G),"-") -> CY2 | K67: =IFERROR(_xlfn.XLOOKUP(F67,'AUXILIAR SAP'!J:J,'AUXILIAR SAP'!I:I),"-") -> REN_CONTROLE_AV | L67: CONTROLE ALTO VALOR | M67: Alteração de nomenclatura 26/03/26
A68: SMARTPHONE_SMARTWATCH | B68: Não disponível para ALTA/MIGRAÇÃO | C68: LINHA ADICIONAL VIVO PÓS 40GB | D68: - | E68: NEXT | F68: CONTROLE ALTO VALOR | G68: 104376162 | H68: =_xlfn.XLOOKUP(F68,'AUXILIAR SAP'!E:E,'AUXILIAR SAP'!B:B) -> CU6 | I68: =_xlfn.XLOOKUP(F68,'AUXILIAR SAP'!E:E,'AUXILIAR SAP'!D:D) -> CONTROLE_AV | J68: =IFERROR(_xlfn.XLOOKUP(F68,'AUXILIAR SAP'!J:J,'AUXILIAR SAP'!G:G),"-") -> CY2 | K68: =IFERROR(_xlfn.XLOOKUP(F68,'AUXILIAR SAP'!J:J,'AUXILIAR SAP'!I:I),"-") -> REN_CONTROLE_AV | L68: CONTROLE ALTO VALOR | M68: Alteração de nomenclatura 26/03/26
A69: SMARTPHONE_SMARTWATCH | B69: Não disponível para ALTA/MIGRAÇÃO | C69: LINHA ADICIONAL VIVO PÓS 60GB | D69: - | E69: NEXT | F69: CONTROLE ALTO VALOR | G69: 104376202 | H69: =_xlfn.XLOOKUP(F69,'AUXILIAR SAP'!E:E,'AUXILIAR SAP'!B:B) -> CU6 | I69: =_xlfn.XLOOKUP(F69,'AUXILIAR SAP'!E:E,'AUXILIAR SAP'!D:D) -> CONTROLE_AV | J69: =IFERROR(_xlfn.XLOOKUP(F69,'AUXILIAR SAP'!J:J,'AUXILIAR SAP'!G:G),"-") -> CY2 | K69: =IFERROR(_xlfn.XLOOKUP(F69,'AUXILIAR SAP'!J:J,'AUXILIAR SAP'!I:I),"-") -> REN_CONTROLE_AV | L69: CONTROLE ALTO VALOR | M69: Alteração de nomenclatura 26/03/26
A70: SMARTPHONE_SMARTWATCH | B70: Não disponível para ALTA/MIGRAÇÃO | C70: TITULAR VIVO PÓS 35GB | D70: - | E70: NEXT | F70: PÓS INDIVIDUAL | G70: 104376042 | H70: =_xlfn.XLOOKUP(F70,'AUXILIAR SAP'!E:E,'AUXILIAR SAP'!B:B) -> ZF2 | I70: =_xlfn.XLOOKUP(F70,'AUXILIAR SAP'!E:E,'AUXILIAR SAP'!D:D) -> PÓS_IND | J70: =IFERROR(_xlfn.XLOOKUP(F70,'AUXILIAR SAP'!J:J,'AUXILIAR SAP'!G:G),"-") -> ZF5 | K70: =IFERROR(_xlfn.XLOOKUP(F70,'AUXILIAR SAP'!J:J,'AUXILIAR SAP'!I:I),"-") -> REN_PÓS_IND | L70: PÓS INDIVIDUAL | M70: Alteração de nomenclatura 26/03/26
A71: SMARTPHONE_SMARTWATCH | B71: Disponível para ALTA/MIGRAÇÃO | C71: VIVO POS TRAVEL 60GB | D71: - | E71: NEXT | F71: PÓS INDIVIDUAL | G71: 104376082 | H71: =_xlfn.XLOOKUP(F71,'AUXILIAR SAP'!E:E,'AUXILIAR SAP'!B:B) -> ZF2 | I71: =_xlfn.XLOOKUP(F71,'AUXILIAR SAP'!E:E,'AUXILIAR SAP'!D:D) -> PÓS_IND | J71: =IFERROR(_xlfn.XLOOKUP(F71,'AUXILIAR SAP'!J:J,'AUXILIAR SAP'!G:G),"-") -> ZF5 | K71: =IFERROR(_xlfn.XLOOKUP(F71,'AUXILIAR SAP'!J:J,'AUXILIAR SAP'!I:I),"-") -> REN_PÓS_IND | L71: PÓS INDIVIDUAL | M71: Alteração do Plano
... A75: SMARTPHONE_SMARTWATCH | B75: Disponível para ALTA/MIGRAÇÃO | C75: TITULAR VIVO FAMILIA 300GB | D75: - | E75: NEXT | F75: FAMILIA 4/5 | G75: 104375952 | H75: =_xlfn.XLOOKUP(F75,'AUXILIAR SAP'!E:E,'AUXILIAR SAP'!B:B) -> CV2 | I75: =_xlfn.XLOOKUP(F75,'AUXILIAR SAP'!E:E,'AUXILIAR SAP'!D:D) -> FAM_4/5 | J75: =IFERROR(_xlfn.XLOOKUP(F75,'AUXILIAR SAP'!J:J,'AUXILIAR SAP'!G:G),"-") -> CY7 | K75: =IFERROR(_xlfn.XLOOKUP(F75,'AUXILIAR SAP'!J:J,'AUXILIAR SAP'!I:I),"-") -> REN_FAM_4/5 | L75: FAMILIA 4 | M75: Alteração de nome do Grupamento 28/08
A76: SMARTPHONE_SMARTWATCH | B76: Disponível para ALTA/MIGRAÇÃO | C76: TITULAR VIVO V | D76: - | E76: NEXT | F76: VIVO V | G76: 101225942 | H76: =_xlfn.XLOOKUP(F76,'AUXILIAR SAP'!E:E,'AUXILIAR SAP'!B:B) -> 28Y | I76: =_xlfn.XLOOKUP(F76,'AUXILIAR SAP'!E:E,'AUXILIAR SAP'!D:D) -> VIVO_V | J76: =IFERROR(_xlfn.XLOOKUP(F76,'AUXILIAR SAP'!J:J,'AUXILIAR SAP'!G:G),"-") -> 08Y | K76: =IFERROR(_xlfn.XLOOKUP(F76,'AUXILIAR SAP'!J:J,'AUXILIAR SAP'!I:I),"-") -> REN_VIVO_V | L76: VIVO V
A77: TABLET_MODEM_BOX_FIXO | B77: Não disponível para ALTA/MIGRAÇÃO | C77: Tit Internet Móvel 1GB | D77: - | E77: NEXT | F77: PRÉ | G77: 79392 | H77: =_xlfn.XLOOKUP(F77,'AUXILIAR SAP'!E:E,'AUXILIAR SAP'!B:B) -> PPP | I77: =_xlfn.XLOOKUP(F77,'AUXILIAR SAP'!E:E,'AUXILIAR SAP'!D:D) -> PRE | J77: =IFERROR(_xlfn.XLOOKUP(F77,'AUXILIAR SAP'!J:J,'AUXILIAR SAP'!G:G),"-") -> - | K77: =IFERROR(_xlfn.XLOOKUP(F77,'AUXILIAR SAP'!J:J,'AUXILIAR SAP'!I:I),"-") -> - | L77: PRÉ
A78: TABLET_MODEM_BOX_FIXO | B78: Não disponível para ALTA/MIGRAÇÃO | C78: Tit Internet Móvel 2GB | D78: - | E78: NEXT | F78: PRÉ | G78: 79402 | H78: =_xlfn.XLOOKUP(F78,'AUXILIAR SAP'!E:E,'AUXILIAR SAP'!B:B) -> PPP | I78: =_xlfn.XLOOKUP(F78,'AUXILIAR SAP'!E:E,'AUXILIAR SAP'!D:D) -> PRE | J78: =IFERROR(_xlfn.XLOOKUP(F78,'AUXILIAR SAP'!J:J,'AUXILIAR SAP'!G:G),"-") -> - | K78: =IFERROR(_xlfn.XLOOKUP(F78,'AUXILIAR SAP'!J:J,'AUXILIAR SAP'!I:I),"-") -> - | L78: PRÉ
A79: TABLET_MODEM_BOX_FIXO | B79: Não disponível para ALTA/MIGRAÇÃO | C79: Linha Adicional Internet Móvel 1GB - Dados | D79: - | E79: NEXT | F79: PRÉ | G79: 434620712 | H79: =_xlfn.XLOOKUP(F79,'AUXILIAR SAP'!E:E,'AUXILIAR SAP'!B:B) -> PPP | I79: =_xlfn.XLOOKUP(F79,'AUXILIAR SAP'!E:E,'AUXILIAR SAP'!D:D) -> PRE | J79: =IFERROR(_xlfn.XLOOKUP(F79,'AUXILIAR SAP'!J:J,'AUXILIAR SAP'!G:G),"-") -> - | K79: =IFERROR(_xlfn.XLOOKUP(F79,'AUXILIAR SAP'!J:J,'AUXILIAR SAP'!I:I),"-") -> - | L79: PRÉ
A80: TABLET_MODEM_BOX_FIXO | B80: Não disponível para ALTA/MIGRAÇÃO | C80: Linha Adicional Internet Móvel 8GB - Dados | D80: - | E80: NEXT | F80: MULTIVIVO | G80: 434620742 | H80: =_xlfn.XLOOKUP(F80,'AUXILIAR SAP'!E:E,'AUXILIAR SAP'!B:B) -> KAU | I80: =_xlfn.XLOOKUP(F80,'AUXILIAR SAP'!E:E,'AUXILIAR SAP'!D:D) -> MULTIVIVO | J80: =IFERROR(_xlfn.XLOOKUP(F80,'AUXILIAR SAP'!J:J,'AUXILIAR SAP'!G:G),"-") -> - | K80: =IFERROR(_xlfn.XLOOKUP(F80,'AUXILIAR SAP'!J:J,'AUXILIAR SAP'!I:I),"-") -> - | L80: MULTIVIVO
A81: TABLET_MODEM_BOX_FIXO | B81: Não disponível para ALTA/MIGRAÇÃO | C81: Linha Adicional Internet Móvel 14GB - Dados | D81: - | E81: NEXT | F81: MULTIVIVO | G81: 434620752 | H81: =_xlfn.XLOOKUP(F81,'AUXILIAR SAP'!E:E,'AUXILIAR SAP'!B:B) -> KAU | I81: =_xlfn.XLOOKUP(F81,'AUXILIAR SAP'!E:E,'AUXILIAR SAP'!D:D) -> MULTIVIVO | J81: =IFERROR(_xlfn.XLOOKUP(F81,'AUXILIAR SAP'!J:J,'AUXILIAR SAP'!G:G),"-") -> - | K81: =IFERROR(_xlfn.XLOOKUP(F81,'AUXILIAR SAP'!J:J,'AUXILIAR SAP'!I:I),"-") -> - | L81: MULTIVIVO
A82: TABLET_MODEM_BOX_FIXO | B82: Não disponível para ALTA/MIGRAÇÃO | C82: Linha Adicional Internet Móvel 20GB - Dados | D82: - | E82: NEXT | F82: MULTIVIVO | G82: 434620702 | H82: =_xlfn.XLOOKUP(F82,'AUXILIAR SAP'!E:E,'AUXILIAR SAP'!B:B) -> KAU | I82: =_xlfn.XLOOKUP(F82,'AUXILIAR SAP'!E:E,'AUXILIAR SAP'!D:D) -> MULTIVIVO | J82: =IFERROR(_xlfn.XLOOKUP(F82,'AUXILIAR SAP'!J:J,'AUXILIAR SAP'!G:G),"-") -> - | K82: =IFERROR(_xlfn.XLOOKUP(F82,'AUXILIAR SAP'!J:J,'AUXILIAR SAP'!I:I),"-") -> - | L82: MULTIVIVO
A83: TABLET_MODEM_BOX_FIXO | B83: Não disponível para ALTA/MIGRAÇÃO | C83: Linha Adicional Internet Móvel 40GB - Dados | D83: - | E83: NEXT | F83: MULTIVIVO | G83: 434620732 | H83: =_xlfn.XLOOKUP(F83,'AUXILIAR SAP'!E:E,'AUXILIAR SAP'!B:B) -> KAU | I83: =_xlfn.XLOOKUP(F83,'AUXILIAR SAP'!E:E,'AUXILIAR SAP'!D:D) -> MULTIVIVO | J83: =IFERROR(_xlfn.XLOOKUP(F83,'AUXILIAR SAP'!J:J,'AUXILIAR SAP'!G:G),"-") -> - | K83: =IFERROR(_xlfn.XLOOKUP(F83,'AUXILIAR SAP'!J:J,'AUXILIAR SAP'!I:I),"-") -> - | L83: MULTIVIVO
A84: TABLET_MODEM_BOX_FIXO | B84: Não disponível para ALTA/MIGRAÇÃO | C84: LINHA ADICIONAL INTERNET_Móvel_100GB | D84: - | E84: NEXT | F84: MULTIVIVO | G84: 434893144 | H84: =_xlfn.XLOOKUP(F84,'AUXILIAR SAP'!E:E,'AUXILIAR SAP'!B:B) -> KAU | I84: =_xlfn.XLOOKUP(F84,'AUXILIAR SAP'!E:E,'AUXILIAR SAP'!D:D) -> MULTIVIVO | J84: =IFERROR(_xlfn.XLOOKUP(F84,'AUXILIAR SAP'!J:J,'AUXILIAR SAP'!G:G),"-") -> - | K84: =IFERROR(_xlfn.XLOOKUP(F84,'AUXILIAR SAP'!J:J,'AUXILIAR SAP'!I:I),"-") -> - | L84: MULTIVIVO
A85: TABLET_MODEM_BOX_FIXO | B85: Não disponível para ALTA/MIGRAÇÃO | C85: LINHA ADICIONAL INTERNET Móvel 100GB | D85: - | E85: NEXT | F85: MULTIVIVO | G85: 434893164 | H85: =_xlfn.XLOOKUP(F85,'AUXILIAR SAP'!E:E,'AUXILIAR SAP'!B:B) -> KAU | I85: =_xlfn.XLOOKUP(F85,'AUXILIAR SAP'!E:E,'AUXILIAR SAP'!D:D) -> MULTIVIVO | J85: =IFERROR(_xlfn.XLOOKUP(F85,'AUXILIAR SAP'!J:J,'AUXILIAR SAP'!G:G),"-") -> - | K85: =IFERROR(_xlfn.XLOOKUP(F85,'AUXILIAR SAP'!J:J,'AUXILIAR SAP'!I:I),"-") -> - | L85: MULTIVIVO
A86: TABLET_MODEM_BOX_FIXO | B86: Não disponível para ALTA/MIGRAÇÃO | C86: TIT INTERNET MÓVEL 13GB | D86: - | E86: NEXT | F86: VIM 8GB | G86: 197572 | H86: =_xlfn.XLOOKUP(F86,'AUXILIAR SAP'!E:E,'AUXILIAR SAP'!B:B) -> YAQ | I86: =_xlfn.XLOOKUP(F86,'AUXILIAR SAP'!E:E,'AUXILIAR SAP'!D:D) -> VIM_8GB | J86: =IFERROR(_xlfn.XLOOKUP(F86,'AUXILIAR SAP'!J:J,'AUXILIAR SAP'!G:G),"-") -> - | K86: =IFERROR(_xlfn.XLOOKUP(F86,'AUXILIAR SAP'!J:J,'AUXILIAR SAP'!I:I),"-") -> - | L86: VIM 8GB | M86: Alteração de nomenclatura 26/03/26
A87: TABLET_MODEM_BOX_FIXO | B87: Não disponível para ALTA/MIGRAÇÃO | C87: TIT INTERNET MÓVEL 19GB | D87: - | E87: NEXT | F87: VIM 14GB | G87: 197302 | H87: =_xlfn.XLOOKUP(F87,'AUXILIAR SAP'!E:E,'AUXILIAR SAP'!B:B) -> YAR | I87: =_xlfn.XLOOKUP(F87,'AUXILIAR SAP'!E:E,'AUXILIAR SAP'!D:D) -> VIM_14GB | J87: =IFERROR(_xlfn.XLOOKUP(F87,'AUXILIAR SAP'!J:J,'AUXILIAR SAP'!G:G),"-") -> - | K87: =IFERROR(_xlfn.XLOOKUP(F87,'AUXILIAR SAP'!J:J,'AUXILIAR SAP'!I:I),"-") -> - | L87: VIM 14GB | M87: Alteração de nomenclatura 26/03/26
A88: TABLET_MODEM_BOX_FIXO | B88: Não disponível para ALTA/MIGRAÇÃO | C88: TIT INTERNET MÓVEL 25GB | D88: - | E88: NEXT | F88: VIM 20GB | G88: 79432 | H88: =_xlfn.XLOOKUP(F88,'AUXILIAR SAP'!E:E,'AUXILIAR SAP'!B:B) -> YAS | I88: =_xlfn.XLOOKUP(F88,'AUXILIAR SAP'!E:E,'AUXILIAR SAP'!D:D) -> VIM_20GB | J88: =IFERROR(_xlfn.XLOOKUP(F88,'AUXILIAR SAP'!J:J,'AUXILIAR SAP'!G:G),"-") -> - | K88: =IFERROR(_xlfn.XLOOKUP(F88,'AUXILIAR SAP'!J:J,'AUXILIAR SAP'!I:I),"-") -> - | L88: VIM 20GB | M88: Alteração de nomenclatura 26/03/26
A89: TABLET_MODEM_BOX_FIXO | B89: Não disponível para ALTA/MIGRAÇÃO | C89: Tit Internet Móvel 40GB | D89: - | E89: NEXT | F89: VIM 40GB | G89: 79442 | H89: =_xlfn.XLOOKUP(F89,'AUXILIAR SAP'!E:E,'AUXILIAR SAP'!B:B) -> 85W | I89: =_xlfn.XLOOKUP(F89,'AUXILIAR SAP'!E:E,'AUXILIAR SAP'!D:D) -> VIM_40GB | J89: =IFERROR(_xlfn.XLOOKUP(F89,'AUXILIAR SAP'!J:J,'AUXILIAR SAP'!G:G),"-") -> - | K89: =IFERROR(_xlfn.XLOOKUP(F89,'AUXILIAR SAP'!J:J,'AUXILIAR SAP'!I:I),"-") -> - | L89: VIM 40GB
A90: TABLET_MODEM_BOX_FIXO | B90: Disponível para ALTA/MIGRAÇÃO | C90: Titular INTERNET_MOVEL_100GB | D90: - | E90: NEXT | F90: VIM 40GB | G90: 434893134 | H90: =_xlfn.XLOOKUP(F90,'AUXILIAR SAP'!E:E,'AUXILIAR SAP'!B:B) -> 85W | I90: =_xlfn.XLOOKUP(F90,'AUXILIAR SAP'!E:E,'AUXILIAR SAP'!D:D) -> VIM_40GB | J90: =IFERROR(_xlfn.XLOOKUP(F90,'AUXILIAR SAP'!J:J,'AUXILIAR SAP'!G:G),"-") -> - | K90: =IFERROR(_xlfn.XLOOKUP(F90,'AUXILIAR SAP'!J:J,'AUXILIAR SAP'!I:I),"-") -> - | L90: VIM 100GB | M90: Alteração de grupamento 03/02/26
A91: TABLET_MODEM_BOX_FIXO | B91: Disponível para ALTA/MIGRAÇÃO | C91: Titular INTERNET MOVEL 100GB | D91: - | E91: NEXT | F91: VIM 40GB | G91: 434893154 | H91: =_xlfn.XLOOKUP(F91,'AUXILIAR SAP'!E:E,'AUXILIAR SAP'!B:B) -> 85W | I91: =_xlfn.XLOOKUP(F91,'AUXILIAR SAP'!E:E,'AUXILIAR SAP'!D:D) -> VIM_40GB | J91: =IFERROR(_xlfn.XLOOKUP(F91,'AUXILIAR SAP'!J:J,'AUXILIAR SAP'!G:G),"-") -> - | K91: =IFERROR(_xlfn.XLOOKUP(F91,'AUXILIAR SAP'!J:J,'AUXILIAR SAP'!I:I),"-") -> - | L91: VIM 100GB | M91: Alteração de grupamento 03/02/26
A92: SMARTPHONE_SMARTWATCH | B92: Não disponível para ALTA/MIGRAÇÃO | C92: Tit SmartVivo V | D92: - | E92: NEXT | F92: PRÉ | G92: 79382 | H92: =_xlfn.XLOOKUP(F92,'AUXILIAR SAP'!E:E,'AUXILIAR SAP'!B:B) -> PPP | I92: =_xlfn.XLOOKUP(F92,'AUXILIAR SAP'!E:E,'AUXILIAR SAP'!D:D) -> PRE | J92: =IFERROR(_xlfn.XLOOKUP(F92,'AUXILIAR SAP'!J:J,'AUXILIAR SAP'!G:G),"-") -> - | K92: =IFERROR(_xlfn.XLOOKUP(F92,'AUXILIAR SAP'!J:J,'AUXILIAR SAP'!I:I),"-") -> - | L92: PRÉ
A93: SMARTPHONE_SMARTWATCH | B93: Não disponível para ALTA/MIGRAÇÃO | C93: TITULAR VIVO PÓS - 10GB. | D93: Vivo Total Básico | E93: NEXT | F93: CONTROLE ALTO VALOR | G93: 442435588 | H93: =_xlfn.XLOOKUP(F93,'AUXILIAR SAP'!E:E,'AUXILIAR SAP'!B:B) -> CU6 | I93: =_xlfn.XLOOKUP(F93,'AUXILIAR SAP'!E:E,'AUXILIAR SAP'!D:D) -> CONTROLE_AV | J93: =IFERROR(_xlfn.XLOOKUP(F93,'AUXILIAR SAP'!J:J,'AUXILIAR SAP'!G:G),"-") -> CY2 | K93: =IFERROR(_xlfn.XLOOKUP(F93,'AUXILIAR SAP'!J:J,'AUXILIAR SAP'!I:I),"-") -> REN_CONTROLE_AV | L93: CONTROLE ALTO VALOR | M93: Alteração do Plano
A94: SMARTPHONE_SMARTWATCH | B94: Não disponível para ALTA/MIGRAÇÃO | C94: LINHA ADICIONAL VIVO PÓS - 10GB | D94: Vivo Total Básico | E94: NEXT | F94: CONTROLE ALTO VALOR | G94: 442435598 | H94: =_xlfn.XLOOKUP(F94,'AUXILIAR SAP'!E:E,'AUXILIAR SAP'!B:B) -> CU6 | I94: =_xlfn.XLOOKUP(F94,'AUXILIAR SAP'!E:E,'AUXILIAR SAP'!D:D) -> CONTROLE_AV | J94: =IFERROR(_xlfn.XLOOKUP(F94,'AUXILIAR SAP'!J:J,'AUXILIAR SAP'!G:G),"-") -> CY2 | K94: =IFERROR(_xlfn.XLOOKUP(F94,'AUXILIAR SAP'!J:J,'AUXILIAR SAP'!I:I),"-") -> REN_CONTROLE_AV | L94: CONTROLE ALTO VALOR | M94: Alteração do Plano
A95: SMARTPHONE_SMARTWATCH | B95: Disponível para ALTA/MIGRAÇÃO | C95: TITULAR VIVO PÓS - 50GB | D95: Vivo Total Pro | E95: NEXT | F95: PÓS INDIVIDUAL | G95: 442435628 | H95: =_xlfn.XLOOKUP(F95,'AUXILIAR SAP'!E:E,'AUXILIAR SAP'!B:B) -> ZF2 | I95: =_xlfn.XLOOKUP(F95,'AUXILIAR SAP'!E:E,'AUXILIAR SAP'!D:D) -> PÓS_IND | J95: =IFERROR(_xlfn.XLOOKUP(F95,'AUXILIAR SAP'!J:J,'AUXILIAR SAP'!G:G),"-") -> ZF5 | K95: =IFERROR(_xlfn.XLOOKUP(F95,'AUXILIAR SAP'!J:J,'AUXILIAR SAP'!I:I),"-") -> REN_PÓS_IND | L95: PÓS INDIVIDUAL | M95: Alinhar retirada da tabela/Não será mais comercializado 20.07
A96: SMARTPHONE_SMARTWATCH | B96: Não disponível para ALTA/MIGRAÇÃO | C96: LINHA ADICIONAL VIVO PÓS - 50GB | D96: Vivo Total Pro | E96: NEXT | F96: CONTROLE ALTO VALOR | G96: 442435638 | H96: =_xlfn.XLOOKUP(F96,'AUXILIAR SAP'!E:E,'AUXILIAR SAP'!B:B) -> CU6 | I96: =_xlfn.XLOOKUP(F96,'AUXILIAR SAP'!E:E,'AUXILIAR SAP'!D:D) -> CONTROLE_AV | J96: =IFERROR(_xlfn.XLOOKUP(F96,'AUXILIAR SAP'!J:J,'AUXILIAR SAP'!G:G),"-") -> CY2 | K96: =IFERROR(_xlfn.XLOOKUP(F96,'AUXILIAR SAP'!J:J,'AUXILIAR SAP'!I:I),"-") -> REN_CONTROLE_AV | L96: CONTROLE ALTO VALOR | M96: Alinhar retirada da tabela/Não será mais comercializado 20.07
A97: SMARTPHONE_SMARTWATCH | B97: Não disponível para ALTA/MIGRAÇÃO | C97: TITULAR VIVO PÓS FAMÍLIA - 180GB | D97: Vivo Total Família 3 | E97: NEXT | F97: FAMILIA 3 | G97: 442435668 | H97: =_xlfn.XLOOKUP(F97,'AUXILIAR SAP'!E:E,'AUXILIAR SAP'!B:B) -> CU9 | I97: =_xlfn.XLOOKUP(F97,'AUXILIAR SAP'!E:E,'AUXILIAR SAP'!D:D) -> FAM_3 | J97: =IFERROR(_xlfn.XLOOKUP(F97,'AUXILIAR SAP'!J:J,'AUXILIAR SAP'!G:G),"-") -> CY5 | K97: =IFERROR(_xlfn.XLOOKUP(F97,'AUXILIAR SAP'!J:J,'AUXILIAR SAP'!I:I),"-") -> REN_FAM_3 | L97: FAMILIA 2 | M97: Alteração de nome do Grupamento 28/08
A98: SMARTPHONE_SMARTWATCH | B98: Não disponível para ALTA/MIGRAÇÃO | C98: LINHA ADICIONAL VIVO PÓS FAMÍLIA - 180GB | D98: Vivo Total Família 3 | E98: NEXT | F98: PÓS INDIVIDUAL | G98: 442435678 | H98: =_xlfn.XLOOKUP(F98,'AUXILIAR SAP'!E:E,'AUXILIAR SAP'!B:B) -> ZF2 | I98: =_xlfn.XLOOKUP(F98,'AUXILIAR SAP'!E:E,'AUXILIAR SAP'!D:D) -> PÓS_IND | J98: =IFERROR(_xlfn.XLOOKUP(F98,'AUXILIAR SAP'!J:J,'AUXILIAR SAP'!G:G),"-") -> ZF5 | K98: =IFERROR(_xlfn.XLOOKUP(F98,'AUXILIAR SAP'!J:J,'AUXILIAR SAP'!I:I),"-") -> REN_PÓS_IND | L98: PÓS INDIVIDUAL | M98: Alteração do Plano
A99: SMARTPHONE_SMARTWATCH | B99: Disponível para ALTA/MIGRAÇÃO | C99: Titular Vivo Pós Família 300GB | D99: Vivo Total Família 5 | E99: NEXT | F99: FAMILIA 4/5 | G99: 442435688 | H99: =_xlfn.XLOOKUP(F99,'AUXILIAR SAP'!E:E,'AUXILIAR SAP'!B:B) -> CV2 | I99: =_xlfn.XLOOKUP(F99,'AUXILIAR SAP'!E:E,'AUXILIAR SAP'!D:D) -> FAM_4/5 | J99: =IFERROR(_xlfn.XLOOKUP(F99,'AUXILIAR SAP'!J:J,'AUXILIAR SAP'!G:G),"-") -> CY7 | K99: =IFERROR(_xlfn.XLOOKUP(F99,'AUXILIAR SAP'!J:J,'AUXILIAR SAP'!I:I),"-") -> REN_FAM_4/5 | L99: FAMILIA 3 | M99: Alteração de nome do Grupamento 28/08
A100: SMARTPHONE_SMARTWATCH | B100: Não disponível para ALTA/MIGRAÇÃO | C100: Linha Adicional Vivo Pós Família 300GB | D100: Vivo Total Família 5 | E100: NEXT | F100: PÓS INDIVIDUAL | G100: 442435698 | H100: =_xlfn.XLOOKUP(F100,'AUXILIAR SAP'!E:E,'AUXILIAR SAP'!B:B) -> ZF2 | I100: =_xlfn.XLOOKUP(F100,'AUXILIAR SAP'!E:E,'AUXILIAR SAP'!D:D) -> PÓS_IND | J100: =IFERROR(_xlfn.XLOOKUP(F100,'AUXILIAR SAP'!J:J,'AUXILIAR SAP'!G:G),"-") -> ZF5 | K100: =IFERROR(_xlfn.XLOOKUP(F100,'AUXILIAR SAP'!J:J,'AUXILIAR SAP'!I:I),"-") -> REN_PÓS_IND | L100: PÓS INDIVIDUAL
A101: SMARTPHONE_SMARTWATCH | B101: Disponível para ALTA/MIGRAÇÃO | C101: Titular Plano Pós Vivo V 600GB | D101: Vivo Total V | Vivo Total V 600Mbps | E101: NEXT | F101: VIVO V | G101: 442435708 | H101: =_xlfn.XLOOKUP(F101,'AUXILIAR SAP'!E:E,'AUXILIAR SAP'!B:B) -> 28Y | I101: =_xlfn.XLOOKUP(F101,'AUXILIAR SAP'!E:E,'AUXILIAR SAP'!D:D) -> VIVO_V | J101: =IFERROR(_xlfn.XLOOKUP(F101,'AUXILIAR SAP'!J:J,'AUXILIAR SAP'!G:G),"-") -> 08Y | K101: =IFERROR(_xlfn.XLOOKUP(F101,'AUXILIAR SAP'!J:J,'AUXILIAR SAP'!I:I),"-") -> REN_VIVO_V | L101: VIVO V
A102: SMARTPHONE_SMARTWATCH | B102: Não disponível para ALTA/MIGRAÇÃO | C102: Linha Adicional Plano Pós Vivo V 600GB | D102: Vivo Total V | Vivo Total V 600Mbps | E102: NEXT | F102: PÓS INDIVIDUAL | G102: 442435718 | H102: =_xlfn.XLOOKUP(F102,'AUXILIAR SAP'!E:E,'AUXILIAR SAP'!B:B) -> ZF2 | I102: =_xlfn.XLOOKUP(F102,'AUXILIAR SAP'!E:E,'AUXILIAR SAP'!D:D) -> PÓS_IND | J102: =IFERROR(_xlfn.XLOOKUP(F102,'AUXILIAR SAP'!J:J,'AUXILIAR SAP'!G:G),"-") -> ZF5 | K102: =IFERROR(_xlfn.XLOOKUP(F102,'AUXILIAR SAP'!J:J,'AUXILIAR SAP'!I:I),"-") -> REN_PÓS_IND | L102: PÓS INDIVIDUAL
A103: SMARTPHONE_SMARTWATCH | B103: Não disponível para ALTA/MIGRAÇÃO | C103: VIVO CONTROLE 10GB X | D103: - | E103: NEXT | F103: CONTROLE BTL | G103: 105121472 | H103: =_xlfn.XLOOKUP(F103,'AUXILIAR SAP'!E:E,'AUXILIAR SAP'!B:B) -> ZF4 | I103: =_xlfn.XLOOKUP(F103,'AUXILIAR SAP'!E:E,'AUXILIAR SAP'!D:D) -> CONTROLE_BTL | J103: =IFERROR(_xlfn.XLOOKUP(F103,'AUXILIAR SAP'!J:J,'AUXILIAR SAP'!G:G),"-") -> ZF7 | K103: =IFERROR(_xlfn.XLOOKUP(F103,'AUXILIAR SAP'!J:J,'AUXILIAR SAP'!I:I),"-") -> REN_CONTROLE_BTL | L103: PRÉ | M103: Alteração de nomenclatura 26/03/26
A104: SMARTPHONE_SMARTWATCH | B104: Não disponível para ALTA/MIGRAÇÃO | C104: VIVO CONTROLE 11GB IV | D104: - | E104: NEXT | F104: CONTROLE BTL | G104: 105008292 | H104: =_xlfn.XLOOKUP(F104,'AUXILIAR SAP'!E:E,'AUXILIAR SAP'!B:B) -> ZF4 | I104: =_xlfn.XLOOKUP(F104,'AUXILIAR SAP'!E:E,'AUXILIAR SAP'!D:D) -> CONTROLE_BTL | J104: =IFERROR(_xlfn.XLOOKUP(F104,'AUXILIAR SAP'!J:J,'AUXILIAR SAP'!G:G),"-") -> ZF7 | K104: =IFERROR(_xlfn.XLOOKUP(F104,'AUXILIAR SAP'!J:J,'AUXILIAR SAP'!I:I),"-") -> REN_CONTROLE_BTL | L104: PRÉ | M104: Alteração de nomenclatura 26/03/26
A105: SMARTPHONE_SMARTWATCH | B105: Não disponível para ALTA/MIGRAÇÃO | C105: VIVO CONTROLE 6GB I | D105: - | E105: NEXT | F105: CONTROLE BTL | G105: 105943523 | H105: =_xlfn.XLOOKUP(F105,'AUXILIAR SAP'!E:E,'AUXILIAR SAP'!B:B) -> ZF4 | I105: =_xlfn.XLOOKUP(F105,'AUXILIAR SAP'!E:E,'AUXILIAR SAP'!D:D) -> CONTROLE_BTL | J105: =IFERROR(_xlfn.XLOOKUP(F105,'AUXILIAR SAP'!J:J,'AUXILIAR SAP'!G:G),"-") -> ZF7 | K105: =IFERROR(_xlfn.XLOOKUP(F105,'AUXILIAR SAP'!J:J,'AUXILIAR SAP'!I:I),"-") -> REN_CONTROLE_BTL | L105: PRÉ | M105: Alteração de nome do Grupamento 28/08
A106: SMARTPHONE_SMARTWATCH | B106: Não disponível para ALTA/MIGRAÇÃO | C106: TITULAR VIVO PÓS 25GB II | D106: - | E106: NEXT | F106: PÓS INDIVIDUAL | G106: 434939262 | H106: =_xlfn.XLOOKUP(F106,'AUXILIAR SAP'!E:E,'AUXILIAR SAP'!B:B) -> ZF2 | I106: =_xlfn.XLOOKUP(F106,'AUXILIAR SAP'!E:E,'AUXILIAR SAP'!D:D) -> PÓS_IND | J106: =IFERROR(_xlfn.XLOOKUP(F106,'AUXILIAR SAP'!J:J,'AUXILIAR SAP'!G:G),"-") -> ZF5 | K106: =IFERROR(_xlfn.XLOOKUP(F106,'AUXILIAR SAP'!J:J,'AUXILIAR SAP'!I:I),"-") -> REN_PÓS_IND | L106: PÓS INDIVIDUAL | M106: Alteração de nomenclatura 26/03/26
A107: SMARTPHONE_SMARTWATCH | B107: Não disponível para ALTA/MIGRAÇÃO | C107: TITULAR VIVO_POS 20GB. | D107: - | E107: NEXT | F107: PÓS INDIVIDUAL | G107: 435421424 | H107: =_xlfn.XLOOKUP(F107,'AUXILIAR SAP'!E:E,'AUXILIAR SAP'!B:B) -> ZF2 | I107: =_xlfn.XLOOKUP(F107,'AUXILIAR SAP'!E:E,'AUXILIAR SAP'!D:D) -> PÓS_IND | J107: =IFERROR(_xlfn.XLOOKUP(F107,'AUXILIAR SAP'!J:J,'AUXILIAR SAP'!G:G),"-") -> ZF5 | K107: =IFERROR(_xlfn.XLOOKUP(F107,'AUXILIAR SAP'!J:J,'AUXILIAR SAP'!I:I),"-") -> REN_PÓS_IND | L107: PÓS INDIVIDUAL
A108: SMARTPHONE_SMARTWATCH | B108: Não disponível para ALTA/MIGRAÇÃO | C108: VIVO CONTROLE 6GB III | D108: - | E108: NEXT | F108: CONTROLE BTL | G108: 483298874 | H108: =_xlfn.XLOOKUP(F108,'AUXILIAR SAP'!E:E,'AUXILIAR SAP'!B:B) -> ZF4 | I108: =_xlfn.XLOOKUP(F108,'AUXILIAR SAP'!E:E,'AUXILIAR SAP'!D:D) -> CONTROLE_BTL | J108: =IFERROR(_xlfn.XLOOKUP(F108,'AUXILIAR SAP'!J:J,'AUXILIAR SAP'!G:G),"-") -> ZF7 | K108: =IFERROR(_xlfn.XLOOKUP(F108,'AUXILIAR SAP'!J:J,'AUXILIAR SAP'!I:I),"-") -> REN_CONTROLE_BTL | L108: PRÉ | M108: Alteração de nome do Grupamento 28/08
A109: SMARTPHONE_SMARTWATCH | B109: Não disponível para ALTA/MIGRAÇÃO | C109: TITULAR VIVO_POS 35GB | D109: - | E109: NEXT | F109: PÓS INDIVIDUAL | G109: 435421504 | H109: =_xlfn.XLOOKUP(F109,'AUXILIAR SAP'!E:E,'AUXILIAR SAP'!B:B) -> ZF2 | I109: =_xlfn.XLOOKUP(F109,'AUXILIAR SAP'!E:E,'AUXILIAR SAP'!D:D) -> PÓS_IND | J109: =IFERROR(_xlfn.XLOOKUP(F109,'AUXILIAR SAP'!J:J,'AUXILIAR SAP'!G:G),"-") -> ZF5 | K109: =IFERROR(_xlfn.XLOOKUP(F109,'AUXILIAR SAP'!J:J,'AUXILIAR SAP'!I:I),"-") -> REN_PÓS_IND | L109: PÓS INDIVIDUAL
A110: SMARTPHONE_SMARTWATCH | B110: Não disponível para ALTA/MIGRAÇÃO | C110: VIVO CONTROLE 9GB VIII | D110: - | E110: NEXT | F110: CONTROLE ENTRADA | G110: 484082223 | H110: =_xlfn.XLOOKUP(F110,'AUXILIAR SAP'!E:E,'AUXILIAR SAP'!B:B) -> BC4 | I110: =_xlfn.XLOOKUP(F110,'AUXILIAR SAP'!E:E,'AUXILIAR SAP'!D:D) -> CONTROLE_ENT | J110: =IFERROR(_xlfn.XLOOKUP(F110,'AUXILIAR SAP'!J:J,'AUXILIAR SAP'!G:G),"-") -> BE4 | K110: =IFERROR(_xlfn.XLOOKUP(F110,'AUXILIAR SAP'!J:J,'AUXILIAR SAP'!I:I),"-") -> REN_CONTROLE_ENT | L110: CONTROLE ENTRADA
A111: SMARTPHONE_SMARTWATCH | B111: Não disponível para ALTA/MIGRAÇÃO | C111: LINHA ADICIONAL VIVO POS ESSENCIAL PLN | D111: - | E111: NEXT | F111: CONTROLE ALTO VALOR | G111: 104375992 | H111: =_xlfn.XLOOKUP(F111,'AUXILIAR SAP'!E:E,'AUXILIAR SAP'!B:B) -> CU6 | I111: =_xlfn.XLOOKUP(F111,'AUXILIAR SAP'!E:E,'AUXILIAR SAP'!D:D) -> CONTROLE_AV | J111: =IFERROR(_xlfn.XLOOKUP(F111,'AUXILIAR SAP'!J:J,'AUXILIAR SAP'!G:G),"-") -> CY2 | K111: =IFERROR(_xlfn.XLOOKUP(F111,'AUXILIAR SAP'!J:J,'AUXILIAR SAP'!I:I),"-") -> REN_CONTROLE_AV | L111: CONTROLE ALTO VALOR | M111: Alteração do Plano 22/08
A112: SMARTPHONE_SMARTWATCH | B112: Não disponível para ALTA/MIGRAÇÃO | C112: LINHA ADICIONAL VIVO PÓS 35GB PLN | D112: - | E112: NEXT | F112: CONTROLE ALTO VALOR | G112: 104376032 | H112: =_xlfn.XLOOKUP(F112,'AUXILIAR SAP'!E:E,'AUXILIAR SAP'!B:B) -> CU6 | I112: =_xlfn.XLOOKUP(F112,'AUXILIAR SAP'!E:E,'AUXILIAR SAP'!D:D) -> CONTROLE_AV | J112: =IFERROR(_xlfn.XLOOKUP(F112,'AUXILIAR SAP'!J:J,'AUXILIAR SAP'!G:G),"-") -> CY2 | K112: =IFERROR(_xlfn.XLOOKUP(F112,'AUXILIAR SAP'!J:J,'AUXILIAR SAP'!I:I),"-") -> REN_CONTROLE_AV | L112: CONTROLE ALTO VALOR | M112: Alteração de nomenclatura 26/03/26
A113: SMARTPHONE_SMARTWATCH | B113: Não disponível para ALTA/MIGRAÇÃO | C113: LINHA ADICIONAL VIVO POS TRAVEL PLN | D113: - | E113: NEXT | F113: CONTROLE ALTO VALOR | G113: 104376072 | H113: =_xlfn.XLOOKUP(F113,'AUXILIAR SAP'!E:E,'AUXILIAR SAP'!B:B) -> CU6 | I113: =_xlfn.XLOOKUP(F113,'AUXILIAR SAP'!E:E,'AUXILIAR SAP'!D:D) -> CONTROLE_AV | J113: =IFERROR(_xlfn.XLOOKUP(F113,'AUXILIAR SAP'!J:J,'AUXILIAR SAP'!G:G),"-") -> CY2 | K113: =IFERROR(_xlfn.XLOOKUP(F113,'AUXILIAR SAP'!J:J,'AUXILIAR SAP'!I:I),"-") -> REN_CONTROLE_AV | L113: CONTROLE ALTO VALOR | M113: Alteração do Plano 22/08
A114: SMARTPHONE_SMARTWATCH | B114: Não disponível para ALTA/MIGRAÇÃO | C114: LINHA ADICIONAL VIVO FAMILIA 2 PLN | D114: - | E114: NEXT | F114: CONTROLE ALTO VALOR | G114: 104564442 | H114: =_xlfn.XLOOKUP(F114,'AUXILIAR SAP'!E:E,'AUXILIAR SAP'!B:B) -> CU6 | I114: =_xlfn.XLOOKUP(F114,'AUXILIAR SAP'!E:E,'AUXILIAR SAP'!D:D) -> CONTROLE_AV | J114: =IFERROR(_xlfn.XLOOKUP(F114,'AUXILIAR SAP'!J:J,'AUXILIAR SAP'!G:G),"-") -> CY2 | K114: =IFERROR(_xlfn.XLOOKUP(F114,'AUXILIAR SAP'!J:J,'AUXILIAR SAP'!I:I),"-") -> REN_CONTROLE_AV | L114: CONTROLE ALTO VALOR | M114: Alteração do Plano 22/08
A115: SMARTPHONE_SMARTWATCH | B115: Não disponível para ALTA/MIGRAÇÃO | C115: LINHA ADICIONAL VIVO FAMILIA 3 PLN | D115: - | E115: NEXT | F115: CONTROLE ALTO VALOR | G115: 104564472 | H115: =_xlfn.XLOOKUP(F115,'AUXILIAR SAP'!E:E,'AUXILIAR SAP'!B:B) -> CU6 | I115: =_xlfn.XLOOKUP(F115,'AUXILIAR SAP'!E:E,'AUXILIAR SAP'!D:D) -> CONTROLE_AV | J115: =IFERROR(_xlfn.XLOOKUP(F115,'AUXILIAR SAP'!J:J,'AUXILIAR SAP'!G:G),"-") -> CY2 | K115: =IFERROR(_xlfn.XLOOKUP(F115,'AUXILIAR SAP'!J:J,'AUXILIAR SAP'!I:I),"-") -> REN_CONTROLE_AV | L115: CONTROLE ALTO VALOR | M115: Alteração do Plano 22/08
A116: SMARTPHONE_SMARTWATCH | B116: Não disponível para ALTA/MIGRAÇÃO | C116: LINHA ADICIONAL VIVO FAMILIA 4 PLN | D116: - | E116: NEXT | F116: PÓS INDIVIDUAL | G116: 104564502 | H116: =_xlfn.XLOOKUP(F116,'AUXILIAR SAP'!E:E,'AUXILIAR SAP'!B:B) -> ZF2 | I116: =_xlfn.XLOOKUP(F116,'AUXILIAR SAP'!E:E,'AUXILIAR SAP'!D:D) -> PÓS_IND | J116: =IFERROR(_xlfn.XLOOKUP(F116,'AUXILIAR SAP'!J:J,'AUXILIAR SAP'!G:G),"-") -> ZF5 | K116: =IFERROR(_xlfn.XLOOKUP(F116,'AUXILIAR SAP'!J:J,'AUXILIAR SAP'!I:I),"-") -> REN_PÓS_IND | L116: PÓS INDIVIDUAL | M116: Alteração do Plano 22/08
A117: SMARTPHONE_SMARTWATCH | B117: Não disponível para ALTA/MIGRAÇÃO | C117: LINHA ADICIONAL VIVO FAMILIA 5 PLN | D117: - | E117: NEXT | F117: PÓS INDIVIDUAL | G117: 104564532 | H117: =_xlfn.XLOOKUP(F117,'AUXILIAR SAP'!E:E,'AUXILIAR SAP'!B:B) -> ZF2 | I117: =_xlfn.XLOOKUP(F117,'AUXILIAR SAP'!E:E,'AUXILIAR SAP'!D:D) -> PÓS_IND | J117: =IFERROR(_xlfn.XLOOKUP(F117,'AUXILIAR SAP'!J:J,'AUXILIAR SAP'!G:G),"-") -> ZF5 | K117: =IFERROR(_xlfn.XLOOKUP(F117,'AUXILIAR SAP'!J:J,'AUXILIAR SAP'!I:I),"-") -> REN_PÓS_IND | L117: PÓS INDIVIDUAL | M117: Alteração do Plano 22/08
A118: SMARTPHONE_SMARTWATCH | B118: Não disponível para ALTA/MIGRAÇÃO | C118: LINHA ADICIONAL VIVO PÓS 35GB II PLN | D118: - | E118: NEXT | F118: CONTROLE ALTO VALOR | G118: 104376102 | H118: =_xlfn.XLOOKUP(F118,'AUXILIAR SAP'!E:E,'AUXILIAR SAP'!B:B) -> CU6 | I118: =_xlfn.XLOOKUP(F118,'AUXILIAR SAP'!E:E,'AUXILIAR SAP'!D:D) -> CONTROLE_AV | J118: =IFERROR(_xlfn.XLOOKUP(F118,'AUXILIAR SAP'!J:J,'AUXILIAR SAP'!G:G),"-") -> CY2 | K118: =IFERROR(_xlfn.XLOOKUP(F118,'AUXILIAR SAP'!J:J,'AUXILIAR SAP'!I:I),"-") -> REN_CONTROLE_AV | L118: CONTROLE ALTO VALOR | M118: Alteração de nomenclatura 26/03/26
...

Sheet AUXILIAR SAP
B2: Tabela Regular | G2: Tabela Renova
B3: COD SAP (USAR PARA VENDA MANUAL) | C3: NOME PLANO SAP (válido até 20/08/2025) | D3: NOME PLANO SAP (válido a partir de 21/08/2025) | E3: GRUPO TABELA DE PREÇOS (a partir de 28/08/2025) | G3: COD SAP RENOVA (USAR PARA VENDA MANUAL) | H3: NOME PLANO SAP (válido até 20/08/2025) | I3: NOME PLANO SAP (válido a partir de 21/08/2025) | J3: GRUPO TABELA DE PREÇOS (a partir de 28/08/2025)
B4: BC4 | C4: CONTROLE_ENT | D4: CONTROLE_ENT | E4: CONTROLE ENTRADA | G4: BE4 | H4: REN_CONTROLE_ENT | I4: REN_CONTROLE_ENT | J4: CONTROLE ENTRADA
B5: CU6 | C5: CONTROLE_AV | D5: CONTROLE_AV | E5: CONTROLE ALTO VALOR | G5: CY2 | H5: REN_CONTROLE_AV | I5: REN_CONTROLE_AV | J5: CONTROLE ALTO VALOR
B6: ZF2 | C6: PÓS_IND | D6: PÓS_IND | E6: PÓS INDIVIDUAL | G6: ZF5 | H6: REN_PÓS_IND | I6: REN_PÓS_IND | J6: PÓS INDIVIDUAL
B7: ZF3 | C7: FAM_1 | D7: FAM_2 | E7: FAMILIA 2 | G7: ZF6 | H7: REN_VIVO_TOT_IND | I7: REN_FAM_2 | J7: FAMILIA 2
B8: CU9 | C8: FAM_2 | D8: FAM_3 | E8: FAMILIA 3 | G8: CY5 | H8: REN_FAM_ENTRADA | I8: REN_FAM_3 | J8: FAMILIA 3
B9: CV2 | C9: FAM_3 | D9: FAM_4/5 | E9: FAMILIA 4/5 | G9: CY7 | H9: REN_FAM_ALTO_VALOR | I9: REN_FAM_4/5 | J9: FAMILIA 4/5
B10: ZF4 | C10: FAM_4 | D10: CONTROLE_BTL | E10: CONTROLE BTL | G10: ZF7 | H10: REN_VIVO_TOT_AV | I10: REN_CONTROLE_BTL | J10: CONTROLE BTL
B11: 28Y | C11: VIVO_V | D11: VIVO_V | E11: VIVO V | G11: 08Y | H11: REN_VIVO_V | I11: REN_VIVO_V | J11: VIVO V
B12: PPP | C12: PRE | D12: PRE | E12: PRÉ
B13: KAU | C13: MULTIVIVO | D13: MULTIVIVO | E13: MULTIVIVO
B14: YAQ | C14: VIM_8GB | D14: VIM_8GB | E14: VIM 8GB
B15: YAR | C15: VIM_14GB | D15: VIM_14GB | E15: VIM 14GB
B16: YAS | C16: VIM_20GB | D16: VIM_20GB | E16: VIM 20GB
B17: 85W | C17: VIM_40GB | D17: VIM_40GB | E17: VIM 40GB
B18: ZE5 | C18: VIM_100GB | D18: VIM_100GB | E18: VIM 100GB
B19: F10 | C19: FIXO_ILIMITADO | D19: FIXO_ILIMITADO | E19: Vivo Fixo Ilimitado
B20: F12 | C20: FIXO_ILIMITADO_TOTAL | D20: FIXO_ILIMITADO_TOTAL | E20: Vivo Fixo Ilimitado Total
B21: UYV | C21: VITRINE | D21: VITRINE | E21: -
B22: CHA | C22: CHIP_AVULSO | D22: CHIP_AVULSO | E22: -

Sheet PRODUTOS
A1: Cod_Sap | B1: Descricao_Sap | C1: Modelo (Nome DPGC) | D1: Cor | E1: Nome Comercial | F1: Fabricante | G1: Categoria | H1: Subcategoria | I1: ID_DPGC | J1: Tecnologia | K1: Produto com eSIM | L1: Gama | M1: Tabela | N1: Portfólio | O1: Lançamento | P1: Margem Conectados | Q1: Margem não conectados
A2: FFZT04663000 | B2: ZTE FWT WP755 (FIXO) PRETO BASICO | C2: FWT ZTE WP755 (Fixo) | D2: Preto | E2: FWT ZTE WP755 | F2: ZTE | G2: Box e Modem e FWT | H2: FWT | I2: ZTE102 | J2: 3G | K2: NÃO | L2: Low | M2: DEVICES ESPECIAIS | N2: EOL | O2: - | P2: 0% | Q2: 0%
A3: RGWN00162000 | B3: WNC ROTEADOR WLD71 PRETO LTE | C3: BLACKBOX WNC WLD71 (LTE 28) | D3: Preto | E3: BLACKBOX FLEX WLD71 (LTE 28) | F3: Flex | G3: Box e Modem e FWT | H3: Box e Modem | I3: FLX02 | J3: 4G | K3: NÃO | L3: Premium | M3: DEVICES ESPECIAIS | N3: EOL | O3: - | P3: 0.1 | Q3: 0%
A4: RGWN00262000 | B4: WNC ROTEADOR WLD71-T5A PRETO LTE | C4: BLACKBOX WNC WLD71 (LTE 28) | D4: Preto | E4: BLACKBOX FLEX WLD71 (LTE 28) | F4: Flex | G4: Box e Modem e FWT | H4: Box e Modem | I4: FLX02 | J4: 4G | K4: NÃO | L4: Premium | M4: DEVICES ESPECIAIS | N4: EOL | O4: - | P4: 0.1 | Q4: 0%
A5: BGSA34762000 | B5: SAMSUNG TAB A8 S PEN | C5: Samsung P205 | D5: Preto | E5: Galaxy TAB A 8'' Spen | F5: Samsung | G5: Notebook e Tablets | H5: Tablet | I5: SAM302 | J5: 4G | K5: NÃO | L5: Tablet | M5: TABLETS | N5: EOL | O5: - | P5: 0.15 | Q5: 0%
A6: AFML00762000 | B6: MULTILASER VITA 3G C/ BASE (FIXO) PRETO | C6: Multilaser P9109 | D6: Preto | E6: Multi Vita 3G | F6: Multi | G6: Box e Modem e FWT | H6: FWT | I6: MUL11 | J6: 3G | K6: NÃO | L6: Barra Câmera 3G | M6: DEVICES ESPECIAIS | N6: EOL | O6: - | P6: 0% | Q6: 0%
A7: MGHU05523000 | B7: HUAWEI MODEM E8372 BRANCO WIFI LTE | C7: Pen Modem Huawei E8372 (LTE WIFI) | D7: Branco | E7: Pen Modem Huawei E8372 (LTE Wi-Fi 28) | F7: Huawei | G7: Box e Modem e FWT | H7: Box e Modem | I7: HUA119 | J7: 4G | K7: NÃO | L7: Modem | M7: DEVICES ESPECIAIS | N7: EOL | O7: - | P7: 0% | Q7: 0%
A8: MGZT05123000 | B8: ZTE MF79S MODEM BRANCO | C8: Pen Modem ZTE MF79S | D8: Branco | E8: Pen Modem ZTE MF79S | F8: ZTE | G8: Box e Modem e FWT | H8: Box e Modem | I8: ZTE000006 | J8: 4G | K8: NÃO | L8: Modem | M8: DEVICES ESPECIAIS | N8: EOL | O8: - | P8: 0% | Q8: 0%
A9: TGSA35312007 | B9: SAMSUNG A505 128GB SMART AZ PPB/PI107/04 | C9: Samsung A505 128GB | D9: Azul | E9: Samsung Galaxy A50 128GB | F9: Samsung | G9: Smartphone | H9: Smartphone | I9: SAM316 | J9: 4G | K9: NÃO | L9: Premium | M9: SMARTPHONES | N9: EOL | O9: 43728 | P9: 0% | Q9: 0%
A10: TGSA35314007 | B10: SAMSUNG A505 128GB SMART AZ PPB/PI324/14 | C10: Samsung A505 128GB | D10: Azul | E10: Samsung Galaxy A50 128GB | F10: Samsung | G10: Smartphone | H10: Smartphone | I10: SAM316 | J10: 4G | K10: NÃO | L10: Premium | M10: SMARTPHONES | N10: EOL | O10: 43728 | P10: 0% | Q10: 0%
A11: DGAP10536000 | B11: APPLE WATCH S5 PSR SPORT 40MM DEMO DRDO | C11: Apple Watch S5 Pulseira Sport 40MM (Demo) | D11: Dourado | E11: Apple Watch S5 Pulseira Sport 40MM | F11: Apple | G11: Bem Estar | H11: Smartwatch | I11: APX96 | J11: 4G | K11: SIM | L11: Wearable Conectado | M11: ELETRÔNICOS | N11: EOL | O11: 43749 | P11: 0% | Q11: 0%
A12: TGSA35714000 | B12: SAMSUNG A207M SMART AZ PPB/PI324/14 | C12: Samsung A207G | D12: Azul | E12: Samsung Galaxy A20S | F12: Samsung | G12: Smartphone | H12: Smartphone | I12: SAM317 | J12: 4G | K12: NÃO | L12: Mid | M12: SMARTPHONES | N12: EOL | O12: 43798 | P12: 0% | Q12: 0%
A13: DGAP095R2000 | B13: APPLE IPHONE 11 256GB RX PPB/PI643/10 | C13: iPhone 11 256GB | D13: Roxo | E13: iPhone 11 256GB | F13: Apple | G13: Smartphone | H13: Smartphone | I13: APP79 | J13: 4G | K13: SIM | L13: Flagship | M13: SMARTPHONES | N13: EOL | O13: 43749 | P13: 0% | Q13: 0%
A14: DGAP11026000 | B14: APPLE IPHONE SE 64GB DEMO BR | C14: iPhone SE 64GB (Demo) | D14: Branco | E14: iPhone SE 64GB (Demo) | F14: Apple | G14: Smartphone | H14: Smartphone | I14: APX102 | J14: 4G | K14: SIM | L14: Flagship | M14: DEMO | N14: EOL | O14: - | P14: 0% | Q14: 0%
A15: DGAP11006000 | B15: APPLE IPHONE SE 64GB DEMO VM | C15: iPhone SE 64GB (Demo) | D15: Vermelho | E15: iPhone SE 64GB (Demo) | F15: Apple | G15: Smartphone | H15: Smartphone | I15: APX102 | J15: 4G | K15: SIM | L15: Flagship | M15: DEMO | N15: EOL | O15: - | P15: 0% | Q15: 0%
A16: TGSA37362000 | B16: SAMSUNG A115M SMART PT PPB/PI432/11 | C16: Samsung A115M | D16: Preto | E16: Samsung Galaxy A11 | F16: Samsung | G16: Smartphone | H16: Smartphone | I16: SAM331 | J16: 4G | K16: NÃO | L16: Mid | M16: SMARTPHONES | N16: EOL | O16: 43995 | P16: 0% | Q16: 0%
A17: TGSA37264000 | B17: SAMSUNG A217M SMART PT PPB/PI324/14 | C17: Samsung A217M | D17: Preto | E17: Samsung Galaxy A21S | F17: Samsung | G17: Smartphone | H17: Smartphone | I17: SAM332 | J17: 4G | K17: NÃO | L17: High | M17: SMARTPHONES | N17: EOL | O17: 43995 | P17: 0% | Q17: 0%
A18: BGSA35562000 | B18: SAMSUNG T295 TABLET PT PPB/PI432/11 | C18: Samsung Tab T295 | D18: Preto | E18: Samsung Galaxy Tab A 8" | F18: Samsung | G18: Notebook e Tablets | H18: Tablet | I18: SAM320 | J18: 4G | K18: NÃO | L18: Tablet | M18: TABLETS | N18: EOL | O18: - | P18: 0% | Q18: 0%
A19: MGZT05323000 | B19: ZTE MF79U MODEM BR | C19: ZTE MF79U MODEM | D19: Branco | E19: Pen Modem MF79U (LTE Wi-Fi 28) | F19: ZTE | G19: Box e Modem e FWT | H19: Box e Modem | I19: ZTE126 | J19: 4G | K19: NÃO | L19: Modem | M19: DEVICES ESPECIAIS | N19: EOL | O19: - | P19: 0.15 | Q19: 0%
A20: DGAP126G3000 | B20: APPLE IPHONE 12 256GB VD | C20: iPhone 12 256GB | D20: Verde | E20: iPhone 12 256GB | F20: Apple | G20: Smartphone | H20: Smartphone | I20: APP139 | J20: 5G | K20: SIM | L20: Flagship | M20: SMARTPHONES | N20: EOL | O20: 44148 | P20: 0% | Q20: 0%
A21: RGWN00462000 | B21: BLACKBOX BLUCASTLE BC-4GMCPGA LTE PT | C21: Blackbox Blucastle BC (4GLTE) | D21: Preto | E21: Blackbox Bluecastle | F21: Blucastle | G21: Box e Modem e FWT | H21: Box e Modem | I21: FLX04 | J21: 4G | K21: NÃO | L21: Premium | M21: DEVICES ESPECIAIS | N21: EOL | O21: - | P21: 0.1 | Q21: 0%
A22: BGSA38534007 | B22: SAMSUNG T505 TABLET DR PPB/PI291/12 | C22: Samsug T505 Tablet | D22: Dourado | E22: Samsung Galaxy Tab A7 10.4" 64GB | F22: Samsung | G22: Notebook e Tablets | H22: Tablet | I22: SAM357 | J22: 4G | K22: NÃO | L22: Tablet | M22: TABLETS | N22: EOL | O22: - | P22: 0.15 | Q22: 0%
A23: BGSA38534000 | B23: SAMSUNG T505 TABLET DR PPB/PI291/12 | C23: Samsug T505 Tablet | D23: Dourado | E23: Samsung Galaxy Tab A7 10.4" 64GB | F23: Samsung | G23: Notebook e Tablets | H23: Tablet | I23: SAM357 | J23: 4G | K23: NÃO | L23: Tablet | M23: TABLETS | N23: EOL | O23: - | P23: 0.15 | Q23: 0%
A24: AFML00763000 | B24: MULTILASER VITA 3G C/ BASE (FIXO) PRETO | C24: Multilaser P9109 | D24: Preto | E24: Multi Vita 3G | F24: Multi | G24: Box e Modem e FWT | H24: FWT | I24: MUL11 | J24: 3G | K24: NÃO | L24: Barra Câmera 3G | M24: DEVICES ESPECIAIS | N24: EOL | O24: - | P24: 0% | Q24: 0%
A25: MGZT05263000 | B25: ZTE MF971 MODEM PRETO | C25: Pen Modem ZTE MF971 | D25: Preto | E25: Pen Modem ZTE MF971 CA | F25: ZTE | G25: Box e Modem e FWT | H25: Box e Modem | I25: ZTE129 | J25: 4G | K25: NÃO | L25: Modem | M25: DEVICES ESPECIAIS | N25: EOL | O25: - | P25: 0% | Q25: 0%
A26: TGMO40182000 | B26: MOTOROLA XT2095 SMARTPHONE 64GB CB | C26: Motorola XT2095 | D26: Cobre | E26: Moto E7 64GB | F26: Motorola | G26: Smartphone | H26: Smartphone | I26: MOT144 | J26: 4G | K26: NÃO | L26: Mid | M26: SMARTPHONES | N26: EOL | O26: 44176 | P26: 0% | Q26: 0%
A27: TGSA39062007 | B27: SAMSUNG A025M SMART PT PPB/PI432/11 | C27: Samsung A025M | D27: Preto | E27: Samsung Galaxy A02S | F27: Samsung | G27: Smartphone | H27: Smartphone | I27: SAM367 | J27: 4G | K27: NÃO | L27: Mid | M27: SMARTPHONES | N27: EOL | O27: 44218 | P27: 0% | Q27: 0%
A28: TGSA39102000 | B28: SAMSUNG A125M SMART VM PPB/PI432/11 | C28: Samsung A125M | D28: Vermelho | E28: Samsung Galaxy A12 | F28: Samsung | G28: Smartphone | H28: Smartphone | I28: SAM366 | J28: 4G | K28: NÃO | L28: Mid | M28: SMARTPHONES | N28: EOL | O28: 44218 | P28: 0% | Q28: 0%
A29: DGAP13862007 | B29: APPLE IPHONE 11 256GB PT | C29: iPhone 11 256GB | D29: Preto | E29: iPhone 11 256GB | F29: Apple | G29: Smartphone | H29: Smartphone | I29: APP79 | J29: 4G | K29: SIM | L29: Flagship | M29: SMARTPHONES | N29: EOL | O29: 43749 | P29: 0% | Q29: 0%
A30: DGAP09326000 | B30: APPLE IPHONE 11 64GB DEMO BRANCO | C30: iPhone 11 64GB (Demo) | D30: Branco | E30: iPhone 11 64GB (Demo) | F30: Apple | G30: Smartphone | H30: Smartphone | I30: APX77 | J30: 4G | K30: SIM | L30: Flagship | M30: DEMO | N30: EOL | O30: - | P30: 0% | Q30: 0%
A31: DGAP09306000 | B31: APPLE IPHONE 11 64GB DEMO VERMELHO | C31: iPhone 11 64GB (Demo) | D31: Vermelho | E31: iPhone 11 64GB (Demo) | F31: Apple | G31: Smartphone | H31: Smartphone | I31: APX77 | J31: 4G | K31: SIM | L31: Flagship | M31: DEMO | N31: EOL | O31: - | P31: 0% | Q31: 0%
A32: DGAP093Y6000 | B32: APPLE IPHONE 11 64GB DEMO AMARELO | C32: iPhone 11 64GB (Demo) | D32: Amarelo | E32: iPhone 11 64GB (Demo) | F32: Apple | G32: Smartphone | H32: Smartphone | I32: APX77 | J32: 4G | K32: SIM | L32: Flagship | M32: DEMO | N32: EOL | O32: - | P32: 0% | Q32: 0%
A33: DGAP093R6000 | B33: APPLE IPHONE 11 64GB DEMO ROXO | C33: iPhone 11 64GB (Demo) | D33: Roxo | E33: iPhone 11 64GB (Demo) | F33: Apple | G33: Smartphone | H33: Smartphone | I33: APX77 | J33: 4G | K33: SIM | L33: Flagship | M33: DEMO | N33: EOL | O33: - | P33: 0% | Q33: 0%
A34: DGAP093G6000 | B34: APPLE IPHONE 11 64GB DEMO VERDE | C34: iPhone 11 64GB (Demo) | D34: Verde | E34: iPhone 11 64GB (Demo) | F34: Apple | G34: Smartphone | H34: Smartphone | I34: APX77 | J34: 4G | K34: SIM | L34: Flagship | M34: DEMO | N34: EOL | O34: - | P34: 0% | Q34: 0%
A35: DGAP09946000 | B35: APPLE IPHONE 11 PRO 64GB DEMO PRATA | C35: iPhone 11 Pro 64GB (Demo) | D35: Prata | E35: iPhone 11 Pro 64GB (Demo) | F35: Apple | G35: Smartphone | H35: Smartphone | I35: APX80 | J35: 4G | K35: SIM | L35: Flagship | M35: DEMO | N35: EOL | O35: - | P35: 0% | Q35: 0%
A36: DGAP09936000 | B36: APPLE IPHONE 11 PRO 64GB DEMO DOURADO | C36: iPhone 11 Pro 64GB (Demo) | D36: Dourado | E36: iPhone 11 Pro 64GB (Demo) | F36: Apple | G36: Smartphone | H36: Smartphone | I36: APX80 | J36: 4G | K36: SIM | L36: Flagship | M36: DEMO | N36: EOL | O36: - | P36: 0% | Q36: 0%
A37: DGAP099G6000 | B37: APPLE IPHONE 11 PRO 64GB DEMO VERDE | C37: iPhone 11 Pro 64GB (Demo) | D37: Verde | E37: iPhone 11 Pro 64GB (Demo) | F37: Apple | G37: Smartphone | H37: Smartphone | I37: APX80 | J37: 4G | K37: SIM | L37: Flagship | M37: DEMO | N37: EOL | O37: - | P37: 0% | Q37: 0%
A38: DGAP096C6000 | B38: APPLE IPHONE 11 PRO MAX 64GB DEMO CINZA | C38: iPhone 11 Pro Max 64GB (Demo) | D38: Cinza | E38: iPhone 11 Pro Max 64GB (Demo) | F38: Apple | G38: Smartphone | H38: Smartphone | I38: APX83 | J38: 4G | K38: SIM | L38: Flagship | M38: DEMO | N38: EOL | O38: - | P38: 0% | Q38: 0%
A39: DGAP09646000 | B39: APPLE IPHONE 11 PRO MAX 64GB DEMO PRATA | C39: iPhone 11 Pro Max 64GB (Demo) | D39: Prata | E39: iPhone 11 Pro Max 64GB (Demo) | F39: Apple | G39: Smartphone | H39: Smartphone | I39: APX83 | J39: 4G | K39: SIM | L39: Flagship | M39: DEMO | N39: EOL | O39: - | P39: 0% | Q39: 0%
A40: DGAP09636000 | B40: APPLE IPHONE 11 PRO MAX 64GB DEMO DOURADO | C40: iPhone 11 Pro Max 64GB (Demo) | D40: Dourado | E40: iPhone 11 Pro Max 64GB (Demo) | F40: Apple | G40: Smartphone | H40: Smartphone | I40: APX83 | J40: 4G | K40: SIM | L40: Flagship | M40: DEMO | N40: EOL | O40: - | P40: 0% | Q40: 0%
A41: DGAP13026000 | B41: APPLE IPHONE 12 64GB DEMO BR | C41: iPhone 12 64GB (Demo) | D41: Branco | E41: iPhone 12 64GB (Demo) | F41: Apple | G41: Smartphone | H41: Smartphone | I41: APX137 | J41: 5G | K41: SIM | L41: Flagship | M41: DEMO | N41: EOL | O41: - | P41: 0% | Q41: 0%
... A48: DGAP12546000 | B48: APPLE IPHONE 12 PRO MAX 128GB PR DEMO | C48: iPhone 12 Pro Max 128GB (Demo) | D48: Prata | E48: iPhone 12 Pro Max 128GB (Demo) | F48: Apple | G48: Smartphone | H48: Smartphone | I48: APX143 | J48: 5G | K48: SIM | L48: Flagship | M48: DEMO | N48: EOL | O48: - | P48: 0% | Q48: 0%
A49: TGNK28412000 | B49: NOKIA NK032 SMARTPHONE AZ | C49: NOKIA NK032 | D49: Azul | E49: Nokia 5.4 | F49: Nokia | G49: Smartphone | H49: Smartphone | I49: NOK195 | J49: 4G | K49: NÃO | L49: High | M49: SMARTPHONES | N49: EOL | O49: 44302 | P49: 0% | Q49: 0%
A50: TGNK284R2000 | B50: NOKIA NK033 SMARTPHONE RX | C50: NOKIA NK032 | D50: Roxo | E50: Nokia 5.4 | F50: Nokia | G50: Smartphone | H50: Smartphone | I50: NOK195 | J50: 4G | K50: NÃO | L50: High | M50: SMARTPHONES | N50: EOL | O50: 44302 | P50: 0% | Q50: 0%
A51: TGNK285C2000 | B51: NOKIA NK034 SMARTPHONE CZ | C51: NOKIA NK034 | D51: Cinza | E51: Nokia 2.4 | F51: Nokia | G51: Smartphone | H51: Smartphone | I51: NOK194 | J51: 4G | K51: NÃO | L51: Mid | M51: SMARTPHONES | N51: EOL | O51: 44309 | P51: 0% | Q51: 0%
A52: TGNK285R2000 | B52: NOKIA NK035 SMARTPHONE RX | C52: NOKIA NK034 | D52: Roxo | E52: Nokia 2.4 | F52: Nokia | G52: Smartphone | H52: Smartphone | I52: NOK194 | J52: 4G | K52: NÃO | L52: Mid | M52: SMARTPHONES | N52: EOL | O52: 44309 | P52: 0% | Q52: 0%
A53: RGWN00362000 | B53: BLACKBOX PLUS BLUCASTLE BC-MG818H LTE PT | C53: BLACKBOX Plus BLUCASTLE | D53: Preto | E53: Blackbox Plus | F53: Bluecastle | G53: Box e Modem e FWT | H53: Box e Modem | I53: FLX03 | J53: 4G | K53: NÃO | L53: Premium | M53: DEVICES ESPECIAIS | N53: EOL | O53: - | P53: 0% | Q53: 0%
A54: 22017875 | B54: SANDISK MICRO SD ULTRA 16GB | C54: SANDISK MICRO SD ULTRA 16GB | D54: N/I | E54: Cartão de Memória SanDisk Micro SD 16GB | F54: Sandisk | G54: Essenciais | H54: Outros | I54: ALF13 | K54: NÃO | M54: ELETRÔNICOS | N54: EOL | O54: - | P54: 0% | Q54: 0%
A55: 22018137 | B55: CABO GEONAV PREMIUM 3X1 1,5M NYLON CINZA | C55: CABO GEONAV PREMIUM 3X1 1,5M NYLON | D55: Cinza | E55: Cabo Premium 3x1 1,5M | F55: Geonav | G55: Essenciais | H55: Cabos | I55: ALF18 | K55: NÃO | M55: ELETRÔNICOS | N55: EOL | O55: - | P55: 0% | Q55: 0.35
A56: 22018235 | B56: CABO LIGHTNING SILICONE 12CM PRETO | C56: CABO LIGHTNING SILICONE 12CM | D56: Preto | E56: Cabo Lightning Silicone 12cm | F56: Geonav | G56: Essenciais | H56: Cabos | I56: ALF26 | K56: NÃO | M56: ELETRÔNICOS | N56: EOL | O56: - | P56: 0% | Q56: 0%
A57: 22018236 | B57: CABO MICRO USB SILICONE 12CM PRETO | C57: CABO MICRO USB SILICONE 12CM | D57: Preto | E57: Cabo Micro USB Silicone 12cm | F57: Geonav | G57: Essenciais | H57: Cabos | I57: ALF27 | K57: NÃO | M57: ELETRÔNICOS | N57: EOL | O57: - | P57: 0% | Q57: 0%
A58: 22017716 | B58: CABO LIGHTNING PREMIUM 1,5M DOURADO/BRCO | C58: CABO LIGHTNING PREMIUM 1,5M | D58: Dourado | E58: Cabo Lightning Premium 1,5m | F58: Geonav | G58: Essenciais | H58: Cabos | I58: ALF3 | K58: NÃO | M58: ELETRÔNICOS | N58: EOL | O58: - | P58: 0% | Q58: 0%
A59: 22017726 | B59: CABO LIGHTNING PREMIUM 1,5M TITANIUM/PTO | C59: CABO LIGHTNING PREMIUM 1,5M | D59: Titanium | E59: Cabo Lightning Premium 1,5m | F59: Geonav | G59: Essenciais | H59: Cabos | I59: ALF3 | K59: NÃO | M59: ELETRÔNICOS | N59: EOL | O59: - | P59: 0% | Q59: 0%
A60: 22018241 | B60: PELICULA PREMIUM IPHONE 7 e 8 PLUS | C60: PELICULA PREMIUM IPHONE 7 e 8 PLUS | D60: Transparente | E60: Película Premium Iphone 7 e 8 Plus | F60: Alfacomex | G60: Essenciais | H60: Películas | I60: ALF31 | K60: NÃO | M60: ELETRÔNICOS | N60: EOL | O60: - | P60: 0% | Q60: 0%
A61: 22018243 | B61: CABO USB-C SILICONE 12CM PRETO | C61: CABO USB-C SILICONE 12CM | D61: Preto | E61: Cabo USB-C 12cm Silicone | F61: Geonav | G61: Essenciais | H61: Cabos | I61: ALF33 | K61: NÃO | M61: ELETRÔNICOS | N61: EOL | O61: - | P61: 0% | Q61: 0%
A62: 22017727 | B62: CABO MICRO USB PREMIUM 1,5M TITANIUM/PTO | C62: CABO MICRO USB PREMIUM 1,5M | D62: Titanium | E62: Cabo Micro USB Premium 1,5m | F62: Geonav | G62: Essenciais | H62: Cabos | I62: ALF4 | K62: NÃO | M62: ELETRÔNICOS | N62: EOL | O62: - | P62: 0% | Q62: 0%
A63: 22018517 | B63: PELICULA PROTETORA DE VIDRO 3D IPHONE XR | C63: PELICULA PROTETORA DE VIDRO 3D IPHONE XR | D63: Transparente | E63: Película Premium Iphone XR 3D | F63: Alfacomex | G63: Essenciais | H63: Películas | I63: ALF42 | K63: NÃO | M63: ELETRÔNICOS | N63: EOL | O63: - | P63: 0% | Q63: 0%
A64: 22018518 | B64: PELICULA PROT DE VIDRO IPHONE XR | C64: PELICULA PROT DE VIDRO IPHONE XR | D64: Transparente | E64: Película Premium Iphone XR | F64: Alfacomex | G64: Essenciais | H64: Películas | I64: ALF43 | K64: NÃO | M64: ELETRÔNICOS | N64: EOL | O64: - | P64: 0% | Q64: 0%
A65: 22018561 | B65: CABO HDMI SPEED 2.0 ALFACOMEX 1,8M CINZA | C65: CABO HDMI SPEED 2.0 ALFACOMEX 1,8M | D65: Cinza | E65: Cabo HDMI 1,8m | F65: Geonav | G65: Essenciais | H65: Cabos | I65: ALF44 | K65: NÃO | M65: ELETRÔNICOS | N65: EOL | O65: - | P65: 0% | Q65: 0%
A66: 22018675 | B66: GOOGLE CHROMECAST 3 | C66: GOOGLE CHROMECAST 3 | D66: Preto | E66: Google Chromecast 3 | F66: Google | G66: Casa Inteligente | H66: Áudio e Vídeo | I66: ALL7 | J66: Wi-Fi | K66: NÃO | M66: ELETRÔNICOS | N66: EOL | O66: - | P66: 0% | Q66: 0%
A67: 22018275 | B67: CARREGADOR PORTÁTIL ANKER 6.700mAh PRETO | C67: CARREGADOR PORTÁTIL ANKER 6.700mAh | D67: Preto | E67: Carregador Portátil Anker 6.700mAh | F67: Anker | G67: Essenciais | H67: Carregadores | I67: ANK01 | K67: NÃO | M67: ELETRÔNICOS | N67: EOL | O67: - | P67: 0% | Q67: 0%
A68: 22018276 | B68: CARREGADOR PORTÁTIL ANKER 13.000mAh PRTO | C68: CARREGADOR PORTÁTIL ANKER 13.000mAh | D68: Preto | E68: Carregador Portátil Anker 13.000mAh | F68: Anker | G68: Essenciais | H68: Carregadores | I68: ANK02 | K68: NÃO | M68: ELETRÔNICOS | N68: EOL | O68: - | P68: 0% | Q68: 0%
A69: 22018327 | B69: CARREGADOR USB APPLE 5W BRANCO | C69: CARREGADOR USB APPLE 5W | D69: Branco | E69: Carregador Viagem Apple 5W | F69: Apple | G69: Essenciais | H69: Carregadores | I69: APL02 | K69: NÃO | M69: ELETRÔNICOS | N69: EOL | O69: - | P69: 0% | Q69: 0%
A70: 22018330 | B70: FONE DE OUVIDO APPLE EARPODS BRANCO | C70: FONE DE OUVIDO APPLE EARPODS | D70: Branco | E70: Headphone Apple Earpods | F70: Apple | G70: Áudio | H70: Fones | I70: APL05 | K70: NÃO | M70: ELETRÔNICOS | N70: Out | O70: - | P70: 0% | Q70: 0%
A71: 22018331 | B71: ADAPTADOR LIGTHNING APPLE 3,5MM BRANCO | C71: ADAPTADOR LIGTHNING APPLE 3,5MM | D71: Branco | E71: Adaptador Lightning Apple 3,5MM | F71: Apple | G71: Essenciais | H71: Cabos | I71: APL06 | K71: NÃO | M71: ELETRÔNICOS | N71: EOL | O71: - | P71: 0% | Q71: 0%
A72: 22018364 | B72: CAPA PROT SILICONE IPHONE 7/8 PLUS PRETO | C72: CAPA PROT SILICONE IPHONE 7/8 PLUS | D72: Preto | E72: Capa Silicone Iphone 7/8 Plus | F72: Apple | G72: Essenciais | H72: Capas | I72: APL07 | K72: NÃO | L72: Flagship | M72: ELETRÔNICOS | N72: EOL | O72: - | P72: 0% | Q72: 0%
A73: 22018355 | B73: CAPA DE SILICONE APPLE IPHONE 7/8/SE PT | C73: APPLE CAPA DE SILICONE IPHONE SE/7/8 | D73: Preto | E73: Capa de Silicone Iphone 7/8/SE | F73: Apple | G73: Essenciais | H73: Capas | I73: APL10 | K73: NÃO | L73: Flagship | M73: ELETRÔNICOS | N73: EOL | O73: - | P73: 0% | Q73: 0%
A74: 22018625 | B74: PELICULA DE VIDRO MOTOROLA MOTO G7 PLAY | C74: PELICULA DE VIDRO MOTOROLA MOTO G7 PLAY | D74: N/I | E74: Película Vidro Motorola Moto G7 Play | F74: Customic | G74: Essenciais | H74: Películas | I74: CST21 | K74: NÃO | M74: ELETRÔNICOS | N74: EOL | O74: - | P74: 0% | Q74: 0%
A75: 22018627 | B75: PELICULA DE VIDRO MOTOROLA MOTO G7 POWER | C75: PELICULA DE VIDRO MOTOROLA MOTO G7 POWER | D75: N/I | E75: Película Vidro Motorola Moto G7 Power | F75: Customic | G75: Essenciais | H75: Películas | I75: CST23 | K75: NÃO | M75: ELETRÔNICOS | N75: EOL | O75: - | P75: 0% | Q75: 0%
A76: 22018067 | B76: CABO LIGHTNING EASY MOBILE 1,5M GRAFITE | C76: CABO LIGHTNING EASY MOBILE 1,5M GRAFITE | D76: GRAFITE | E76: Cabo Lightning Easy Mobile 1,5m | F76: Easy Mobile | G76: Essenciais | H76: Cabos | I76: ESY01 | K76: NÃO | M76: ELETRÔNICOS | N76: EOL | O76: - | P76: 0% | Q76: 0%
A77: 22018065 | B77: CABO MICRO EASY MOBILE 1,5M GRAFITE | C77: CABO MICRO EASY MOBILE 1,5M GRAFITE | D77: Grafite | E77: Cabo Micro USB Easy Mobile 1,5m | F77: Easy Mobile | G77: Essenciais | H77: Cabos | I77: ESY02 | K77: NÃO | M77: ELETRÔNICOS | N77: EOL | O77: - | P77: 0% | Q77: 0%
A78: 22018156 | B78: SUPORTE VEICULAR MAGNET EA PRETO | C78: SUPORTE VEICULAR MAGNET EA | D78: Preto | E78: Suporte Veicular Magnético | F78: Easy Mobile | G78: Essenciais | H78: Outros | I78: ESY05 | K78: NÃO | M78: ELETRÔNICOS | N78: EOL | O78: - | P78: 0% | Q78: 0%
A79: 22018185 | B79: REPETIDOR VIVO SMART WI-FI | C79: REPETIDOR VIVO SMART WI-FI | D79: Preto | E79: Repetidor Vivo Smart WI-FI | F79: Mitrastar | G79: Casa Inteligente | H79: Conectividade | I79: FLX01 | J79: Wi-Fi | K79: NÃO | M79: ELETRÔNICOS | N79: EOL | O79: - | P79: 0% | Q79: 0%
A80: 22018145 | B80: HARMAN JBL T110 (PRETO) | C80: HARMAN JBL T110 | D80: Preto | E80: Headphone JBL TUNE 110 | F80: JBL | G80: Áudio | H80: Fones | I80: HAR12 | K80: NÃO | M80: ELETRÔNICOS | N80: EOL | O80: - | P80: 0% | Q80: 0%
A81: 22018325 | B81: HARMAN JBL GO II (PRETO) | C81: HARMAN JBL GO II | D81: Preto | E81: Caixa de Som JBL Go 2 | F81: JBL | G81: Áudio | H81: Caixa de Som | I81: HAR15 | K81: NÃO | M81: ELETRÔNICOS | N81: EOL | O81: - | P81: 0% | Q81: 0%
A82: 22018633 | B82: HARMAN JBL FREE BRANCO | C82: HARMAN JBL FREE | D82: Branco | E82: Headphone JBL Free | F82: JBL | G82: Áudio | H82: Fones | I82: HAR20 | K82: NÃO | M82: ELETRÔNICOS | N82: EOL | O82: - | P82: 0% | Q82: 0%
A83: 22018646 | B83: HARMAN HEADPHONE JBL T500 BT PRETO | C83: HARMAN HEADPHONE JBL T500 BT | D83: Preto | E83: Fone de ouvido JBL T500 BT | F83: JBL | G83: Áudio | H83: Fones | I83: HAR21 | K83: NÃO | M83: ELETRÔNICOS | N83: EOL | O83: - | P83: 0% | Q83: 0%
A84: 22018661 | B84: CABO LIGHTNING USB APPLE 1M BRANCO | C84: CABO LIGTHNING APPLE 1M | D84: Branco | E84: Cabo Lightning Apple 1m | F84: Apple | G84: Essenciais | H84: Cabos | I84: APL01 | K84: NÃO | M84: ELETRÔNICOS | N84: EOL | O84: - | P84: 0% | Q84: 0%
A85: 22018700 | B85: CAPA PROTETORA COURO SAMSUNG S10 PRETO | C85: CAPA PROTETORA COURO SAMSUNG S10 | D85: Preto | E85: Capa Couro Samsung S10 | F85: Samsung | G85: Essenciais | H85: Capas | I85: SSG12 | K85: NÃO | L85: Flagship | M85: ELETRÔNICOS | N85: EOL | O85: - | P85: 0% | Q85: 0%
A86: 22018678 | B86: SAMSUNG BUDS R170 AMARELO | C86: SAMSUNG BUDS R170 | D86: Amarelo | E86: Headphone Samsung Buds R170 | F86: Samsung | G86: Áudio | H86: Fones | I86: SSG27 | K86: NÃO | M86: ELETRÔNICOS | N86: EOL | O86: - | P86: 0% | Q86: 0%
A87: 22018726 | B87: APPLE AIRPODS 2 CARREGADOR COM FIO | C87: APPLE AIRPODS 2 CARREGADOR COM FIO | D87: Branco | E87: AirPods com estojo de recarga | F87: Apple | G87: Áudio | H87: Fones | I87: APL26 | K87: NÃO | M87: ELETRÔNICOS | N87: EOL | O87: - | P87: 0% | Q87: 0%
A88: 22018756 | B88: PELICULA DE VIDRO 3D GALAXY A30/A30S | C88: PELICULA DE VIDRO 3D GALAXY A30/A30S | D88: N/I | E88: Película Vidro Samsung Galaxy A30 3D | F88: Customic | G88: Essenciais | H88: Películas | I88: CST26 | K88: NÃO | M88: ELETRÔNICOS | N88: EOL | O88: - | P88: 0% | Q88: 0%
A89: 22018765 | B89: PELICULA DE VIDRO 3D GALAXY A10/A10S | C89: PELICULA DE VIDRO 3D GALAXY A10/A10S | D89: N/I | E89: Película Vidro Samsung Galaxy A10 3D | F89: Customic | G89: Essenciais | H89: Películas | I89: CST28 | K89: NÃO | M89: ELETRÔNICOS | N89: EOL | O89: - | P89: 0% | Q89: 0%
A90: 22018766 | B90: PELICULA DE VIDRO 3D GALAXY A20 | C90: PELICULA DE VIDRO 3D GALAXY A20 | D90: N/I | E90: Película Vidro Samsung Galaxy A20 3D | F90: Customic | G90: Essenciais | H90: Películas | I90: CST29 | K90: NÃO | M90: ELETRÔNICOS | N90: EOL | O90: - | P90: 0% | Q90: 0%
A91: 22018797 | B91: CAPA LAUT ACCENTS VD IPHONE X/XS CORAL | C91: CAPA LAUT ACCENTS VD IPHONE X/XS | D91: Coral | E91: Capa Vidro Accents Iphone X/XS | F91: Laut | G91: Essenciais | H91: Capas | I91: COM51 | K91: NÃO | L91: Flagship | M91: ELETRÔNICOS | N91: EOL | O91: - | P91: 0% | Q91: 0%
A92: 22018796 | B92: CAPA LAUT ACCENTS VIDRO IPHONE XR CORAL | C92: CAPA LAUT ACCENTS VIDRO IPHONE XR | D92: Coral | E92: Capa Vidro Accents Iphone XR | F92: Laut | G92: Essenciais | H92: Capas | I92: COM52 | K92: NÃO | L92: Flagship | M92: ELETRÔNICOS | N92: EOL | O92: - | P92: 0% | Q92: 0%
A93: 22018571 | B93: CAPA LAUT ACCENTS VIDRO IPHONE XR PRETO | C93: CAPA LAUT ACCENTS VIDRO IPHONE XR | D93: Preto | E93: Capa Vidro Accents Iphone XR | F93: Laut | G93: Essenciais | H93: Capas | I93: COM52 | K93: NÃO | L93: Flagship | M93: ELETRÔNICOS | N93: EOL | O93: - | P93: 0% | Q93: 0%
A94: 22018570 | B94: CAPA LAUT ACCENTS VIDRO IPHONE X/XS PT | C94: CAPA LAUT ACCENTS VD IPHONE X/XS | D94: Preto | E94: Capa Vidro Accents Iphone X/XS | F94: Laut | G94: Essenciais | H94: Capas | I94: COM51 | K94: NÃO | L94: Flagship | M94: ELETRÔNICOS | N94: EOL | O94: - | P94: 0% | Q94: 0%
A95: 22018572 | B95: CAPA LAUT ACCENTS VD IPHONE XS MAX PRETO | C95: CAPA LAUT ACCENTS VD IPHONE XS MAX | D95: Preto | E95: Capa Vidro Accents Iphone XS Max | F95: Laut | G95: Essenciais | H95: Capas | I95: COM50 | K95: NÃO | L95: Flagship | M95: ELETRÔNICOS | N95: EOL | O95: - | P95: 0% | Q95: 0%
A96: 22018573 | B96: CAPA LAUT FLURO CRYSTAL IPHONE X/XS ONIX | C96: CAPA LAUT FLURO CRYSTAL IPHONE X/XS ONIX | D96: Onix | E96: Capa Crystal Fluro Iphone X/XS | F96: Laut | G96: Essenciais | H96: Capas | I96: COM54 | K96: NÃO | L96: Flagship | M96: ELETRÔNICOS | N96: EOL | O96: - | P96: 0% | Q96: 0%
A97: 22018568 | B97: CAPA LAUT FLURO CRYSTAL IPHONE XS MAX PT | C97: CAPA LAUT FLURO CRYSTAL IPHONE XS MAX | D97: Preto | E97: Capa Crystal Fluro Iphone XS Max | F97: Laut | G97: Essenciais | H97: Capas | I97: COM55 | K97: NÃO | L97: Flagship | M97: ELETRÔNICOS | N97: EOL | O97: - | P97: 0% | Q97: 0%
A98: 22018585 | B98: CAPA LAUT SHIELD IPHONE XR PRETO | C98: CAPA LAUT SHIELD IPHONE XR | D98: Preto | E98: Capa Shield Iphone XR | F98: Laut | G98: Essenciais | H98: Capas | I98: COM56 | K98: NÃO | L98: Flagship | M98: ELETRÔNICOS | N98: EOL | O98: - | P98: 0% | Q98: 0%
A99: 22018816 | B99: SAMSUNG GALAXY R370 FIT PRATA | C99: SAMSUNG GALAXY R370 FIT | D99: Prata | E99: Galaxy Watch FIT | F99: Samsung | G99: Bem Estar | H99: Smartwatch | I99: SSG23 | J99: Bluetooth | K99: NÃO | L99: Wearable | M99: ELETRÔNICOS | N99: EOL | O99: - | P99: 0% | Q99: 0%
A100: 22018928 | B100: MOUSE GAMER LOGITECH G502 HERO PRETO | C100: MOUSE GAMER LOGITECH G502 HERO | D100: Preto | E100: Mouse Gamer Hero Logitech G502 | F100: Logitech | G100: Games | H100: Acessórios para Games | I100: ALF75 | K100: NÃO | M100: ELETRÔNICOS | N100: EOL | O100: - | P100: 0% | Q100: 0.1
A101: 22018930 | B101: MOUSE PAD GAMER LOGITECH G640 PRETO | C101: MOUSE PAD GAMER LOGITECH G640 | D101: Preto | E101: Mouse Pad Gamer Logitech G640 | F101: Logitech | G101: Games | H101: Acessórios para Games | I101: ALF77 | K101: NÃO | M101: ELETRÔNICOS | N101: EOL | O101: - | P101: 0% | Q101: 0.1
A102: 22018931 | B102: TECLADO GAMER LOGITECH G413 ABNT2 PRETO | C102: TECLADO GAMER LOGITECH G413 ABNT2 | D102: Preto | E102: Teclado Gamer ABNT2 Logitech G413 | F102: Logitech | G102: Notebook e Tablets | H102: Acessórios para Notebook e Tablets | I102: ALF78 | K102: NÃO | M102: ELETRÔNICOS | N102: EOL | O102: - | P102: 0% | Q102: 0.1
A103: 22018832 | B103: RAZER MOUSE DEATHADDER ESSENTIAL PRETO | C103: RAZER MOUSE DEATHADDER ESSENTIAL | D103: Preto | E103: Mouse Deathadder Essential Razer | F103: Razer | G103: Games | H103: Acessórios para Games | I103: RZR01 | K103: NÃO | M103: ELETRÔNICOS | N103: EOL | O103: - | P103: 0% | Q103: 0.1
A104: 22018847 | B104: RAZER MOUSE DEATHADDER ELITE PRETO | C104: RAZER MOUSE DEATHADDER ELITE | D104: Preto | E104: Mouse Deathadder Elite Razer | F104: Razer | G104: Games | H104: Acessórios para Games | I104: RZR04 | K104: NÃO | M104: ELETRÔNICOS | N104: EOL | O104: - | P104: 0% | Q104: 0.1
A105: 22018946 | B105: MOUSEPAD RAZER GOLIATHUS LARGE SPEED CM | C105: MOUSEPAD RAZER GOLIATHUS LARGE SPEED CM | D105: Preto | E105: Mouse Pad Goliathus Large Razer | F105: Razer | G105: Games | H105: Acessórios para Games | I105: RZR06 | K105: NÃO | M105: ELETRÔNICOS | N105: EOL | O105: - | P105: 0% | Q105: 0.1
A106: 22018882 | B106: PELÍCULA DE VIDRO 3D GALAXY A70 | C106: PELÍCULA DE VIDRO 3D GALAXY A70 | D106: N/I | E106: Película Vidro Samsung Galaxy A70 3D | F106: Customic | G106: Essenciais | H106: Películas | I106: CST30 | K106: NÃO | M106: ELETRÔNICOS | N106: EOL | O106: - | P106: 0% | Q106: 0%
...

Sheet SMARTPHONES
E1: SMARTPHONES e WATCHES CONECTADOS | NS1: TABELA ANTERIOR
E2: Vigência a partir de: 15/09/2026 | F2: TABELA REGULAR | GW2: TABELA RENOVA | NS2: TABELA REGULAR | OC2: TABELA RENOVA | ON2: Δ | OO2: Δ Renova | OQ2: TABELA REGULAR - Itaú Black e Platinum (Master), Itaú Infinite e Signature (Visa), Caixa (CEF), Santander, Banco do Brasil Ourocard (Via, Elo e Master) Sicredi, Banrisul (Visa e Master) e Banco BRB somente em até 18x | OZ2: TABELA REGULAR - Demais Cartões | PI2: TABELA REGULAR - Itaú Black e Platinum (Master), Itaú Infinite e Signature (Visa), Caixa (CEF), Santander, Banco do Brasil Ourocard (Via, Elo e Master) Sicredi, Banrisul (Visa e Master) e Banco BRB somente em até 18x | PR2: TABELA RENOVA - Demais Cartões
A3: PORTFÓLIO | B3: CATEGORIA | C3: MARCA | D3: OFERTA DE COMUNICAÇÃO | E3: Nome Comercial | F3: PRÉ | G3: PIX e Vivo Pay | H3: 2x | I3: 3x | J3: 4x | K3: 5x | L3: 6x | M3: 7x | N3: 8x | O3: 9x | P3: 10x | Q3: 11x | R3: 12x | S3: 13x | T3: 14x | U3: 15x | V3: 16x | W3: 17x | X3: 18x | Y3: 19x | Z3: 20x | AA3: 21x | AB3: CONTROLE BTL | AC3: PIX e Vivo Pay | AD3: 2x | AE3: 3x | AF3: 4x | AG3: 5x | AH3: 6x | AI3: 7x | AJ3: 8x | AK3: 9x | AL3: 10x | AM3: 11x | AN3: 12x | AO3: 13x | AP3: 14x | AQ3: 15x | AR3: 16x | AS3: 17x | AT3: 18x | AU3: 19x | AV3: 20x | AW3: 21x | AX3: CONTROLE ENTRADA | AY3: PIX e Vivo Pay | AZ3: 2x | BA3: 3x | BB3: 4x | BC3: 5x | BD3: 6x | BE3: 7x | BF3: 8x | BG3: 9x | BH3: 10x | BI3: 11x | BJ3: 12x | BK3: 13x | BL3: 14x | BM3: 15x | BN3: 16x | BO3: 17x | BP3: 18x | BQ3: 19x | BR3: 20x | BS3: 21x | BT3: CONTROLE ALTO VALOR | BU3: PIX e Vivo Pay | BV3: 2x | BW3: 3x | BX3: 4x | BY3: 5x | BZ3: 6x | CA3: 7x | CB3: 8x | CC3: 9x | CD3: 10x | CE3: 11x | CF3: 12x | CG3: 13x | CH3: 14x | CI3: 15x | CJ3: 16x | CK3: 17x | CL3: 18x | CM3: 19x | CN3: 20x | CO3: 21x | CP3: PÓS INDIVIDUAL | CQ3: PIX e Vivo Pay | CR3: 2x | CS3: 3x | CT3: 4x | CU3: 5x | CV3: 6x | CW3: 7x | CX3: 8x | CY3: 9x | CZ3: 10x | DA3: 11x | DB3: 12x | DC3: 13x | DD3: 14x | DE3: 15x | DF3: 16x | DG3: 17x | DH3: 18x | DI3: 19x | DJ3: 20x | DK3: 21x | DL3: FAMILIA 2 | DM3: PIX e Vivo Pay | DN3: 2x | DO3: 3x | DP3: 4x | DQ3: 5x | DR3: 6x | DS3: 7x | DT3: 8x | DU3: 9x | DV3: 10x | DW3: 11x | DX3: 12x | DY3: 13x | DZ3: 14x | EA3: 15x | EB3: 16x | EC3: 17x | ED3: 18x | EE3: 19x | EF3: 20x | EG3: 21x | EH3: FAMILIA 3 | EI3: PIX e Vivo Pay | EJ3: 2x | EK3: 3x | EL3: 4x | EM3: 5x | EN3: 6x | EO3: 7x | EP3: 8x | EQ3: 9x | ER3: 10x | ES3: 11x | ET3: 12x | EU3: 13x | EV3: 14x | EW3: 15x | EX3: 16x | EY3: 17x | EZ3: 18x | FA3: 19x | FB3: 20x | FC3: 21x | FD3: FAMILIA 4/5 | FE3: PIX e Vivo Pay | FF3: 2x | FG3: 3x | FH3: 4x | FI3: 5x | FJ3: 6x | FK3: 7x | FL3: 8x | FM3: 9x | FN3: 10x | FO3: 11x | FP3: 12x | FQ3: 13x | FR3: 14x | FS3: 15x | FT3: 16x | FU3: 17x | FV3: 18x | FW3: 19x | FX3: 20x | FY3: 21x | FZ3: VIVO V | GA3: PIX e Vivo Pay | GB3: 2x | GC3: 3x | GD3: 4x | GE3: 5x | GF3: 6x | GG3: 7x | GH3: 8x | GI3: 9x | GJ3: 10x | GK3: 11x | GL3: 12x | GM3: 13x | GN3: 14x | GO3: 15x | GP3: 16x | GQ3: 17x | GR3: 18x | GS3: 19x | GT3: 20x | GU3: 21x | GW3: DESCONTO | GX3: CONTROLE BTL | GY3: PIX e Vivo Pay | GZ3: 2x | HA3: 3x | HB3: 4x | HC3: 5x | HD3: 6x | HE3: 7x | HF3: 8x | HG3: 9x | HH3: 10x | HI3: 11x | HJ3: 12x | HK3: 13x | HL3: 14x | HM3: 15x | HN3: 16x | HO3: 17x | HP3: 18x | HQ3: 19x | HR3: 20x | HS3: 21x | HT3: CONTROLE ENTRADA | HU3: PIX e Vivo Pay | HV3: 2x | HW3: 3x | HX3: 4x | HY3: 5x | HZ3: 6x | IA3: 7x | IB3: 8x | IC3: 9x | ID3: 10x | IE3: 11x | IF3: 12x | IG3: 13x | IH3: 14x | II3: 15x | IJ3: 16x | IK3: 17x | IL3: 18x | IM3: 19x | IN3: 20x | IO3: 21x | IP3: CONTROLE ALTO VALOR | IQ3: PIX e Vivo Pay | IR3: 2x | IS3: 3x | IT3: 4x | IU3: 5x | IV3: 6x | IW3: 7x | IX3: 8x | IY3: 9x | IZ3: 10x | JA3: 11x | JB3: 12x | JC3: 13x | JD3: 14x | JE3: 15x | JF3: 16x | JG3: 17x | JH3: 18x | JI3: 19x | JJ3: 20x | JK3: 21x | JL3: PÓS INDIVIDUAL | JM3: PIX e Vivo Pay | JN3: 2x | JO3: 3x | JP3: 4x | JQ3: 5x | JR3: 6x | JS3: 7x | JT3: 8x | JU3: 9x | JV3: 10x | JW3: 11x | JX3: 12x | JY3: 13x | JZ3: 14x | KA3: 15x | KB3: 16x | KC3: 17x | KD3: 18x | KE3: 19x | KF3: 20x | KG3: 21x | KH3: FAMILIA 2 | KI3: PIX e Vivo Pay | KJ3: 2x | KK3: 3x | KL3: 4x | KM3: 5x | KN3: 6x | KO3: 7x | KP3: 8x | KQ3: 9x | KR3: 10x | KS3: 11x | KT3: 12x | KU3: 13x | KV3: 14x | KW3: 15x | KX3: 16x | KY3: 17x | KZ3: 18x | LA3: 19x | LB3: 20x | LC3: 21x | LD3: FAMILIA 3 | LE3: PIX e Vivo Pay | LF3: 2x | LG3: 3x | LH3: 4x | LI3: 5x | LJ3: 6x | LK3: 7x | LL3: 8x | LM3: 9x | LN3: 10x | LO3: 11x | LP3: 12x | LQ3: 13x | LR3: 14x | LS3: 15x | LT3: 16x | LU3: 17x | LV3: 18x | LW3: 19x | LX3: 20x | LY3: 21x | LZ3: FAMILIA 4/5 | MA3: PIX e Vivo Pay | MB3: 2x | MC3: 3x | MD3: 4x | ME3: 5x | MF3: 6x | MG3: 7x | MH3: 8x | MI3: 9x | MJ3: 10x | MK3: 11x | ML3: 12x | MM3: 13x | MN3: 14x | MO3: 15x | MP3: 16x | MQ3: 17x | MR3: 18x | MS3: 19x | MT3: 20x | MU3: 21x | MV3: VIVO V | MW3: PIX e Vivo Pay | MX3: 2x | MY3: 3x | MZ3: 4x | NA3: 5x | NB3: 6x | NC3: 7x | ND3: 8x | NE3: 9x | NF3: 10x | NG3: 11x | NH3: 12x | NI3: 13x | NJ3: 14x | NK3: 15x | NL3: 16x | NM3: 17x | NN3: 18x | NO3: 19x | NP3: 20x | NQ3: 21x | NS3: PRÉ | NT3: CONTROLE BTL | NU3: CONTROLE ENTRADA | NV3: CONTROLE ALTO VALOR | NW3: PÓS INDIVIDUAL | NX3: FAMILIA 2 | NY3: FAMILIA 3 | NZ3: FAMILIA 4/5 | OA3: VIVO V | OC3: DESCONTO | OD3: CONTROLE BTL | OE3: CONTROLE ENTRADA | OF3: CONTROLE ALTO VALOR | OG3: PÓS INDIVIDUAL | OH3: FAMILIA 2 | OI3: FAMILIA 3 | OJ3: FAMILIA 4/5 | OK3: VIVO V | OL3: Δ | OM3: Δ Renova | ON3: 8 | OO3: 1 | OQ3: CONTROLE BTL | OR3: CONTROLE ENTRADA | OS3: CONTROLE ALTO VALOR | OT3: PÓS INDIVIDUAL | OU3: FAMILIA 2 | OV3: FAMILIA 3 | OW3: FAMILIA 4/5 | OX3: VIVO V | OZ3: CONTROLE BTL | PA3: CONTROLE ENTRADA | PB3: CONTROLE ALTO VALOR | PC3: PÓS INDIVIDUAL | PD3: FAMILIA 2 | PE3: FAMILIA 3 | PF3: FAMILIA 4/5 | PG3: VIVO V | PI3: CONTROLE BTL | PJ3: CONTROLE ENTRADA | PK3: CONTROLE ALTO VALOR | PL3: PÓS INDIVIDUAL | PM3: FAMILIA 2 | PN3: FAMILIA 3 | PO3: FAMILIA 4/5 | PP3: VIVO V | PR3: CONTROLE BTL | PS3: CONTROLE ENTRADA | PT3: CONTROLE ALTO VALOR | PU3: PÓS INDIVIDUAL | PV3: FAMILIA 2 | PW3: FAMILIA 3 | PX3: FAMILIA 4/5 | PY3: VIVO V
A4: EOL | B4: Smartphone | C4: Apple | D4: Vivo Total Família 3 | E4: iPhone SE 5G 128GB | F4: 3399 | G4: 3059.1 | H4: 3399 | I4: 3399 | J4: 3399 | K4: 3399 | L4: 3399 | M4: 3399 | N4: 3399 | O4: 3399 | P4: 3399 | Q4: 3399 | R4: 3399 | S4: 3662.25 | T4: 3681.55 | U4: 3700.91 | V4: 3720.35 | W4: 3739.84 | X4: 3759.4 | Y4: 3779.03 | Z4: 3798.73 | AA4: 3818.49 | AB4: 3399 | AC4: 3059.1 | AD4: 3399 | AE4: 3399 | AF4: 3399 | AG4: 3399 | AH4: 3399 | AI4: 3399 | AJ4: 3399 | AK4: 3399 | AL4: 3399 | AM4: 3399 | AN4: 3399 | AO4: 3662.25 | AP4: 3681.55 | AQ4: 3700.91 | AR4: 3720.35 | AS4: 3739.84 | AT4: 3759.4 | AU4: 3779.03 | AV4: 3798.73 | AW4: 3818.49 | AX4: 3399 | AY4: 3059.1 | AZ4: 3399 | BA4: 3399 | BB4: 3399 | BC4: 3399 | BD4: 3399 | BE4: 3399 | BF4: 3399 | BG4: 3399 | BH4: 3399 | BI4: 3399 | BJ4: 3399 | BK4: 3662.25 | BL4: 3681.55 | BM4: 3700.91 | BN4: 3720.35 | BO4: 3739.84 | BP4: 3759.4 | BQ4: 3779.03 | BR4: 3798.73 | BS4: 3818.49 | BT4: 3399 | BU4: 3059.1 | BV4: 3399 | BW4: 3399 | BX4: 3399 | BY4: 3399 | BZ4: 3399 | CA4: 3399 | CB4: 3399 | CC4: 3399 | CD4: 3399 | CE4: 3399 | CF4: 3399 | CG4: 3662.25 | CH4: 3681.55 | CI4: 3700.91 | CJ4: 3720.35 | CK4: 3739.84 | CL4: 3759.4 | CM4: 3779.03 | CN4: 3798.73 | CO4: 3818.49 | CP4: 2799 | CQ4: 2519.1 | CR4: 2799 | CS4: 2799 | CT4: 2799 | CU4: 2799 | CV4: 2799 | CW4: 2799 | CX4: 2799 | CY4: 2799 | CZ4: 2799 | DA4: 2799 | DB4: 2799 | DC4: 3015.78 | DD4: 3031.67 | DE4: 3047.62 | DF4: 3063.62 | DG4: 3079.68 | DH4: 3095.78 | DI4: 3111.95 | DJ4: 3128.17 | DK4: 3144.44 | DL4: 2399 | DM4: 2159.1 | DN4: 2399 | DO4: 2399 | DP4: 2399 | DQ4: 2399 | DR4: 2399 | DS4: 2399 | DT4: 2399 | DU4: 2399 | DV4: 2399 | DW4: 2399 | DX4: 2399 | DY4: 2584.8 | DZ4: 2598.42 | EA4: 2612.09 | EB4: 2625.8 | EC4: 2639.56 | ED4: 2653.37 | EE4: 2667.23 | EF4: 2681.13 | EG4: 2695.07 | EH4: 2399 | EI4: 2159.1 | EJ4: 2399 | EK4: 2399 | EL4: 2399 | EM4: 2399 | EN4: 2399 | EO4: 2399 | EP4: 2399 | EQ4: 2399 | ER4: 2399 | ES4: 2399 | ET4: 2399 | EU4: 2584.8 | EV4: 2598.42 | EW4: 2612.09 | EX4: 2625.8 | EY4: 2639.56 | EZ4: 2653.37 | FA4: 2667.23 | FB4: 2681.13 | FC4: 2695.07 | FD4: 2299 | FE4: 2069.1 | FF4: 2299 | FG4: 2299 | FH4: 2299 | FI4: 2299 | FJ4: 2299 | FK4: 2299 | FL4: 2299 | FM4: 2299 | FN4: 2299 | FO4: 2299 | FP4: 2299 | FQ4: 2477.06 | FR4: 2490.11 | FS4: 2503.21 | FT4: 2516.35 | FU4: 2529.54 | FV4: 2542.77 | FW4: 2556.04 | FX4: 2569.37 | FY4: 2582.73 | FZ4: 2099 | GA4: 1889.1 | GB4: 2099 | GC4: 2099 | GD4: 2099 | GE4: 2099 | GF4: 2099 | GG4: 2099 | GH4: 2099 | GI4: 2099 | GJ4: 2099 | GK4: 2099 | GL4: 2099 | GM4: 2261.57 | GN4: 2273.48 | GO4: 2285.44 | GP4: 2297.44 | GQ4: 2309.48 | GR4: 2321.56 | GS4: 2333.68 | GT4: 2345.85 | GU4: 2358.05 | GW4: 0 | GX4: 3399 | GY4: 3059.1 | GZ4: 3399 | HA4: 3399 | HB4: 3399 | HC4: 3399 | HD4: 3399 | HE4: 3399 | HF4: 3399 | HG4: 3399 | HH4: 3399 | HI4: 3399 | HJ4: 3399 | HK4: 3662.25 | HL4: 3681.55 | HM4: 3700.91 | HN4: 3720.35 | HO4: 3739.84 | HP4: 3759.4 | HQ4: 3779.03 | HR4: 3798.73 | HS4: 3818.49 | HT4: 3399 | HU4: 3059.1 | HV4: 3399 | HW4: 3399 | HX4: 3399 | HY4: 3399 | HZ4: 3399 | IA4: 3399 | IB4: 3399 | IC4: 3399 | ID4: 3399 | IE4: 3399 | IF4: 3399 | IG4: 3662.25 | IH4: 3681.55 | II4: 3700.91 | IJ4: 3720.35 | IK4: 3739.84 | IL4: 3759.4 | IM4: 3779.03 | IN4: 3798.73 | IO4: 3818.49 | IP4: 3399 | IQ4: 3059.1 | IR4: 3399 | IS4: 3399 | IT4: 3399 | IU4: 3399 | IV4: 3399 | IW4: 3399 | IX4: 3399 | IY4: 3399 | IZ4: 3399 | JA4: 3399 | JB4: 3399 | JC4: 3662.25 | JD4: 3681.55 | JE4: 3700.91 | JF4: 3720.35 | JG4: 3739.84 | JH4: 3759.4 | JI4: 3779.03 | JJ4: 3798.73 | JK4: 3818.49 | JL4: 2799 | JM4: 2519.1 | JN4: 2799 | JO4: 2799 | JP4: 2799 | JQ4: 2799 | JR4: 2799 | JS4: 2799 | JT4: 2799 | JU4: 2799 | JV4: 2799 | JW4: 2799 | JX4: 2799 | JY4: 3015.78 | JZ4: 3031.67 | KA4: 3047.62 | KB4: 3063.62 | KC4: 3079.68 | KD4: 3095.78 | KE4: 3111.95 | KF4: 3128.17 | KG4: 3144.44 | KH4: 2399 | KI4: 2159.1 | KJ4: 2399 | KK4: 2399 | KL4: 2399 | KM4: 2399 | KN4: 2399 | KO4: 2399 | KP4: 2399 | KQ4: 2399 | KR4: 2399 | KS4: 2399 | KT4: 2399 | KU4: 2584.8 | KV4: 2598.42 | KW4: 2612.09 | KX4: 2625.8 | KY4: 2639.56 | KZ4: 2653.37 | LA4: 2667.23 | LB4: 2681.13 | LC4: 2695.07 | LD4: 2399 | LE4: 2159.1 | LF4: 2399 | LG4: 2399 | LH4: 2399 | LI4: 2399 | LJ4: 2399 | LK4: 2399 | LL4: 2399 | LM4: 2399 | LN4: 2399 | LO4: 2399 | LP4: 2399 | LQ4: 2584.8 | LR4: 2598.42 | LS4: 2612.09 | LT4: 2625.8 | LU4: 2639.56 | LV4: 2653.37 | LW4: 2667.23 | LX4: 2681.13 | LY4: 2695.07 | LZ4: 2299 | MA4: 2069.1 | MB4: 2299 | MC4: 2299 | MD4: 2299 | ME4: 2299 | MF4: 2299 | MG4: 2299 | MH4: 2299 | MI4: 2299 | MJ4: 2299 | MK4: 2299 | ML4: 2299 | MM4: 2477.06 | MN4: 2490.11 | MO4: 2503.21 | MP4: 2516.35 | MQ4: 2529.54 | MR4: 2542.77 | MS4: 2556.04 | MT4: 2569.37 | MU4: 2582.73 | MV4: 2099 | MW4: 1889.1 | MX4: 2099 | MY4: 2099 | MZ4: 2099 | NA4: 2099 | NB4: 2099 | NC4: 2099 | ND4: 2099 | NE4: 2099 | NF4: 2099 | NG4: 2099 | NH4: 2099 | NI4: 2261.57 | NJ4: 2273.48 | NK4: 2285.44 | NL4: 2297.44 | NM4: 2309.48 | NN4: 2321.56 | NO4: 2333.68 | NP4: 2345.85 | NQ4: 2358.05 | NS4: 3399 | NT4: 3399 | NU4: 3399 | NV4: 3399 | NW4: 2799 | NX4: 2399 | NY4: 2399 | NZ4: 2299 | OA4: 2099 | OC4: 0 | OD4: 3399 | OE4: 3399 | OF4: 3399 | OG4: 2799 | OH4: 2399 | OI4: 2399 | OJ4: 2299 | OK4: 2099 | OL4: 0 | OM4: 0 | OQ4: 21x | OR4: 21x | OS4: 21x | OT4: 21x | OU4: 21x | OV4: 21x | OW4: 21x | OX4: 21x | OZ4: 12x | PA4: 12x | PB4: 12x | PC4: 12x | PD4: 12x | PE4: 12x | PF4: 12x | PG4: 12x | PI4: 21x | PJ4: 21x | PK4: 21x | PL4: 21x | PM4: 21x | PN4: 21x | PO4: 21x | PP4: 21x | PR4: 12x | PS4: 12x | PT4: 12x | PU4: 12x | PV4: 12x | PW4: 12x | PX4: 12x | PY4: 12x
A5: EOL | B5: Smartphone | C5: Apple | D5: Vivo Total Família 3 | E5: iPhone SE 5G 64GB | F5: 2899 | G5: 2609.1 | H5: 2899 | I5: 2899 | J5: 2899 | K5: 2899 | L5: 2899 | M5: 2899 | N5: 2899 | O5: 2899 | P5: 2899 | Q5: 2899 | R5: 2899 | S5: 3123.53 | T5: 3139.99 | U5: 3156.5 | V5: 3173.07 | W5: 3189.7 | X5: 3206.39 | Y5: 3223.13 | Z5: 3239.93 | AA5: 3256.78 | AB5: 2899 | AC5: 2609.1 | AD5: 2899 | AE5: 2899 | AF5: 2899 | AG5: 2899 | AH5: 2899 | AI5: 2899 | AJ5: 2899 | AK5: 2899 | AL5: 2899 | AM5: 2899 | AN5: 2899 | AO5: 3123.53 | AP5: 3139.99 | AQ5: 3156.5 | AR5: 3173.07 | AS5: 3189.7 | AT5: 3206.39 | AU5: 3223.13 | AV5: 3239.93 | AW5: 3256.78 | AX5: 2899 | AY5: 2609.1 | AZ5: 2899 | BA5: 2899 | BB5: 2899 | BC5: 2899 | BD5: 2899 | BE5: 2899 | BF5: 2899 | BG5: 2899 | BH5: 2899 | BI5: 2899 | BJ5: 2899 | BK5: 3123.53 | BL5: 3139.99 | BM5: 3156.5 | BN5: 3173.07 | BO5: 3189.7 | BP5: 3206.39 | BQ5: 3223.13 | BR5: 3239.93 | BS5: 3256.78 | BT5: 2849 | BU5: 2564.1 | BV5: 2849 | BW5: 2849 | BX5: 2849 | BY5: 2849 | BZ5: 2849 | CA5: 2849 | CB5: 2849 | CC5: 2849 | CD5: 2849 | CE5: 2849 | CF5: 2849 | CG5: 3069.65 | CH5: 3085.83 | CI5: 3102.06 | CJ5: 3118.35 | CK5: 3134.69 | CL5: 3151.09 | CM5: 3167.54 | CN5: 3184.05 | CO5: 3200.61 | CP5: 2299 | CQ5: 2069.1 | CR5: 2299 | CS5: 2299 | CT5: 2299 | CU5: 2299 | CV5: 2299 | CW5: 2299 | CX5: 2299 | CY5: 2299 | CZ5: 2299 | DA5: 2299 | DB5: 2299 | DC5: 2477.06 | DD5: 2490.11 | DE5: 2503.21 | DF5: 2516.35 | DG5: 2529.54 | DH5: 2542.77 | DI5: 2556.04 | DJ5: 2569.37 | DK5: 2582.73 | DL5: 1899 | DM5: 1709.1 | DN5: 1899 | DO5: 1899 | DP5: 1899 | DQ5: 1899 | DR5: 1899 | DS5: 1899 | DT5: 1899 | DU5: 1899 | DV5: 1899 | DW5: 1899 | DX5: 1899 | DY5: 2046.08 | DZ5: 2056.86 | EA5: 2067.68 | EB5: 2078.53 | EC5: 2089.43 | ED5: 2100.36 | EE5: 2111.32 | EF5: 2122.32 | EG5: 2133.36 | EH5: 1849 | EI5: 1664.1 | EJ5: 1849 | EK5: 1849 | EL5: 1849 | EM5: 1849 | EN5: 1849 | EO5: 1849 | EP5: 1849 | EQ5: 1849 | ER5: 1849 | ES5: 1849 | ET5: 1849 | EU5: 1992.2 | EV5: 2002.7 | EW5: 2013.24 | EX5: 2023.81 | EY5: 2034.41 | EZ5: 2045.05 | FA5: 2055.73 | FB5: 2066.44 | FC5: 2077.19 | FD5: 1799 | FE5: 1619.1 | FF5: 1799 | FG5: 1799 | FH5: 1799 | FI5: 1799 | FJ5: 1799 | FK5: 1799 | FL5: 1799 | FM5: 1799 | FN5: 1799 | FO5: 1799 | FP5: 1799 | FQ5: 1938.33 | FR5: 1948.55 | FS5: 1958.8 | FT5: 1969.08 | FU5: 1979.4 | FV5: 1989.75 | FW5: 2000.14 | FX5: 2010.56 | FY5: 2021.02 | FZ5: 1599 | GA5: 1439.1 | GB5: 1599 | GC5: 1599 | GD5: 1599 | GE5: 1599 | GF5: 1599 | GG5: 1599 | GH5: 1599 | GI5: 1599 | GJ5: 1599 | GK5: 1599 | GL5: 1599 | GM5: 1722.84 | GN5: 1731.92 | GO5: 1741.03 | GP5: 1750.17 | GQ5: 1759.34 | GR5: 1768.55 | GS5: 1777.78 | GT5: 1787.04 | GU5: 1796.34 | GW5: 0 | GX5: 2899 | GY5: 2609.1 | GZ5: 2899 | HA5: 2899 | HB5: 2899 | HC5: 2899 | HD5: 2899 | HE5: 2899 | HF5: 2899 | HG5: 2899 | HH5: 2899 | HI5: 2899 | HJ5: 2899 | HK5: 3123.53 | HL5: 3139.99 | HM5: 3156.5 | HN5: 3173.07 | HO5: 3189.7 | HP5: 3206.39 | HQ5: 3223.13 | HR5: 3239.93 | HS5: 3256.78 | HT5: 2899 | HU5: 2609.1 | HV5: 2899 | HW5: 2899 | HX5: 2899 | HY5: 2899 | HZ5: 2899 | IA5: 2899 | IB5: 2899 | IC5: 2899 | ID5: 2899 | IE5: 2899 | IF5: 2899 | IG5: 3123.53 | IH5: 3139.99 | II5: 3156.5 | IJ5: 3173.07 | IK5: 3189.7 | IL5: 3206.39 | IM5: 3223.13 | IN5: 3239.93 | IO5: 3256.78 | IP5: 2849 | IQ5: 2564.1 | IR5: 2849 | IS5: 2849 | IT5: 2849 | IU5: 2849 | IV5: 2849 | IW5: 2849 | IX5: 2849 | IY5: 2849 | IZ5: 2849 | JA5: 2849 | JB5: 2849 | JC5: 3069.65 | JD5: 3085.83 | JE5: 3102.06 | JF5: 3118.35 | JG5: 3134.69 | JH5: 3151.09 | JI5: 3167.54 | JJ5: 3184.05 | JK5: 3200.61 | JL5: 2299 | JM5: 2069.1 | JN5: 2299 | JO5: 2299 | JP5: 2299 | JQ5: 2299 | JR5: 2299 | JS5: 2299 | JT5: 2299 | JU5: 2299 | JV5: 2299 | JW5: 2299 | JX5: 2299 | JY5: 2477.06 | JZ5: 2490.11 | KA5: 2503.21 | KB5: 2516.35 | KC5: 2529.54 | KD5: 2542.77 | KE5: 2556.04 | KF5: 2569.37 | KG5: 2582.73 | KH5: 1899 | KI5: 1709.1 | KJ5: 1899 | KK5: 1899 | KL5: 1899 | KM5: 1899 | KN5: 1899 | KO5: 1899 | KP5: 1899 | KQ5: 1899 | KR5: 1899 | KS5: 1899 | KT5: 1899 | KU5: 2046.08 | KV5: 2056.86 | KW5: 2067.68 | KX5: 2078.53 | KY5: 2089.43 | KZ5: 2100.36 | LA5: 2111.32 | LB5: 2122.32 | LC5: 2133.36 | LD5: 1849 | LE5: 1664.1 | LF5: 1849 | LG5: 1849 | LH5: 1849 | LI5: 1849 | LJ5: 1849 | LK5: 1849 | LL5: 1849 | LM5: 1849 | LN5: 1849 | LO5: 1849 | LP5: 1849 | LQ5: 1992.2 | LR5: 2002.7 | LS5: 2013.24 | LT5: 2023.81 | LU5: 2034.41 | LV5: 2045.05 | LW5: 2055.73 | LX5: 2066.44 | LY5: 2077.19 | LZ5: 1799 | MA5: 1619.1 | MB5: 1799 | MC5: 1799 | MD5: 1799 | ME5: 1799 | MF5: 1799 | MG5: 1799 | MH5: 1799 | MI5: 1799 | MJ5: 1799 | MK5: 1799 | ML5: 1799 | MM5: 1938.33 | MN5: 1948.55 | MO5: 1958.8 | MP5: 1969.08 | MQ5: 1979.4 | MR5: 1989.75 | MS5: 2000.14 | MT5: 2010.56 | MU5: 2021.02 | MV5: 1599 | MW5: 1439.1 | MX5: 1599 | MY5: 1599 | MZ5: 1599 | NA5: 1599 | NB5: 1599 | NC5: 1599 | ND5: 1599 | NE5: 1599 | NF5: 1599 | NG5: 1599 | NH5: 1599 | NI5: 1722.84 | NJ5: 1731.92 | NK5: 1741.03 | NL5: 1750.17 | NM5: 1759.34 | NN5: 1768.55 | NO5: 1777.78 | NP5: 1787.04 | NQ5: 1796.34 | NS5: 2899 | NT5: 2899 | NU5: 2899 | NV5: 2849 | NW5: 2299 | NX5: 1899 | NY5: 1849 | NZ5: 1799 | OA5: 1599 | OC5: 0 | OD5: 2899 | OE5: 2899 | OF5: 2849 | OG5: 2299 | OH5: 1899 | OI5: 1849 | OJ5: 1799 | OK5: 1599 | OL5: 0 | OM5: 0 | OQ5: 21x | OR5: 21x | OS5: 21x | OT5: 21x | OU5: 21x | OV5: 21x | OW5: 21x | OX5: 21x | OZ5: 12x | PA5: 12x | PB5: 12x | PC5: 12x | PD5: 12x | PE5: 12x | PF5: 12x | PG5: 12x | PI5: 21x | PJ5: 21x | PK5: 21x | PL5: 21x | PM5: 21x | PN5: 21x | PO5: 21x | PP5: 21x | PR5: 12x | PS5: 12x | PT5: 12x | PU5: 12x | PV5: 12x | PW5: 12x | PX5: 12x | PY5: 12x
A6: EOL | B6: Smartphone | C6: Apple | D6: Vivo Total Família 3 | E6: iPhone 13 128GB | F6: 3499 | G6: 3149.1 | H6: 3499 | I6: 3499 | J6: 3499 | K6: 3499 | L6: 3499 | M6: 3499 | N6: 3499 | O6: 3499 | P6: 3499 | Q6: 3499 | R6: 3499 | S6: 3770 | T6: 3789.86 | U6: 3809.8 | V6: 3829.8 | W6: 3849.87 | X6: 3870.01 | Y6: 3890.21 | Z6: 3910.49 | AA6: 3930.83 | AB6: 3499 | AC6: 3149.1 | AD6: 3499 | AE6: 3499 | AF6: 3499 | AG6: 3499 | AH6: 3499 | AI6: 3499 | AJ6: 3499 | AK6: 3499 | AL6: 3499 | AM6: 3499 | AN6: 3499 | AO6: 3770 | AP6: 3789.86 | AQ6: 3809.8 | AR6: 3829.8 | AS6: 3849.87 | AT6: 3870.01 | AU6: 3890.21 | AV6: 3910.49 | AW6: 3930.83 | AX6: 3399 | AY6: 3059.1 | AZ6: 3399 | BA6: 3399 | BB6: 3399 | BC6: 3399 | BD6: 3399 | BE6: 3399 | BF6: 3399 | BG6: 3399 | BH6: 3399 | BI6: 3399 | BJ6: 3399 | BK6: 3662.25 | BL6: 3681.55 | BM6: 3700.91 | BN6: 3720.35 | BO6: 3739.84 | BP6: 3759.4 | BQ6: 3779.03 | BR6: 3798.73 | BS6: 3818.49 | BT6: 3299 | BU6: 2969.1 | BV6: 3299 | BW6: 3299 | BX6: 3299 | BY6: 3299 | BZ6: 3299 | CA6: 3299 | CB6: 3299 | CC6: 3299 | CD6: 3299 | CE6: 3299 | CF6: 3299 | CG6: 3554.51 | CH6: 3573.24 | CI6: 3592.03 | CJ6: 3610.89 | CK6: 3629.81 | CL6: 3648.8 | CM6: 3667.85 | CN6: 3686.97 | CO6: 3706.15 | CP6: 3099 | CQ6: 2789.1 | CR6: 3099 | CS6: 3099 | CT6: 3099 | CU6: 3099 | CV6: 3099 | CW6: 3099 | CX6: 3099 | CY6: 3099 | CZ6: 3099 | DA6: 3099 | DB6: 3099 | DC6: 3339.02 | DD6: 3356.61 | DE6: 3374.27 | DF6: 3391.98 | DG6: 3409.76 | DH6: 3427.59 | DI6: 3445.49 | DJ6: 3463.45 | DK6: 3481.46 | DL6: 2899 | DM6: 2609.1 | DN6: 2899 | DO6: 2899 | DP6: 2899 | DQ6: 2899 | DR6: 2899 | DS6: 2899 | DT6: 2899 | DU6: 2899 | DV6: 2899 | DW6: 2899 | DX6: 2899 | DY6: 3123.53 | DZ6: 3139.99 | EA6: 3156.5 | EB6: 3173.07 | EC6: 3189.7 | ED6: 3206.39 | EE6: 3223.13 | EF6: 3239.93 | EG6: 3256.78 | EH6: 2849 | EI6: 2564.1 | EJ6: 2849 | EK6: 2849 | EL6: 2849 | EM6: 2849 | EN6: 2849 | EO6: 2849 | EP6: 2849 | EQ6: 2849 | ER6: 2849 | ES6: 2849 | ET6: 2849 | EU6: 3069.65 | EV6: 3085.83 | EW6: 3102.06 | EX6: 3118.35 | EY6: 3134.69 | EZ6: 3151.09 | FA6: 3167.54 | FB6: 3184.05 | FC6: 3200.61 | FD6: 2799 | FE6: 2519.1 | FF6: 2799 | FG6: 2799 | FH6: 2799 | FI6: 2799 | FJ6: 2799 | FK6: 2799 | FL6: 2799 | FM6: 2799 | FN6: 2799 | FO6: 2799 | FP6: 2799 | FQ6: 3015.78 | FR6: 3031.67 | FS6: 3047.62 | FT6: 3063.62 | FU6: 3079.68 | FV6: 3095.78 | FW6: 3111.95 | FX6: 3128.17 | FY6: 3144.44 | FZ6: 2599 | GA6: 2339.1 | GB6: 2599 | GC6: 2599 | GD6: 2599 | GE6: 2599 | GF6: 2599 | GG6: 2599 | GH6: 2599 | GI6: 2599 | GJ6: 2599 | GK6: 2599 | GL6: 2599 | GM6: 2800.29 | GN6: 2815.05 | GO6: 2829.85 | GP6: 2844.71 | GQ6: 2859.62 | GR6: 2874.58 | GS6: 2889.59 | GT6: 2904.65 | GU6: 2919.75 | GW6: 0 | GX6: 3499 | GY6: 3149.1 | GZ6: 3499 | HA6: 3499 | HB6: 3499 | HC6: 3499 | HD6: 3499 | HE6: 3499 | HF6: 3499 | HG6: 3499 | HH6: 3499 | HI6: 3499 | HJ6: 3499 | HK6: 3770 | HL6: 3789.86 | HM6: 3809.8 | HN6: 3829.8 | HO6: 3849.87 | HP6: 3870.01 | HQ6: 3890.21 | HR6: 3910.49 | HS6: 3930.83 | HT6: 3399 | HU6: 3059.1 | HV6: 3399 | HW6: 3399 | HX6: 3399 | HY6: 3399 | HZ6: 3399 | IA6: 3399 | IB6: 3399 | IC6: 3399 | ID6: 3399 | IE6: 3399 | IF6: 3399 | IG6: 3662.25 | IH6: 3681.55 | II6: 3700.91 | IJ6: 3720.35 | IK6: 3739.84 | IL6: 3759.4 | IM6: 3779.03 | IN6: 3798.73 | IO6: 3818.49 | IP6: 3299 | IQ6: 2969.1 | IR6: 3299 | IS6: 3299 | IT6: 3299 | IU6: 3299 | IV6: 3299 | IW6: 3299 | IX6: 3299 | IY6: 3299 | IZ6: 3299 | JA6: 3299 | JB6: 3299 | JC6: 3554.51 | JD6: 3573.24 | JE6: 3592.03 | JF6: 3610.89 | JG6: 3629.81 | JH6: 3648.8 | JI6: 3667.85 | JJ6: 3686.97 | JK6: 3706.15 | JL6: 3099 | JM6: 2789.1 | JN6: 3099 | JO6: 3099 | JP6: 3099 | JQ6: 3099 | JR6: 3099 | JS6: 3099 | JT6: 3099 | JU6: 3099 | JV6: 3099 | JW6: 3099 | JX6: 3099 | JY6: 3339.02 | JZ6: 3356.61 | KA6: 3374.27 | KB6: 3391.98 | KC6: 3409.76 | KD6: 3427.59 | KE6: 3445.49 | KF6: 3463.45 | KG6: 3481.46 | KH6: 2899 | KI6: 2609.1 | KJ6: 2899 | KK6: 2899 | KL6: 2899 | KM6: 2899 | KN6: 2899 | KO6: 2899 | KP6: 2899 | KQ6: 2899 | KR6: 2899 | KS6: 2899 | KT6: 2899 | KU6: 3123.53 | KV6: 3139.99 | KW6: 3156.5 | KX6: 3173.07 | KY6: 3189.7 | KZ6: 3206.39 | LA6: 3223.13 | LB6: 3239.93 | LC6: 3256.78 | LD6: 2849 | LE6: 2564.1 | LF6: 2849 | LG6: 2849 | LH6: 2849 | LI6: 2849 | LJ6: 2849 | LK6: 2849 | LL6: 2849 | LM6: 2849 | LN6: 2849 | LO6: 2849 | LP6: 2849 | LQ6: 3069.65 | LR6: 3085.83 | LS6: 3102.06 | LT6: 3118.35 | LU6: 3134.69 | LV6: 3151.09 | LW6: 3167.54 | LX6: 3184.05 | LY6: 3200.61 | LZ6: 2799 | MA6: 2519.1 | MB6: 2799 | MC6: 2799 | MD6: 2799 | ME6: 2799 | MF6: 2799 | MG6: 2799 | MH6: 2799 | MI6: 2799 | MJ6: 2799 | MK6: 2799 | ML6: 2799 | MM6: 3015.78 | MN6: 3031.67 | MO6: 3047.62 | MP6: 3063.62 | MQ6: 3079.68 | MR6: 3095.78 | MS6: 3111.95 | MT6: 3128.17 | MU6: 3144.44 | MV6: 2599 | MW6: 2339.1 | MX6: 2599 | MY6: 2599 | MZ6: 2599 | NA6: 2599 | NB6: 2599 | NC6: 2599 | ND6: 2599 | NE6: 2599 | NF6: 2599 | NG6: 2599 | NH6: 2599 | NI6: 2800.29 | NJ6: 2815.05 | NK6: 2829.85 | NL6: 2844.71 | NM6: 2859.62 | NN6: 2874.58 | NO6: 2889.59 | NP6: 2904.65 | NQ6: 2919.75 | NS6: 3499 | NT6: 3499 | NU6: 3399 | NV6: 3299 | NW6: 3099 | NX6: 2899 | NY6: 2849 | NZ6: 2799 | OA6: 2599 | OC6: 0 | OD6: 3499 | OE6: 3399 | OF6: 3299 | OG6: 3099 | OH6: 2899 | OI6: 2849 | OJ6: 2799 | OK6: 2599 | OL6: 0 | OM6: 0 | OQ6: 21x | OR6: 21x | OS6: 21x | OT6: 21x | OU6: 21x | OV6: 21x | OW6: 21x | OX6: 21x | OZ6: 12x | PA6: 12x | PB6: 12x | PC6: 12x | PD6: 12x | PE6: 12x | PF6: 12x | PG6: 12x | PI6: 21x | PJ6: 21x | PK6: 21x | PL6: 21x | PM6: 21x | PN6: 21x | PO6: 21x | PP6: 21x | PR6: 12x | PS6: 12x | PT6: 12x | PU6: 12x | PV6: 12x | PW6: 12x | PX6: 12x | PY6: 12x
A7: Out | B7: Smartphone | C7: Apple | D7: Vivo Total Família 3 | E7: iPhone 13 256GB | F7: 3599 | G7: 3239.1 | H7: 3599 | I7: 3599 | J7: 3599 | K7: 3599 | L7: 3599 | M7: 3599 | N7: 3599 | O7: 3599 | P7: 3599 | Q7: 3599 | R7: 3599 | S7: 3877.74 | T7: 3898.18 | U7: 3918.68 | V7: 3939.25 | W7: 3959.9 | X7: 3980.61 | Y7: 4001.39 | Z7: 4022.25 | AA7: 4043.17 | AB7: 3599 | AC7: 3239.1 | AD7: 3599 | AE7: 3599 | AF7: 3599 | AG7: 3599 | AH7: 3599 | AI7: 3599 | AJ7: 3599 | AK7: 3599 | AL7: 3599 | AM7: 3599 | AN7: 3599 | AO7: 3877.74 | AP7: 3898.18 | AQ7: 3918.68 | AR7: 3939.25 | AS7: 3959.9 | AT7: 3980.61 | AU7: 4001.39 | AV7: 4022.25 | AW7: 4043.17 | AX7: 3499 | AY7: 3149.1 | AZ7: 3499 | BA7: 3499 | BB7: 3499 | BC7: 3499 | BD7: 3499 | BE7: 3499 | BF7: 3499 | BG7: 3499 | BH7: 3499 | BI7: 3499 | BJ7: 3499 | BK7: 3770 | BL7: 3789.86 | BM7: 3809.8 | BN7: 3829.8 | BO7: 3849.87 | BP7: 3870.01 | BQ7: 3890.21 | BR7: 3910.49 | BS7: 3930.83 | BT7: 3299 | BU7: 2969.1 | BV7: 3299 | BW7: 3299 | BX7: 3299 | BY7: 3299 | BZ7: 3299 | CA7: 3299 | CB7: 3299 | CC7: 3299 | CD7: 3299 | CE7: 3299 | CF7: 3299 | CG7: 3554.51 | CH7: 3573.24 | CI7: 3592.03 | CJ7: 3610.89 | CK7: 3629.81 | CL7: 3648.8 | CM7: 3667.85 | CN7: 3686.97 | CO7: 3706.15 | CP7: 3199 | CQ7: 2879.1 | CR7: 3199 | CS7: 3199 | CT7: 3199 | CU7: 3199 | CV7: 3199 | CW7: 3199 | CX7: 3199 | CY7: 3199 | CZ7: 3199 | DA7: 3199 | DB7: 3199 | DC7: 3446.76 | DD7: 3464.92 | DE7: 3483.15 | DF7: 3501.44 | DG7: 3519.79 | DH7: 3538.2 | DI7: 3556.67 | DJ7: 3575.21 | DK7: 3593.8 | DL7: 3099 | DM7: 2789.1 | DN7: 3099 | DO7: 3099 | DP7: 3099 | DQ7: 3099 | DR7: 3099 | DS7: 3099 | DT7: 3099 | DU7: 3099 | DV7: 3099 | DW7: 3099 | DX7: 3099 | DY7: 3339.02 | DZ7: 3356.61 | EA7: 3374.27 | EB7: 3391.98 | EC7: 3409.76 | ED7: 3427.59 | EE7: 3445.49 | EF7: 3463.45 | EG7: 3481.46 | EH7: 2999 | EI7: 2699.1 | EJ7: 2999 | EK7: 2999 | EL7: 2999 | EM7: 2999 | EN7: 2999 | EO7: 2999 | EP7: 2999 | EQ7: 2999 | ER7: 2999 | ES7: 2999 | ET7: 2999 | EU7: 3231.27 | EV7: 3248.3 | EW7: 3265.38 | EX7: 3282.53 | EY7: 3299.73 | EZ7: 3316.99 | FA7: 3334.31 | FB7: 3351.69 | FC7: 3369.12 | FD7: 2899 | FE7: 2609.1 | FF7: 2899 | FG7: 2899 | FH7: 2899 | FI7: 2899 | FJ7: 2899 | FK7: 2899 | FL7: 2899 | FM7: 2899 | FN7: 2899 | FO7: 2899 | FP7: 2899 | FQ7: 3123.53 | FR7: 3139.99 | FS7: 3156.5 | FT7: 3173.07 | FU7: 3189.7 | FV7: 3206.39 | FW7: 3223.13 | FX7: 3239.93 | FY7: 3256.78 | FZ7: 2799 | GA7: 2519.1 | GB7: 2799 | GC7: 2799 | GD7: 2799 | GE7: 2799 | GF7: 2799 | GG7: 2799 | GH7: 2799 | GI7: 2799 | GJ7: 2799 | GK7: 2799 | GL7: 2799 | GM7: 3015.78 | GN7: 3031.67 | GO7: 3047.62 | GP7: 3063.62 | GQ7: 3079.68 | GR7: 3095.78 | GS7: 3111.95 | GT7: 3128.17 | GU7: 3144.44 | GW7: 0 | GX7: 3599 | GY7: 3239.1 | GZ7: 3599 | HA7: 3599 | HB7: 3599 | HC7: 3599 | HD7: 3599 | HE7: 3599 | HF7: 3599 | HG7: 3599 | HH7: 3599 | HI7: 3599 | HJ7: 3599 | HK7: 3877.74 | HL7: 3898.18 | HM7: 3918.68 | HN7: 3939.25 | HO7: 3959.9 | HP7: 3980.61 | HQ7: 4001.39 | HR7: 4022.25 | HS7: 4043.17 | HT7: 3499 | HU7: 3149.1 | HV7: 3499 | HW7: 3499 | HX7: 3499 | HY7: 3499 | HZ7: 3499 | IA7: 3499 | IB7: 3499 | IC7: 3499 | ID7: 3499 | IE7: 3499 | IF7: 3499 | IG7: 3770 | IH7: 3789.86 | II7: 3809.8 | IJ7: 3829.8 | IK7: 3849.87 | IL7: 3870.01 | IM7: 3890.21 | IN7: 3910.49 | IO7: 3930.83 | IP7: 3299 | IQ7: 2969.1 | IR7: 3299 | IS7: 3299 | IT7: 3299 | IU7: 3299 | IV7: 3299 | IW7: 3299 | IX7: 3299 | IY7: 3299 | IZ7: 3299 | JA7: 3299 | JB7: 3299 | JC7: 3554.51 | JD7: 3573.24 | JE7: 3592.03 | JF7: 3610.89 | JG7: 3629.81 | JH7: 3648.8 | JI7: 3667.85 | JJ7: 3686.97 | JK7: 3706.15 | JL7: 3199 | JM7: 2879.1 | JN7: 3199 | JO7: 3199 | JP7: 3199 | JQ7: 3199 | JR7: 3199 | JS7: 3199 | JT7: 3199 | JU7: 3199 | JV7: 3199 | JW7: 3199 | JX7: 3199 | JY7: 3446.76 | JZ7: 3464.92 | KA7: 3483.15 | KB7: 3501.44 | KC7: 3519.79 | KD7: 3538.2 | KE7: 3556.67 | KF7: 3575.21 | KG7: 3593.8 | KH7: 3099 | KI7: 2789.1 | KJ7: 3099 | KK7: 3099 | KL7: 3099 | KM7: 3099 | KN7: 3099 | KO7: 3099 | KP7: 3099 | KQ7: 3099 | KR7: 3099 | KS7: 3099 | KT7: 3099 | KU7: 3339.02 | KV7: 3356.61 | KW7: 3374.27 | KX7: 3391.98 | KY7: 3409.76 | KZ7: 3427.59 | LA7: 3445.49 | LB7: 3463.45 | LC7: 3481.46 | LD7: 2999 | LE7: 2699.1 | LF7: 2999 | LG7: 2999 | LH7: 2999 | LI7: 2999 | LJ7: 2999 | LK7: 2999 | LL7: 2999 | LM7: 2999 | LN7: 2999 | LO7: 2999 | LP7: 2999 | LQ7: 3231.27 | LR7: 3248.3 | LS7: 3265.38 | LT7: 3282.53 | LU7: 3299.73 | LV7: 3316.99 | LW7: 3334.31 | LX7: 3351.69 | LY7: 3369.12 | LZ7: 2899 | MA7: 2609.1 | MB7: 2899 | MC7: 2899 | MD7: 2899 | ME7: 2899 | MF7: 2899 | MG7: 2899 | MH7: 2899 | MI7: 2899 | MJ7: 2899 | MK7: 2899 | ML7: 2899 | MM7: 3123.53 | MN7: 3139.99 | MO7: 3156.5 | MP7: 3173.07 | MQ7: 3189.7 | MR7: 3206.39 | MS7: 3223.13 | MT7: 3239.93 | MU7: 3256.78 | MV7: 2799 | MW7: 2519.1 | MX7: 2799 | MY7: 2799 | MZ7: 2799 | NA7: 2799 | NB7: 2799 | NC7: 2799 | ND7: 2799 | NE7: 2799 | NF7: 2799 | NG7: 2799 | NH7: 2799 | NI7: 3015.78 | NJ7: 3031.67 | NK7: 3047.62 | NL7: 3063.62 | NM7: 3079.68 | NN7: 3095.78 | NO7: 3111.95 | NP7: 3128.17 | NQ7: 3144.44 | NS7: 3599 | NT7: 3599 | NU7: 3499 | NV7: 3299 | NW7: 3199 | NX7: 3099 | NY7: 2999 | NZ7: 2899 | OA7: 2799 | OC7: 0 | OD7: 3599 | OE7: 3499 | OF7: 3299 | OG7: 3199 | OH7: 3099 | OI7: 2999 | OJ7: 2899 | OK7: 2799 | OL7: 0 | OM7: 0 | OQ7: 21x | OR7: 21x | OS7: 21x | OT7: 21x | OU7: 21x | OV7: 21x | OW7: 21x | OX7: 21x | OZ7: 12x | PA7: 12x | PB7: 12x | PC7: 12x | PD7: 12x | PE7: 12x | PF7: 12x | PG7: 12x | PI7: 21x | PJ7: 21x | PK7: 21x | PL7: 21x | PM7: 21x | PN7: 21x | PO7: 21x | PP7: 21x | PR7: 12x | PS7: 12x | PT7: 12x | PU7: 12x | PV7: 12x | PW7: 12x | PX7: 12x | PY7: 12x
A8: EOL | B8: Smartphone | C8: Apple | D8: Vivo Total Família 3 | E8: iPhone 13 Mini 256GB | F8: 7399 | G8: 6659.1 | H8: 7399 | I8: 7399 | J8: 7399 | K8: 7399 | L8: 7399 | M8: 7399 | N8: 7399 | O8: 7399 | P8: 7399 | Q8: 7399 | R8: 7399 | S8: 7972.05 | T8: 8014.06 | U8: 8056.21 | V8: 8098.51 | W8: 8140.95 | X8: 8183.53 | Y8: 8226.26 | Z8: 8269.13 | AA8: 8312.15 | AB8: 4399 | AC8: 3959.1 | AD8: 4399 | AE8: 4399 | AF8: 4399 | AG8: 4399 | AH8: 4399 | AI8: 4399 | AJ8: 4399 | AK8: 4399 | AL8: 4399 | AM8: 4399 | AN8: 4399 | AO8: 4739.7 | AP8: 4764.68 | AQ8: 4789.74 | AR8: 4814.89 | AS8: 4840.12 | AT8: 4865.44 | AU8: 4890.84 | AV8: 4916.33 | AW8: 4941.9 | AX8: 4399 | AY8: 3959.1 | AZ8: 4399 | BA8: 4399 | BB8: 4399 | BC8: 4399 | BD8: 4399 | BE8: 4399 | BF8: 4399 | BG8: 4399 | BH8: 4399 | BI8: 4399 | BJ8: 4399 | BK8: 4739.7 | BL8: 4764.68 | BM8: 4789.74 | BN8: 4814.89 | BO8: 4840.12 | BP8: 4865.44 | BQ8: 4890.84 | BR8: 4916.33 | BS8: 4941.9 | BT8: 4349 | BU8: 3914.1 | BV8: 4349 | BW8: 4349 | BX8: 4349 | BY8: 4349 | BZ8: 4349 | CA8: 4349 | CB8: 4349 | CC8: 4349 | CD8: 4349 | CE8: 4349 | CF8: 4349 | CG8: 4685.83 | CH8: 4710.52 | CI8: 4735.3 | CJ8: 4760.16 | CK8: 4785.1 | CL8: 4810.14 | CM8: 4835.25 | CN8: 4860.45 | CO8: 4885.73 | CP8: 3999 | CQ8: 3599.1 | CR8: 3999 | CS8: 3999 | CT8: 3999 | CU8: 3999 | CV8: 3999 | CW8: 3999 | CX8: 3999 | CY8: 3999 | CZ8: 3999 | DA8: 3999 | DB8: 3999 | DC8: 4308.72 | DD8: 4331.43 | DE8: 4354.21 | DF8: 4377.07 | DG8: 4400.01 | DH8: 4423.02 | DI8: 4446.12 | DJ8: 4469.29 | DK8: 4492.54 | DL8: 3699 | DM8: 3329.1 | DN8: 3699 | DO8: 3699 | DP8: 3699 | DQ8: 3699 | DR8: 3699 | DS8: 3699 | DT8: 3699 | DU8: 3699 | DV8: 3699 | DW8: 3699 | DX8: 3699 | DY8: 3985.49 | DZ8: 4006.49 | EA8: 4027.56 | EB8: 4048.71 | EC8: 4069.92 | ED8: 4091.21 | EE8: 4112.57 | EF8: 4134.01 | EG8: 4155.51 | EH8: 3649 | EI8: 3284.1 | EJ8: 3649 | EK8: 3649 | EL8: 3649 | EM8: 3649 | EN8: 3649 | EO8: 3649 | EP8: 3649 | EQ8: 3649 | ER8: 3649 | ES8: 3649 | ET8: 3649 | EU8: 3931.61 | EV8: 3952.33 | EW8: 3973.12 | EX8: 3993.98 | EY8: 4014.91 | EZ8: 4035.91 | FA8: 4056.98 | FB8: 4078.13 | FC8: 4099.34 | FD8: 3599 | FE8: 3239.1 | FF8: 3599 | FG8: 3599 | FH8: 3599 | FI8: 3599 | FJ8: 3599 | FK8: 3599 | FL8: 3599 | FM8: 3599 | FN8: 3599 | FO8: 3599 | FP8: 3599 | FQ8: 3877.74 | FR8: 3898.18 | FS8: 3918.68 | FT8: 3939.25 | FU8: 3959.9 | FV8: 3980.61 | FW8: 4001.39 | FX8: 4022.25 | FY8: 4043.17 | FZ8: 3399 | GA8: 3059.1 | GB8: 3399 | GC8: 3399 | GD8: 3399 | GE8: 3399 | GF8: 3399 | GG8: 3399 | GH8: 3399 | GI8: 3399 | GJ8: 3399 | GK8: 3399 | GL8: 3399 | GM8: 3662.25 | GN8: 3681.55 | GO8: 3700.91 | GP8: 3720.35 | GQ8: 3739.84 | GR8: 3759.4 | GS8: 3779.03 | GT8: 3798.73 | GU8: 3818.49 | GW8: 0 | GX8: 4399 | GY8: 3959.1 | GZ8: 4399 | HA8: 4399 | HB8: 4399 | HC8: 4399 | HD8: 4399 | HE8: 4399 | HF8: 4399 | HG8: 4399 | HH8: 4399 | HI8: 4399 | HJ8: 4399 | HK8: 4739.7 | HL8: 4764.68 | HM8: 4789.74 | HN8: 4814.89 | HO8: 4840.12 | HP8: 4865.44 | HQ8: 4890.84 | HR8: 4916.33 | HS8: 4941.9 | HT8: 4399 | HU8: 3959.1 | HV8: 4399 | HW8: 4399 | HX8: 4399 | HY8: 4399 | HZ8: 4399 | IA8: 4399 | IB8: 4399 | IC8: 4399 | ID8: 4399 | IE8: 4399 | IF8: 4399 | IG8: 4739.7 | IH8: 4764.68 | II8: 4789.74 | IJ8: 4814.89 | IK8: 4840.12 | IL8: 4865.44 | IM8: 4890.84 | IN8: 4916.33 | IO8: 4941.9 | IP8: 4349 | IQ8: 3914.1 | IR8: 4349 | IS8: 4349 | IT8: 4349 | IU8: 4349 | IV8: 4349 | IW8: 4349 | IX8: 4349 | IY8: 4349 | IZ8: 4349 | JA8: 4349 | JB8: 4349 | JC8: 4685.83 | JD8: 4710.52 | JE8: 4735.3 | JF8: 4760.16 | JG8: 4785.1 | JH8: 4810.14 | JI8: 4835.25 | JJ8: 4860.45 | JK8: 4885.73 | JL8: 3999 | JM8: 3599.1 | JN8: 3999 | JO8: 3999 | JP8: 3999 | JQ8: 3999 | JR8: 3999 | JS8: 3999 | JT8: 3999 | JU8: 3999 | JV8: 3999 | JW8: 3999 | JX8: 3999 | JY8: 4308.72 | JZ8: 4331.43 | KA8: 4354.21 | KB8: 4377.07 | KC8: 4400.01 | KD8: 4423.02 | KE8: 4446.12 | KF8: 4469.29 | KG8: 4492.54 | KH8: 3699 | KI8: 3329.1 | KJ8: 3699 | KK8: 3699 | KL8: 3699 | KM8: 3699 | KN8: 3699 | KO8: 3699 | KP8: 3699 | KQ8: 3699 | KR8: 3699 | KS8: 3699 | KT8: 3699 | KU8: 3985.49 | KV8: 4006.49 | KW8: 4027.56 | KX8: 4048.71 | KY8: 4069.92 | KZ8: 4091.21 | LA8: 4112.57 | LB8: 4134.01 | LC8: 4155.51 | LD8: 3649 | LE8: 3284.1 | LF8: 3649 | LG8: 3649 | LH8: 3649 | LI8: 3649 | LJ8: 3649 | LK8: 3649 | LL8: 3649 | LM8: 3649 | LN8: 3649 | LO8: 3649 | LP8: 3649 | LQ8: 3931.61 | LR8: 3952.33 | LS8: 3973.12 | LT8: 3993.98 | LU8: 4014.91 | LV8: 4035.91 | LW8: 4056.98 | LX8: 4078.13 | LY8: 4099.34 | LZ8: 3599 | MA8: 3239.1 | MB8: 3599 | MC8: 3599 | MD8: 3599 | ME8: 3599 | MF8: 3599 | MG8: 3599 | MH8: 3599 | MI8: 3599 | MJ8: 3599 | MK8: 3599 | ML8: 3599 | MM8: 3877.74 | MN8: 3898.18 | MO8: 3918.68 | MP8: 3939.25 | MQ8: 3959.9 | MR8: 3980.61 | MS8: 4001.39 | MT8: 4022.25 | MU8: 4043.17 | MV8: 3399 | MW8: 3059.1 | MX8: 3399 | MY8: 3399 | MZ8: 3399 | NA8: 3399 | NB8: 3399 | NC8: 3399 | ND8: 3399 | NE8: 3399 | NF8: 3399 | NG8: 3399 | NH8: 3399 | NI8: 3662.25 | NJ8: 3681.55 | NK8: 3700.91 | NL8: 3720.35 | NM8: 3739.84 | NN8: 3759.4 | NO8: 3779.03 | NP8: 3798.73 | NQ8: 3818.49 | NS8: 7399 | NT8: 4399 | NU8: 4399 | NV8: 4349 | NW8: 3999 | NX8: 3699 | NY8: 3649 | NZ8: 3599 | OA8: 3399 | OC8: 0 | OD8: 4399 | OE8: 4399 | OF8: 4349 | OG8: 3999 | OH8: 3699 | OI8: 3649 | OJ8: 3599 | OK8: 3399 | OL8: 0 | OM8: 0 | OQ8: 21x | OR8: 21x | OS8: 21x | OT8: 21x | OU8: 21x | OV8: 21x | OW8: 21x | OX8: 21x | OZ8: 12x | PA8: 12x | PB8: 12x | PC8: 12x | PD8: 12x | PE8: 12x | PF8: 12x | PG8: 12x | PI8: 21x | PJ8: 21x | PK8: 21x | PL8: 21x | PM8: 21x | PN8: 21x | PO8: 21x | PP8: 21x | PR8: 12x | PS8: 12x | PT8: 12x | PU8: 12x | PV8: 12x | PW8: 12x | PX8: 12x | PY8: 12x
A9: EOL | B9: Smartphone | C9: Apple | D9: Vivo Total Família 3 | E9: iPhone 13 Mini 512GB | F9: 11099 | G9: 9989.1 | H9: 11099 | I9: 11099 | J9: 11099 | K9: 11099 | L9: 11099 | M9: 11099 | N9: 11099 | O9: 11099 | P9: 11099 | Q9: 11099 | R9: 11099 | S9: 11958.61 | T9: 12021.63 | U9: 12084.86 | V9: 12148.31 | W9: 12211.98 | X9: 12275.85 | Y9: 12339.95 | Z9: 12404.26 | AA9: 12468.78 | AB9: 9099 | AC9: 8189.1 | AD9: 9099 | AE9: 9099 | AF9: 9099 | AG9: 9099 | AH9: 9099 | AI9: 9099 | AJ9: 9099 | AK9: 9099 | AL9: 9099 | AM9: 9099 | AN9: 9099 | AO9: 9803.71 | AP9: 9855.38 | AQ9: 9907.21 | AR9: 9959.23 | AS9: 10011.42 | AT9: 10063.79 | AU9: 10116.33 | AV9: 10169.05 | AW9: 10221.95 | AX9: 9099 | AY9: 8189.1 | AZ9: 9099 | BA9: 9099 | BB9: 9099 | BC9: 9099 | BD9: 9099 | BE9: 9099 | BF9: 9099 | BG9: 9099 | BH9: 9099 | BI9: 9099 | BJ9: 9099 | BK9: 9803.71 | BL9: 9855.38 | BM9: 9907.21 | BN9: 9959.23 | BO9: 10011.42 | BP9: 10063.79 | BQ9: 10116.33 | BR9: 10169.05 | BS9: 10221.95 | BT9: 9099 | BU9: 8189.1 | BV9: 9099 | BW9: 9099 | BX9: 9099 | BY9: 9099 | BZ9: 9099 | CA9: 9099 | CB9: 9099 | CC9: 9099 | CD9: 9099 | CE9: 9099 | CF9: 9099 | CG9: 9803.71 | CH9: 9855.38 | CI9: 9907.21 | CJ9: 9959.23 | CK9: 10011.42 | CL9: 10063.79 | CM9: 10116.33 | CN9: 10169.05 | CO9: 10221.95 | CP9: 8599 | CQ9: 7739.1 | CR9: 8599 | CS9: 8599 | CT9: 8599 | CU9: 8599 | CV9: 8599 | CW9: 8599 | CX9: 8599 | CY9: 8599 | CZ9: 8599 | DA9: 8599 | DB9: 8599 | DC9: 9264.99 | DD9: 9313.81 | DE9: 9362.8 | DF9: 9411.96 | DG9: 9461.28 | DH9: 9510.77 | DI9: 9560.43 | DJ9: 9610.25 | DK9: 9660.24 | DL9: 7869 | DM9: 7082.1 | DN9: 7869 | DO9: 7869 | DP9: 7869 | DQ9: 7869 | DR9: 7869 | DS9: 7869 | DT9: 7869 | DU9: 7869 | DV9: 7869 | DW9: 7869 | DX9: 7869 | DY9: 8478.45 | DZ9: 8523.13 | EA9: 8567.96 | EB9: 8612.94 | EC9: 8658.08 | ED9: 8703.37 | EE9: 8748.81 | EF9: 8794.4 | EG9: 8840.15 | EH9: 7869 | EI9: 7082.1 | EJ9: 7869 | EK9: 7869 | EL9: 7869 | EM9: 7869 | EN9: 7869 | EO9: 7869 | EP9: 7869 | EQ9: 7869 | ER9: 7869 | ES9: 7869 | ET9: 7869 | EU9: 8478.45 | EV9: 8523.13 | EW9: 8567.96 | EX9: 8612.94 | EY9: 8658.08 | EZ9: 8703.37 | FA9: 8748.81 | FB9: 8794.4 | FC9: 8840.15 | FD9: 7649 | FE9: 6884.1 | FF9: 7649 | FG9: 7649 | FH9: 7649 | FI9: 7649 | FJ9: 7649 | FK9: 7649 | FL9: 7649 | FM9: 7649 | FN9: 7649 | FO9: 7649 | FP9: 7649 | FQ9: 8241.41 | FR9: 8284.84 | FS9: 8328.42 | FT9: 8372.14 | FU9: 8416.02 | FV9: 8460.04 | FW9: 8504.21 | FX9: 8548.53 | FY9: 8593 | FZ9: 7199 | GA9: 6479.1 | GB9: 7199 | GC9: 7199 | GD9: 7199 | GE9: 7199 | GF9: 7199 | GG9: 7199 | GH9: 7199 | GI9: 7199 | GJ9: 7199 | GK9: 7199 | GL9: 7199 | GM9: 7756.56 | GN9: 7797.43 | GO9: 7838.45 | GP9: 7879.6 | GQ9: 7920.89 | GR9: 7962.33 | GS9: 8003.9 | GT9: 8045.61 | GU9: 8087.46 | GW9: 0 | GX9: 9099 | GY9: 8189.1 | GZ9: 9099 | HA9: 9099 | HB9: 9099 | HC9: 9099 | HD9: 9099 | HE9: 9099 | HF9: 9099 | HG9: 9099 | HH9: 9099 | HI9: 9099 | HJ9: 9099 | HK9: 9803.71 | HL9: 9855.38 | HM9: 9907.21 | HN9: 9959.23 | HO9: 10011.42 | HP9: 10063.79 | HQ9: 10116.33 | HR9: 10169.05 | HS9: 10221.95 | HT9: 9099 | HU9: 8189.1 | HV9: 9099 | HW9: 9099 | HX9: 9099 | HY9: 9099 | HZ9: 9099 | IA9: 9099 | IB9: 9099 | IC9: 9099 | ID9: 9099 | IE9: 9099 | IF9: 9099 | IG9: 9803.71 | IH9: 9855.38 | II9: 9907.21 | IJ9: 9959.23 | IK9: 10011.42 | IL9: 10063.79 | IM9: 10116.33 | IN9: 10169.05 | IO9: 10221.95 | IP9: 9099 | IQ9: 8189.1 | IR9: 9099 | IS9: 9099 | IT9: 9099 | IU9: 9099 | IV9: 9099 | IW9: 9099 | IX9: 9099 | IY9: 9099 | IZ9: 9099 | JA9: 9099 | JB9: 9099 | JC9: 9803.71 | JD9: 9855.38 | JE9: 9907.21 | JF9: 9959.23 | JG9: 10011.42 | JH9: 10063.79 | JI9: 10116.33 | JJ9: 10169.05 | JK9: 10221.95 | JL9: 8599 | JM9: 7739.1 | JN9: 8599 | JO9: 8599 | JP9: 8599 | JQ9: 8599 | JR9: 8599 | JS9: 8599 | JT9: 8599 | JU9: 8599 | JV9: 8599 | JW9: 8599 | JX9: 8599 | JY9: 9264.99 | JZ9: 9313.81 | KA9: 9362.8 | KB9: 9411.96 | KC9: 9461.28 | KD9: 9510.77 | KE9: 9560.43 | KF9: 9610.25 | KG9: 9660.24 | KH9: 7869 | KI9: 7082.1 | KJ9: 7869 | KK9: 7869 | KL9: 7869 | KM9: 7869 | KN9: 7869 | KO9: 7869 | KP9: 7869 | KQ9: 7869 | KR9: 7869 | KS9: 7869 | KT9: 7869 | KU9: 8478.45 | KV9: 8523.13 | KW9: 8567.96 | KX9: 8612.94 | KY9: 8658.08 | KZ9: 8703.37 | LA9: 8748.81 | LB9: 8794.4 | LC9: 8840.15 | LD9: 7869 | LE9: 7082.1 | LF9: 7869 | LG9: 7869 | LH9: 7869 | LI9: 7869 | LJ9: 7869 | LK9: 7869 | LL9: 7869 | LM9: 7869 | LN9: 7869 | LO9: 7869 | LP9: 7869 | LQ9: 8478.45 | LR9: 8523.13 | LS9: 8567.96 | LT9: 8612.94 | LU9: 8658.08 | LV9: 8703.37 | LW9: 8748.81 | LX9: 8794.4 | LY9: 8840.15 | LZ9: 7649 | MA9: 6884.1 | MB9: 7649 | MC9: 7649 | MD9: 7649 | ME9: 7649 | MF9: 7649 | MG9: 7649 | MH9: 7649 | MI9: 7649 | MJ9: 7649 | MK9: 7649 | ML9: 7649 | MM9: 8241.41 | MN9: 8284.84 | MO9: 8328.42 | MP9: 8372.14 | MQ9: 8416.02 | MR9: 8460.04 | MS9: 8504.21 | MT9: 8548.53 | MU9: 8593 | MV9: 7199 | MW9: 6479.1 | MX9: 7199 | MY9: 7199 | MZ9: 7199 | NA9: 7199 | NB9: 7199 | NC9: 7199 | ND9: 7199 | NE9: 7199 | NF9: 7199 | NG9: 7199 | NH9: 7199 | NI9: 7756.56 | NJ9: 7797.43 | NK9: 7838.45 | NL9: 7879.6 | NM9: 7920.89 | NN9: 7962.33 | NO9: 8003.9 | NP9: 8045.61 | NQ9: 8087.46 | NS9: 11099 | NT9: 9099 | NU9: 9099 | NV9: 9099 | NW9: 8599 | NX9: 7869 | NY9: 7869 | NZ9: 7649 | OA9: 7199 | OC9: 0 | OD9: 9099 | OE9: 9099 | OF9: 9099 | OG9: 8599 | OH9: 7869 | OI9: 7869 | OJ9: 7649 | OK9: 7199 | OL9: 0 | OM9: 0 | OQ9: 21x | OR9: 21x | OS9: 21x | OT9: 21x | OU9: 21x | OV9: 21x | OW9: 21x | OX9: 21x | OZ9: 12x | PA9: 12x | PB9: 12x | PC9: 12x | PD9: 12x | PE9: 12x | PF9: 12x | PG9: 12x | PI9: 21x | PJ9: 21x | PK9: 21x | PL9: 21x | PM9: 21x | PN9: 21x | PO9: 21x | PP9: 21x | PR9: 12x | PS9: 12x | PT9: 12x | PU9: 12x | PV9: 12x | PW9: 12x | PX9: 12x | PY9: 12x
A10: EOL | B10: Smartphone | C10: Apple | D10: Vivo Total Família 3 | E10: iPhone 13 Pro 128GB | F10: 4899 | G10: 4409.1 | H10: 4899 | I10: 4899 | J10: 4899 | K10: 4899 | L10: 4899 | M10: 4899 | N10: 4899 | O10: 4899 | P10: 4899 | Q10: 4899 | R10: 4899 | S10: 5278.42 | T10: 5306.24 | U10: 5334.15 | V10: 5362.16 | W10: 5390.26 | X10: 5418.45 | Y10: 5446.74 | Z10: 5475.13 | AA10: 5503.61 | AB10: 4399 | AC10: 3959.1 | AD10: 4399 | AE10: 4399 | AF10: 4399 | AG10: 4399 | AH10: 4399 | AI10: 4399 | AJ10: 4399 | AK10: 4399 | AL10: 4399 | AM10: 4399 | AN10: 4399 | AO10: 4739.7 | AP10: 4764.68 | AQ10: 4789.74 | AR10: 4814.89 | AS10: 4840.12 | AT10: 4865.44 | AU10: 4890.84 | AV10: 4916.33 | AW10: 4941.9 | AX10: 4299 | AY10: 3869.1 | AZ10: 4299 | BA10: 4299 | BB10: 4299 | BC10: 4299 | BD10: 4299 | BE10: 4299 | BF10: 4299 | BG10: 4299 | BH10: 4299 | BI10: 4299 | BJ10: 4299 | BK10: 4631.96 | BL10: 4656.36 | BM10: 4680.86 | BN10: 4705.43 | BO10: 4730.09 | BP10: 4754.83 | BQ10: 4779.66 | BR10: 4804.57 | BS10: 4829.56 | BT10: 4199 | BU10: 3779.1 | BV10: 4199 | BW10: 4199 | BX10: 4199 | BY10: 4199 | BZ10: 4199 | CA10: 4199 | CB10: 4199 | CC10: 4199 | CD10: 4199 | CE10: 4199 | CF10: 4199 | CG10: 4524.21 | CH10: 4548.05 | CI10: 4571.97 | CJ10: 4595.98 | CK10: 4620.06 | CL10: 4644.23 | CM10: 4668.48 | CN10: 4692.81 | CO10: 4717.22 | CP10: 4099 | CQ10: 3689.1 | CR10: 4099 | CS10: 4099 | CT10: 4099 | CU10: 4099 | CV10: 4099 | CW10: 4099 | CX10: 4099 | CY10: 4099 | CZ10: 4099 | DA10: 4099 | DB10: 4099 | DC10: 4416.47 | DD10: 4439.74 | DE10: 4463.09 | DF10: 4486.52 | DG10: 4510.04 | DH10: 4533.63 | DI10: 4557.3 | DJ10: 4581.05 | DK10: 4604.88 | DL10: 3999 | DM10: 3599.1 | DN10: 3999 | DO10: 3999 | DP10: 3999 | DQ10: 3999 | DR10: 3999 | DS10: 3999 | DT10: 3999 | DU10: 3999 | DV10: 3999 | DW10: 3999 | DX10: 3999 | DY10: 4308.72 | DZ10: 4331.43 | EA10: 4354.21 | EB10: 4377.07 | EC10: 4400.01 | ED10: 4423.02 | EE10: 4446.12 | EF10: 4469.29 | EG10: 4492.54 | EH10: 3899 | EI10: 3509.1 | EJ10: 3899 | EK10: 3899 | EL10: 3899 | EM10: 3899 | EN10: 3899 | EO10: 3899 | EP10: 3899 | EQ10: 3899 | ER10: 3899 | ES10: 3899 | ET10: 3899 | EU10: 4200.98 | EV10: 4223.11 | EW10: 4245.33 | EX10: 4267.62 | EY10: 4289.98 | EZ10: 4312.42 | FA10: 4334.94 | FB10: 4357.53 | FC10: 4380.19 | FD10: 3799 | FE10: 3419.1 | FF10: 3799 | FG10: 3799 | FH10: 3799 | FI10: 3799 | FJ10: 3799 | FK10: 3799 | FL10: 3799 | FM10: 3799 | FN10: 3799 | FO10: 3799 | FP10: 3799 | FQ10: 4093.23 | FR10: 4114.8 | FS10: 4136.44 | FT10: 4158.16 | FU10: 4179.95 | FV10: 4201.82 | FW10: 4223.76 | FX10: 4245.77 | FY10: 4267.85 | FZ10: 3699 | GA10: 3329.1 | GB10: 3699 | GC10: 3699 | GD10: 3699 | GE10: 3699 | GF10: 3699 | GG10: 3699 | GH10: 3699 | GI10: 3699 | GJ10: 3699 | GK10: 3699 | GL10: 3699 | GM10: 3985.49 | GN10: 4006.49 | GO10: 4027.56 | GP10: 4048.71 | GQ10: 4069.92 | GR10: 4091.21 | GS10: 4112.57 | GT10: 4134.01 | GU10: 4155.51 | GW10: 0 | GX10: 4399 | GY10: 3959.1 | GZ10: 4399 | HA10: 4399 | HB10: 4399 | HC10: 4399 | HD10: 4399 | HE10: 4399 | HF10: 4399 | HG10: 4399 | HH10: 4399 | HI10: 4399 | HJ10: 4399 | HK10: 4739.7 | HL10: 4764.68 | HM10: 4789.74 | HN10: 4814.89 | HO10: 4840.12 | HP10: 4865.44 | HQ10: 4890.84 | HR10: 4916.33 | HS10: 4941.9 | HT10: 4299 | HU10: 3869.1 | HV10: 4299 | HW10: 4299 | HX10: 4299 | HY10: 4299 | HZ10: 4299 | IA10: 4299 | IB10: 4299 | IC10: 4299 | ID10: 4299 | IE10: 4299 | IF10: 4299 | IG10: 4631.96 | IH10: 4656.36 | II10: 4680.86 | IJ10: 4705.43 | IK10: 4730.09 | IL10: 4754.83 | IM10: 4779.66 | IN10: 4804.57 | IO10: 4829.56 | IP10: 4199 | IQ10: 3779.1 | IR10: 4199 | IS10: 4199 | IT10: 4199 | IU10: 4199 | IV10: 4199 | IW10: 4199 | IX10: 4199 | IY10: 4199 | IZ10: 4199 | JA10: 4199 | JB10: 4199 | JC10: 4524.21 | JD10: 4548.05 | JE10: 4571.97 | JF10: 4595.98 | JG10: 4620.06 | JH10: 4644.23 | JI10: 4668.48 | JJ10: 4692.81 | JK10: 4717.22 | JL10: 4099 | JM10: 3689.1 | JN10: 4099 | JO10: 4099 | JP10: 4099 | JQ10: 4099 | JR10: 4099 | JS10: 4099 | JT10: 4099 | JU10: 4099 | JV10: 4099 | JW10: 4099 | JX10: 4099 | JY10: 4416.47 | JZ10: 4439.74 | KA10: 4463.09 | KB10: 4486.52 | KC10: 4510.04 | KD10: 4533.63 | KE10: 4557.3 | KF10: 4581.05 | KG10: 4604.88 | KH10: 3999 | KI10: 3599.1 | KJ10: 3999 | KK10: 3999 | KL10: 3999 | KM10: 3999 | KN10: 3999 | KO10: 3999 | KP10: 3999 | KQ10: 3999 | KR10: 3999 | KS10: 3999 | KT10: 3999 | KU10: 4308.72 | KV10: 4331.43 | KW10: 4354.21 | KX10: 4377.07 | KY10: 4400.01 | KZ10: 4423.02 | LA10: 4446.12 | LB10: 4469.29 | LC10: 4492.54 | LD10: 3899 | LE10: 3509.1 | LF10: 3899 | LG10: 3899 | LH10: 3899 | LI10: 3899 | LJ10: 3899 | LK10: 3899 | LL10: 3899 | LM10: 3899 | LN10: 3899 | LO10: 3899 | LP10: 3899 | LQ10: 4200.98 | LR10: 4223.11 | LS10: 4245.33 | LT10: 4267.62 | LU10: 4289.98 | LV10: 4312.42 | LW10: 4334.94 | LX10: 4357.53 | LY10: 4380.19 | LZ10: 3799 | MA10: 3419.1 | MB10: 3799 | MC10: 3799 | MD10: 3799 | ME10: 3799 | MF10: 3799 | MG10: 3799 | MH10: 3799 | MI10: 3799 | MJ10: 3799 | MK10: 3799 | ML10: 3799 | MM10: 4093.23 | MN10: 4114.8 | MO10: 4136.44 | MP10: 4158.16 | MQ10: 4179.95 | MR10: 4201.82 | MS10: 4223.76 | MT10: 4245.77 | MU10: 4267.85 | MV10: 3699 | MW10: 3329.1 | MX10: 3699 | MY10: 3699 | MZ10: 3699 | NA10: 3699 | NB10: 3699 | NC10: 3699 | ND10: 3699 | NE10: 3699 | NF10: 3699 | NG10: 3699 | NH10: 3699 | NI10: 3985.49 | NJ10: 4006.49 | NK10: 4027.56 | NL10: 4048.71 | NM10: 4069.92 | NN10: 4091.21 | NO10: 4112.57 | NP10: 4134.01 | NQ10: 4155.51 | NS10: 4899 | NT10: 4399 | NU10: 4299 | NV10: 4199 | NW10: 4099 | NX10: 3999 | NY10: 3899 | NZ10: 3799 | OA10: 3699 | OC10: 0 | OD10: 4399 | OE10: 4299 | OF10: 4199 | OG10: 4099 | OH10: 3999 | OI10: 3899 | OJ10: 3799 | OK10: 3699 | OL10: 0 | OM10: 0 | OQ10: 21x | OR10: 21x | OS10: 21x | OT10: 21x | OU10: 21x | OV10: 21x | OW10: 21x | OX10: 21x | OZ10: 12x | PA10: 12x | PB10: 12x | PC10: 12x | PD10: 12x | PE10: 12x | PF10: 12x | PG10: 12x | PI10: 21x | PJ10: 21x | PK10: 21x | PL10: 21x | PM10: 21x | PN10: 21x | PO10: 21x | PP10: 21x | PR10: 12x | PS10: 12x | PT10: 12x | PU10: 12x | PV10: 12x | PW10: 12x | PX10: 12x | PY10: 12x
A11: EOL | B11: Smartphone | C11: Apple | D11: Vivo Total Família 3 | E11: iPhone 13 Pro 1TB | F11: 16449 | G11: 14804.1 | H11: 16449 | I11: 16449 | J11: 16449 | K11: 16449 | L11: 16449 | M11: 16449 | N11: 16449 | O11: 16449 | P11: 16449 | Q11: 16449 | R11: 16449 | S11: 17722.97 | T11: 17816.36 | U11: 17910.07 | V11: 18004.11 | W11: 18098.46 | X11: 18193.13 | Y11: 18288.12 | Z11: 18383.42 | AA11: 18479.05 | AB11: 13749 | AC11: 12374.1 | AD11: 13749 | AE11: 13749 | AF11: 13749 | AG11: 13749 | AH11: 13749 | AI11: 13749 | AJ11: 13749 | AK11: 13749 | AL11: 13749 | AM11: 13749 | AN11: 13749 | AO11: 14813.85 | AP11: 14891.92 | AQ11: 14970.25 | AR11: 15048.85 | AS11: 15127.71 | AT11: 15206.84 | AU11: 15286.24 | AV11: 15365.9 | AW11: 15445.83 | AX11: 13749 | AY11: 12374.1 | AZ11: 13749 | BA11: 13749 | BB11: 13749 | BC11: 13749 | BD11: 13749 | BE11: 13749 | BF11: 13749 | BG11: 13749 | BH11: 13749 | BI11: 13749 | BJ11: 13749 | BK11: 14813.85 | BL11: 14891.92 | BM11: 14970.25 | BN11: 15048.85 | BO11: 15127.71 | BP11: 15206.84 | BQ11: 15286.24 | BR11: 15365.9 | BS11: 15445.83 | BT11: 13749 | BU11: 12374.1 | BV11: 13749 | BW11: 13749 | BX11: 13749 | BY11: 13749 | BZ11: 13749 | CA11: 13749 | CB11: 13749 | CC11: 13749 | CD11: 13749 | CE11: 13749 | CF11: 13749 | CG11: 14813.85 | CH11: 14891.92 | CI11: 14970.25 | CJ11: 15048.85 | CK11: 15127.71 | CL11: 15206.84 | CM11: 15286.24 | CN11: 15365.9 | CO11: 15445.83 | CP11: 13049 | CQ11: 11744.1 | CR11: 13049 | CS11: 13049 | CT11: 13049 | CU11: 13049 | CV11: 13049 | CW11: 13049 | CX11: 13049 | CY11: 13049 | CZ11: 13049 | DA11: 13049 | DB11: 13049 | DC11: 14059.64 | DD11: 14133.73 | DE11: 14208.07 | DF11: 14282.67 | DG11: 14357.52 | DH11: 14432.62 | DI11: 14507.97 | DJ11: 14583.58 | DK11: 14659.44 | DL11: 12299 | DM11: 11069.1 | DN11: 12299 | DO11: 12299 | DP11: 12299 | DQ11: 12299 | DR11: 12299 | DS11: 12299 | DT11: 12299 | DU11: 12299 | DV11: 12299 | DW11: 12299 | DX11: 12299 | DY11: 13251.55 | DZ11: 13321.38 | EA11: 13391.45 | EB11: 13461.76 | EC11: 13532.31 | ED11: 13603.09 | EE11: 13674.12 | EF11: 13745.38 | EG11: 13816.88 | EH11: 12299 | EI11: 11069.1 | EJ11: 12299 | EK11: 12299 | EL11: 12299 | EM11: 12299 | EN11: 12299 | EO11: 12299 | EP11: 12299 | EQ11: 12299 | ER11: 12299 | ES11: 12299 | ET11: 12299 | EU11: 13251.55 | EV11: 13321.38 | EW11: 13391.45 | EX11: 13461.76 | EY11: 13532.31 | EZ11: 13603.09 | FA11: 13674.12 | FB11: 13745.38 | FC11: 13816.88 | FD11: 11599 | FE11: 10439.1 | FF11: 11599 | FG11: 11599 | FH11: 11599 | FI11: 11599 | FJ11: 11599 | FK11: 11599 | FL11: 11599 | FM11: 11599 | FN11: 11599 | FO11: 11599 | FP11: 11599 | FQ11: 12497.34 | FR11: 12563.19 | FS11: 12629.28 | FT11: 12695.58 | FU11: 12762.11 | FV11: 12828.87 | FW11: 12895.85 | FX11: 12963.06 | FY11: 13030.49 | FZ11: 10849 | GA11: 9764.1 | GB11: 10849 | GC11: 10849 | GD11: 10849 | GE11: 10849 | GF11: 10849 | GG11: 10849 | GH11: 10849 | GI11: 10849 | GJ11: 10849 | GK11: 10849 | GL11: 10849 | GM11: 11689.25 | GN11: 11750.85 | GO11: 11812.66 | GP11: 11874.68 | GQ11: 11936.91 | GR11: 11999.35 | GS11: 12062 | GT11: 12124.86 | GU11: 12187.93 | GW11: 0 | GX11: 13749 | GY11: 12374.1 | GZ11: 13749 | HA11: 13749 | HB11: 13749 | HC11: 13749 | HD11: 13749 | HE11: 13749 | HF11: 13749 | HG11: 13749 | HH11: 13749 | HI11: 13749 | HJ11: 13749 | HK11: 14813.85 | HL11: 14891.92 | HM11: 14970.25 | HN11: 15048.85 | HO11: 15127.71 | HP11: 15206.84 | HQ11: 15286.24 | HR11: 15365.9 | HS11: 15445.83 | HT11: 13749 | HU11: 12374.1 | HV11: 13749 | HW11: 13749 | HX11: 13749 | HY11: 13749 | HZ11: 13749 | IA11: 13749 | IB11: 13749 | IC11: 13749 | ID11: 13749 | IE11: 13749 | IF11: 13749 | IG11: 14813.85 | IH11: 14891.92 | II11: 14970.25 | IJ11: 15048.85 | IK11: 15127.71 | IL11: 15206.84 | IM11: 15286.24 | IN11: 15365.9 | IO11: 15445.83 | IP11: 13749 | IQ11: 12374.1 | IR11: 13749 | IS11: 13749 | IT11: 13749 | IU11: 13749 | IV11: 13749 | IW11: 13749 | IX11: 13749 | IY11: 13749 | IZ11: 13749 | JA11: 13749 | JB11: 13749 | JC11: 14813.85 | JD11: 14891.92 | JE11: 14970.25 | JF11: 15048.85 | JG11: 15127.71 | JH11: 15206.84 | JI11: 15286.24 | JJ11: 15365.9 | JK11: 15445.83 | JL11: 13049 | JM11: 11744.1 | JN11: 13049 | JO11: 13049 | JP11: 13049 | JQ11: 13049 | JR11: 13049 | JS11: 13049 | JT11: 13049 | JU11: 13049 | JV11: 13049 | JW11: 13049 | JX11: 13049 | JY11: 14059.64 | JZ11: 14133.73 | KA11: 14208.07 | KB11: 14282.67 | KC11: 14357.52 | KD11: 14432.62 | KE11: 14507.97 | KF11: 14583.58 | KG11: 14659.44 | KH11: 12299 | KI11: 11069.1 | KJ11: 12299 | KK11: 12299 | KL11: 12299 | KM11: 12299 | KN11: 12299 | KO11: 12299 | KP11: 12299 | KQ11: 12299 | KR11: 12299 | KS11: 12299 | KT11: 12299 | KU11: 13251.55 | KV11: 13321.38 | KW11: 13391.45 | KX11: 13461.76 | KY11: 13532.31 | KZ11: 13603.09 | LA11: 13674.12 | LB11: 13745.38 | LC11: 13816.88 | LD11: 12299 | LE11: 11069.1 | LF11: 12299 | LG11: 12299 | LH11: 12299 | LI11: 12299 | LJ11: 12299 | LK11: 12299 | LL11: 12299 | LM11: 12299 | LN11: 12299 | LO11: 12299 | LP11: 12299 | LQ11: 13251.55 | LR11: 13321.38 | LS11: 13391.45 | LT11: 13461.76 | LU11: 13532.31 | LV11: 13603.09 | LW11: 13674.12 | LX11: 13745.38 | LY11: 13816.88 | LZ11: 11599 | MA11: 10439.1 | MB11: 11599 | MC11: 11599 | MD11: 11599 | ME11: 11599 | MF11: 11599 | MG11: 11599 | MH11: 11599 | MI11: 11599 | MJ11: 11599 | MK11: 11599 | ML11: 11599 | MM11: 12497.34 | MN11: 12563.19 | MO11: 12629.28 | MP11: 12695.58 | MQ11: 12762.11 | MR11: 12828.87 | MS11: 12895.85 | MT11: 12963.06 | MU11: 13030.49 | MV11: 10849 | MW11: 9764.1 | MX11: 10849 | MY11: 10849 | MZ11: 10849 | NA11: 10849 | NB11: 10849 | NC11: 10849 | ND11: 10849 | NE11: 10849 | NF11: 10849 | NG11: 10849 | NH11: 10849 | NI11: 11689.25 | NJ11: 11750.85 | NK11: 11812.66 | NL11: 11874.68 | NM11: 11936.91 | NN11: 11999.35 | NO11: 12062 | NP11: 12124.86 | NQ11: 12187.93 | NS11: 16449 | NT11: 13749 | NU11: 13749 | NV11: 13749 | NW11: 13049 | NX11: 12299 | NY11: 12299 | NZ11: 11599 | OA11: 10849 | OC11: 0 | OD11: 13749 | OE11: 13749 | OF11: 13749 | OG11: 13049 | OH11: 12299 | OI11: 12299 | OJ11: 11599 | OK11: 10849 | OL11: 0 | OM11: 0 | OQ11: 21x | OR11: 21x | OS11: 21x | OT11: 21x | OU11: 21x | OV11: 21x | OW11: 21x | OX11: 21x | OZ11: 12x | PA11: 12x | PB11: 12x | PC11: 12x | PD11: 12x | PE11: 12x | PF11: 12x | PG11: 12x | PI11: 21x | PJ11: 21x | PK11: 21x | PL11: 21x | PM11: 21x | PN11: 21x | PO11: 21x | PP11: 21x | PR11: 12x | PS11: 12x | PT11: 12x | PU11: 12x | PV11: 12x | PW11: 12x | PX11: 12x | PY11: 12x
A12: EOL | B12: Smartphone | C12: Apple | D12: Vivo Total Família 3 | E12: iPhone 13 Pro Max 128GB | F12: 6099 | G12: 5489.1 | H12: 6099 | I12: 6099 | J12: 6099 | K12: 6099 | L12: 6099 | M12: 6099 | N12: 6099 | O12: 6099 | P12: 6099 | Q12: 6099 | R12: 6099 | S12: 6571.36 | T12: 6605.99 | U12: 6640.74 | V12: 6675.61 | W12: 6710.59 | X12: 6745.69 | Y12: 6780.91 | Z12: 6816.25 | AA12: 6851.71 | AB12: 5699 | AC12: 5129.1 | AD12: 5699 | AE12: 5699 | AF12: 5699 | AG12: 5699 | AH12: 5699 | AI12: 5699 | AJ12: 5699 | AK12: 5699 | AL12: 5699 | AM12: 5699 | AN12: 5699 | AO12: 6140.38 | AP12: 6172.74 | AQ12: 6205.21 | AR12: 6237.79 | AS12: 6270.48 | AT12: 6303.28 | AU12: 6336.19 | AV12: 6369.21 | AW12: 6402.34 | AX12: 5599 | AY12: 5039.1 | AZ12: 5599 | BA12: 5599 | BB12: 5599 | BC12: 5599 | BD12: 5599 | BE12: 5599 | BF12: 5599 | BG12: 5599 | BH12: 5599 | BI12: 5599 | BJ12: 5599 | BK12: 6032.64 | BL12: 6064.43 | BM12: 6096.33 | BN12: 6128.34 | BO12: 6160.45 | BP12: 6192.68 | BQ12: 6225.01 | BR12: 6257.45 | BS12: 6290 | BT12: 5499 | BU12: 4949.1 | BV12: 5499 | BW12: 5499 | BX12: 5499 | BY12: 5499 | BZ12: 5499 | CA12: 5499 | CB12: 5499 | CC12: 5499 | CD12: 5499 | CE12: 5499 | CF12: 5499 | CG12: 5924.89 | CH12: 5956.12 | CI12: 5987.45 | CJ12: 6018.88 | CK12: 6050.42 | CL12: 6082.07 | CM12: 6113.83 | CN12: 6145.69 | CO12: 6177.66 | CP12: 5399 | CQ12: 4859.1 | CR12: 5399 | CS12: 5399 | CT12: 5399 | CU12: 5399 | CV12: 5399 | CW12: 5399 | CX12: 5399 | CY12: 5399 | CZ12: 5399 | DA12: 5399 | DB12: 5399 | DC12: 5817.15 | DD12: 5847.8 | DE12: 5878.56 | DF12: 5909.43 | DG12: 5940.4 | DH12: 5971.47 | DI12: 6002.65 | DJ12: 6033.93 | DK12: 6065.32 | DL12: 5199 | DM12: 4679.1 | DN12: 5199 | DO12: 5199 | DP12: 5199 | DQ12: 5199 | DR12: 5199 | DS12: 5199 | DT12: 5199 | DU12: 5199 | DV12: 5199 | DW12: 5199 | DX12: 5199 | DY12: 5601.66 | DZ12: 5631.18 | EA12: 5660.8 | EB12: 5690.52 | EC12: 5720.34 | ED12: 5750.26 | EE12: 5780.29 | EF12: 5810.41 | EG12: 5840.63 | EH12: 5099 | EI12: 4589.1 | EJ12: 5099 | EK12: 5099 | EL12: 5099 | EM12: 5099 | EN12: 5099 | EO12: 5099 | EP12: 5099 | EQ12: 5099 | ER12: 5099 | ES12: 5099 | ET12: 5099 | EU12: 5493.91 | EV12: 5522.87 | EW12: 5551.92 | EX12: 5581.06 | EY12: 5610.31 | EZ12: 5639.66 | FA12: 5669.1 | FB12: 5698.65 | FC12: 5728.29 | FD12: 4999 | FE12: 4499.1 | FF12: 4999 | FG12: 4999 | FH12: 4999 | FI12: 4999 | FJ12: 4999 | FK12: 4999 | FL12: 4999 | FM12: 4999 | FN12: 4999 | FO12: 4999 | FP12: 4999 | FQ12: 5386.17 | FR12: 5414.55 | FS12: 5443.03 | FT12: 5471.61 | FU12: 5500.29 | FV12: 5529.06 | FW12: 5557.92 | FX12: 5586.89 | FY12: 5615.95 | FZ12: 4899 | GA12: 4409.1 | GB12: 4899 | GC12: 4899 | GD12: 4899 | GE12: 4899 | GF12: 4899 | GG12: 4899 | GH12: 4899 | GI12: 4899 | GJ12: 4899 | GK12: 4899 | GL12: 4899 | GM12: 5278.42 | GN12: 5306.24 | GO12: 5334.15 | GP12: 5362.16 | GQ12: 5390.26 | GR12: 5418.45 | GS12: 5446.74 | GT12: 5475.13 | GU12: 5503.61 | GW12: 0 | GX12: 5699 | GY12: 5129.1 | GZ12: 5699 | HA12: 5699 | HB12: 5699 | HC12: 5699 | HD12: 5699 | HE12: 5699 | HF12: 5699 | HG12: 5699 | HH12: 5699 | HI12: 5699 | HJ12: 5699 | HK12: 6140.38 | HL12: 6172.74 | HM12: 6205.21 | HN12: 6237.79 | HO12: 6270.48 | HP12: 6303.28 | HQ12: 6336.19 | HR12: 6369.21 | HS12: 6402.34 | HT12: 5599 | HU12: 5039.1 | HV12: 5599 | HW12: 5599 | HX12: 5599 | HY12: 5599 | HZ12: 5599 | IA12: 5599 | IB12: 5599 | IC12: 5599 | ID12: 5599 | IE12: 5599 | IF12: 5599 | IG12: 6032.64 | IH12: 6064.43 | II12: 6096.33 | IJ12: 6128.34 | IK12: 6160.45 | IL12: 6192.68 | IM12: 6225.01 | IN12: 6257.45 | IO12: 6290 | IP12: 5499 | IQ12: 4949.1 | IR12: 5499 | IS12: 5499 | IT12: 5499 | IU12: 5499 | IV12: 5499 | IW12: 5499 | IX12: 5499 | IY12: 5499 | IZ12: 5499 | JA12: 5499 | JB12: 5499 | JC12: 5924.89 | JD12: 5956.12 | JE12: 5987.45 | JF12: 6018.88 | JG12: 6050.42 | JH12: 6082.07 | JI12: 6113.83 | JJ12: 6145.69 | JK12: 6177.66 | JL12: 5399 | JM12: 4859.1 | JN12: 5399 | JO12: 5399 | JP12: 5399 | JQ12: 5399 | JR12: 5399 | JS12: 5399 | JT12: 5399 | JU12: 5399 | JV12: 5399 | JW12: 5399 | JX12: 5399 | JY12: 5817.15 | JZ12: 5847.8 | KA12: 5878.56 | KB12: 5909.43 | KC12: 5940.4 | KD12: 5971.47 | KE12: 6002.65 | KF12: 6033.93 | KG12: 6065.32 | KH12: 5199 | KI12: 4679.1 | KJ12: 5199 | KK12: 5199 | KL12: 5199 | KM12: 5199 | KN12: 5199 | KO12: 5199 | KP12: 5199 | KQ12: 5199 | KR12: 5199 | KS12: 5199 | KT12: 5199 | KU12: 5601.66 | KV12: 5631.18 | KW12: 5660.8 | KX12: 5690.52 | KY12: 5720.34 | KZ12: 5750.26 | LA12: 5780.29 | LB12: 5810.41 | LC12: 5840.63 | LD12: 5099 | LE12: 4589.1 | LF12: 5099 | LG12: 5099 | LH12: 5099 | LI12: 5099 | LJ12: 5099 | LK12: 5099 | LL12: 5099 | LM12: 5099 | LN12: 5099 | LO12: 5099 | LP12: 5099 | LQ12: 5493.91 | LR12: 5522.87 | LS12: 5551.92 | LT12: 5581.06 | LU12: 5610.31 | LV12: 5639.66 | LW12: 5669.1 | LX12: 5698.65 | LY12: 5728.29 | LZ12: 4999 | MA12: 4499.1 | MB12: 4999 | MC12: 4999 | MD12: 4999 | ME12: 4999 | MF12: 4999 | MG12: 4999 | MH12: 4999 | MI12: 4999 | MJ12: 4999 | MK12: 4999 | ML12: 4999 | MM12: 5386.17 | MN12: 5414.55 | MO12: 5443.03 | MP12: 5471.61 | MQ12: 5500.29 | MR12: 5529.06 | MS12: 5557.92 | MT12: 5586.89 | MU12: 5615.95 | MV12: 4899 | MW12: 4409.1 | MX12: 4899 | MY12: 4899 | MZ12: 4899 | NA12: 4899 | NB12: 4899 | NC12: 4899 | ND12: 4899 | NE12: 4899 | NF12: 4899 | NG12: 4899 | NH12: 4899 | NI12: 5278.42 | NJ12: 5306.24 | NK12: 5334.15 | NL12: 5362.16 | NM12: 5390.26 | NN12: 5418.45 | NO12: 5446.74 | NP12: 5475.13 | NQ12: 5503.61 | NS12: 6099 | NT12: 5699 | NU12: 5599 | NV12: 5499 | NW12: 5399 | NX12: 5199 | NY12: 5099 | NZ12: 4999 | OA12: 4899 | OC12: 0 | OD12: 5699 | OE12: 5599 | OF12: 5499 | OG12: 5399 | OH12: 5199 | OI12: 5099 | OJ12: 4999 | OK12: 4899 | OL12: 0 | OM12: 0 | OQ12: 21x | OR12: 21x | OS12: 21x | OT12: 21x | OU12: 21x | OV12: 21x | OW12: 21x | OX12: 21x | OZ12: 12x | PA12: 12x | PB12: 12x | PC12: 12x | PD12: 12x | PE12: 12x | PF12: 12x | PG12: 12x | PI12: 21x | PJ12: 21x | PK12: 21x | PL12: 21x | PM12: 21x | PN12: 21x | PO12: 21x | PP12: 21x | PR12: 12x | PS12: 12x | PT12: 12x | PU12: 12x | PV12: 12x | PW12: 12x | PX12: 12x | PY12: 12x
A13: EOL | B13: Smartphone | C13: Apple | D13: Vivo Total Família 3 | E13: iPhone 13 Pro Max 1TB | F13: 6299 | G13: 5669.1 | H13: 6299 | I13: 6299 | J13: 6299 | K13: 6299 | L13: 6299 | M13: 6299 | N13: 6299 | O13: 6299 | P13: 6299 | Q13: 6299 | R13: 6299 | S13: 6786.85 | T13: 6822.62 | U13: 6858.51 | V13: 6894.51 | W13: 6930.65 | X13: 6966.9 | Y13: 7003.27 | Z13: 7039.77 | AA13: 7076.39 | AB13: 6299 | AC13: 5669.1 | AD13: 6299 | AE13: 6299 | AF13: 6299 | AG13: 6299 | AH13: 6299 | AI13: 6299 | AJ13: 6299 | AK13: 6299 | AL13: 6299 | AM13: 6299 | AN13: 6299 | AO13: 6786.85 | AP13: 6822.62 | AQ13: 6858.51 | AR13: 6894.51 | AS13: 6930.65 | AT13: 6966.9 | AU13: 7003.27 | AV13: 7039.77 | AW13: 7076.39 | AX13: 6199 | AY13: 5579.1 | AZ13: 6199 | BA13: 6199 | BB13: 6199 | BC13: 6199 | BD13: 6199 | BE13: 6199 | BF13: 6199 | BG13: 6199 | BH13: 6199 | BI13: 6199 | BJ13: 6199 | BK13: 6679.11 | BL13: 6714.31 | BM13: 6749.62 | BN13: 6785.06 | BO13: 6820.62 | BP13: 6856.3 | BQ13: 6892.09 | BR13: 6928.01 | BS13: 6964.05 | BT13: 6099 | BU13: 5489.1 | BV13: 6099 | BW13: 6099 | BX13: 6099 | BY13: 6099 | BZ13: 6099 | CA13: 6099 | CB13: 6099 | CC13: 6099 | CD13: 6099 | CE13: 6099 | CF13: 6099 | CG13: 6571.36 | CH13: 6605.99 | CI13: 6640.74 | CJ13: 6675.61 | CK13: 6710.59 | CL13: 6745.69 | CM13: 6780.91 | CN13: 6816.25 | CO13: 6851.71 | CP13: 5999 | CQ13: 5399.1 | CR13: 5999 | CS13: 5999 | CT13: 5999 | CU13: 5999 | CV13: 5999 | CW13: 5999 | CX13: 5999 | CY13: 5999 | CZ13: 5999 | DA13: 5999 | DB13: 5999 | DC13: 6463.62 | DD13: 6497.68 | DE13: 6531.86 | DF13: 6566.15 | DG13: 6600.56 | DH13: 6635.09 | DI13: 6669.73 | DJ13: 6704.49 | DK13: 6739.37 | DL13: 5899 | DM13: 5309.1 | DN13: 5899 | DO13: 5899 | DP13: 5899 | DQ13: 5899 | DR13: 5899 | DS13: 5899 | DT13: 5899 | DU13: 5899 | DV13: 5899 | DW13: 5899 | DX13: 5899 | DY13: 6355.87 | DZ13: 6389.37 | EA13: 6422.98 | EB13: 6456.7 | EC13: 6490.53 | ED13: 6524.49 | EE13: 6558.55 | EF13: 6592.73 | EG13: 6627.02 | EH13: 5799 | EI13: 5219.1 | EJ13: 5799 | EK13: 5799 | EL13: 5799 | EM13: 5799 | EN13: 5799 | EO13: 5799 | EP13: 5799 | EQ13: 5799 | ER13: 5799 | ES13: 5799 | ET13: 5799 | EU13: 6248.13 | EV13: 6281.06 | EW13: 6314.09 | EX13: 6347.24 | EY13: 6380.51 | EZ13: 6413.88 | FA13: 6447.37 | FB13: 6480.97 | FC13: 6514.68 | FD13: 5699 | FE13: 5129.1 | FF13: 5699 | FG13: 5699 | FH13: 5699 | FI13: 5699 | FJ13: 5699 | FK13: 5699 | FL13: 5699 | FM13: 5699 | FN13: 5699 | FO13: 5699 | FP13: 5699 | FQ13: 6140.38 | FR13: 6172.74 | FS13: 6205.21 | FT13: 6237.79 | FU13: 6270.48 | FV13: 6303.28 | FW13: 6336.19 | FX13: 6369.21 | FY13: 6402.34 | FZ13: 5599 | GA13: 5039.1 | GB13: 5599 | GC13: 5599 | GD13: 5599 | GE13: 5599 | GF13: 5599 | GG13: 5599 | GH13: 5599 | GI13: 5599 | GJ13: 5599 | GK13: 5599 | GL13: 5599 | GM13: 6032.64 | GN13: 6064.43 | GO13: 6096.33 | GP13: 6128.34 | GQ13: 6160.45 | GR13: 6192.68 | GS13: 6225.01 | GT13: 6257.45 | GU13: 6290 | GW13: 0 | GX13: 6299 | GY13: 5669.1 | GZ13: 6299 | HA13: 6299 | HB13: 6299 | HC13: 6299 | HD13: 6299 | HE13: 6299 | HF13: 6299 | HG13: 6299 | HH13: 6299 | HI13: 6299 | HJ13: 6299 | HK13: 6786.85 | HL13: 6822.62 | HM13: 6858.51 | HN13: 6894.51 | HO13: 6930.65 | HP13: 6966.9 | HQ13: 7003.27 | HR13: 7039.77 | HS13: 7076.39 | HT13: 6199 | HU13: 5579.1 | HV13: 6199 | HW13: 6199 | HX13: 6199 | HY13: 6199 | HZ13: 6199 | IA13: 6199 | IB13: 6199 | IC13: 6199 | ID13: 6199 | IE13: 6199 | IF13: 6199 | IG13: 6679.11 | IH13: 6714.31 | II13: 6749.62 | IJ13: 6785.06 | IK13: 6820.62 | IL13: 6856.3 | IM13: 6892.09 | IN13: 6928.01 | IO13: 6964.05 | IP13: 6099 | IQ13: 5489.1 | IR13: 6099 | IS13: 6099 | IT13: 6099 | IU13: 6099 | IV13: 6099 | IW13: 6099 | IX13: 6099 | IY13: 6099 | IZ13: 6099 | JA13: 6099 | JB13: 6099 | JC13: 6571.36 | JD13: 6605.99 | JE13: 6640.74 | JF13: 6675.61 | JG13: 6710.59 | JH13: 6745.69 | JI13: 6780.91 | JJ13: 6816.25 | JK13: 6851.71 | JL13: 5999 | JM13: 5399.1 | JN13: 5999 | JO13: 5999 | JP13: 5999 | JQ13: 5999 | JR13: 5999 | JS13: 5999 | JT13: 5999 | JU13: 5999 | JV13: 5999 | JW13: 5999 | JX13: 5999 | JY13: 6463.62 | JZ13: 6497.68 | KA13: 6531.86 | KB13: 6566.15 | KC13: 6600.56 | KD13: 6635.09 | KE13: 6669.73 | KF13: 6704.49 | KG13: 6739.37 | KH13: 5899 | KI13: 5309.1 | KJ13: 5899 | KK13: 5899 | KL13: 5899 | KM13: 5899 | KN13: 5899 | KO13: 5899 | KP13: 5899 | KQ13: 5899 | KR13: 5899 | KS13: 5899 | KT13: 5899 | KU13: 6355.87 | KV13: 6389.37 | KW13: 6422.98 | KX13: 6456.7 | KY13: 6490.53 | KZ13: 6524.49 | LA13: 6558.55 | LB13: 6592.73 | LC13: 6627.02 | LD13: 5799 | LE13: 5219.1 | LF13: 5799 | LG13: 5799 | LH13: 5799 | LI13: 5799 | LJ13: 5799 | LK13: 5799 | LL13: 5799 | LM13: 5799 | LN13: 5799 | LO13: 5799 | LP13: 5799 | LQ13: 6248.13 | LR13: 6281.06 | LS13: 6314.09 | LT13: 6347.24 | LU13: 6380.51 | LV13: 6413.88 | LW13: 6447.37 | LX13: 6480.97 | LY13: 6514.68 | LZ13: 5699 | MA13: 5129.1 | MB13: 5699 | MC13: 5699 | MD13: 5699 | ME13: 5699 | MF13: 5699 | MG13: 5699 | MH13: 5699 | MI13: 5699 | MJ13: 5699 | MK13: 5699 | ML13: 5699 | MM13: 6140.38 | MN13: 6172.74 | MO13: 6205.21 | MP13: 6237.79 | MQ13: 6270.48 | MR13: 6303.28 | MS13: 6336.19 | MT13: 6369.21 | MU13: 6402.34 | MV13: 5599 | MW13: 5039.1 | MX13: 5599 | MY13: 5599 | MZ13: 5599 | NA13: 5599 | NB13: 5599 | NC13: 5599 | ND13: 5599 | NE13: 5599 | NF13: 5599 | NG13: 5599 | NH13: 5599 | NI13: 6032.64 | NJ13: 6064.43 | NK13: 6096.33 | NL13: 6128.34 | NM13: 6160.45 | NN13: 6192.68 | NO13: 6225.01 | NP13: 6257.45 | NQ13: 6290 | NS13: 6299 | NT13: 6299 | NU13: 6199 | NV13: 6099 | NW13: 5999 | NX13: 5899 | NY13: 5799 | NZ13: 5699 | OA13: 5599 | OC13: 0 | OD13: 6299 | OE13: 6199 | OF13: 6099 | OG13: 5999 | OH13: 5899 | OI13: 5799 | OJ13: 5699 | OK13: 5599 | OL13: 0 | OM13: 0 | OQ13: 21x | OR13: 21x | OS13: 21x | OT13: 21x | OU13: 21x | OV13: 21x | OW13: 21x | OX13: 21x | OZ13: 12x | PA13: 12x | PB13: 12x | PC13: 12x | PD13: 12x | PE13: 12x | PF13: 12x | PG13: 12x | PI13: 21x | PJ13: 21x | PK13: 21x | PL13: 21x | PM13: 21x | PN13: 21x | PO13: 21x | PP13: 21x | PR13: 12x | PS13: 12x | PT13: 12x | PU13: 12x | PV13: 12x | PW13: 12x | PX13: 12x | PY13: 12x
A14: EOL | B14: Smartphone | C14: Apple | D14: Vivo Total Família 3 | E14: iPhone 13 Pro Max 256GB | F14: 6149 | G14: 5534.1 | H14: 6149 | I14: 6149 | J14: 6149 | K14: 6149 | L14: 6149 | M14: 6149 | N14: 6149 | O14: 6149 | P14: 6149 | Q14: 6149 | R14: 6149 | S14: 6625.24 | T14: 6660.15 | U14: 6695.18 | V14: 6730.33 | W14: 6765.6 | X14: 6800.99 | Y14: 6836.5 | Z14: 6872.13 | AA14: 6907.88 | AB14: 5999 | AC14: 5399.1 | AD14: 5999 | AE14: 5999 | AF14: 5999 | AG14: 5999 | AH14: 5999 | AI14: 5999 | AJ14: 5999 | AK14: 5999 | AL14: 5999 | AM14: 5999 | AN14: 5999 | AO14: 6463.62 | AP14: 6497.68 | AQ14: 6531.86 | AR14: 6566.15 | AS14: 6600.56 | AT14: 6635.09 | AU14: 6669.73 | AV14: 6704.49 | AW14: 6739.37 | AX14: 5899 | AY14: 5309.1 | AZ14: 5899 | BA14: 5899 | BB14: 5899 | BC14: 5899 | BD14: 5899 | BE14: 5899 | BF14: 5899 | BG14: 5899 | BH14: 5899 | BI14: 5899 | BJ14: 5899 | BK14: 6355.87 | BL14: 6389.37 | BM14: 6422.98 | BN14: 6456.7 | BO14: 6490.53 | BP14: 6524.49 | BQ14: 6558.55 | BR14: 6592.73 | BS14: 6627.02 | BT14: 5799 | BU14: 5219.1 | BV14: 5799 | BW14: 5799 | BX14: 5799 | BY14: 5799 | BZ14: 5799 | CA14: 5799 | CB14: 5799 | CC14: 5799 | CD14: 5799 | CE14: 5799 | CF14: 5799 | CG14: 6248.13 | CH14: 6281.06 | CI14: 6314.09 | CJ14: 6347.24 | CK14: 6380.51 | CL14: 6413.88 | CM14: 6447.37 | CN14: 6480.97 | CO14: 6514.68 | CP14: 5699 | CQ14: 5129.1 | CR14: 5699 | CS14: 5699 | CT14: 5699 | CU14: 5699 | CV14: 5699 | CW14: 5699 | CX14: 5699 | CY14: 5699 | CZ14: 5699 | DA14: 5699 | DB14: 5699 | DC14: 6140.38 | DD14: 6172.74 | DE14: 6205.21 | DF14: 6237.79 | DG14: 6270.48 | DH14: 6303.28 | DI14: 6336.19 | DJ14: 6369.21 | DK14: 6402.34 | DL14: 5599 | DM14: 5039.1 | DN14: 5599 | DO14: 5599 | DP14: 5599 | DQ14: 5599 | DR14: 5599 | DS14: 5599 | DT14: 5599 | DU14: 5599 | DV14: 5599 | DW14: 5599 | DX14: 5599 | DY14: 6032.64 | DZ14: 6064.43 | EA14: 6096.33 | EB14: 6128.34 | EC14: 6160.45 | ED14: 6192.68 | EE14: 6225.01 | EF14: 6257.45 | EG14: 6290 | EH14: 5499 | EI14: 4949.1 | EJ14: 5499 | EK14: 5499 | EL14: 5499 | EM14: 5499 | EN14: 5499 | EO14: 5499 | EP14: 5499 | EQ14: 5499 | ER14: 5499 | ES14: 5499 | ET14: 5499 | EU14: 5924.89 | EV14: 5956.12 | EW14: 5987.45 | EX14: 6018.88 | EY14: 6050.42 | EZ14: 6082.07 | FA14: 6113.83 | FB14: 6145.69 | FC14: 6177.66 | FD14: 5399 | FE14: 4859.1 | FF14: 5399 | FG14: 5399 | FH14: 5399 | FI14: 5399 | FJ14: 5399 | FK14: 5399 | FL14: 5399 | FM14: 5399 | FN14: 5399 | FO14: 5399 | FP14: 5399 | FQ14: 5817.15 | FR14: 5847.8 | FS14: 5878.56 | FT14: 5909.43 | FU14: 5940.4 | FV14: 5971.47 | FW14: 6002.65 | FX14: 6033.93 | FY14: 6065.32 | FZ14: 5299 | GA14: 4769.1 | GB14: 5299 | GC14: 5299 | GD14: 5299 | GE14: 5299 | GF14: 5299 | GG14: 5299 | GH14: 5299 | GI14: 5299 | GJ14: 5299 | GK14: 5299 | GL14: 5299 | GM14: 5709.4 | GN14: 5739.49 | GO14: 5769.68 | GP14: 5799.97 | GQ14: 5830.37 | GR14: 5860.87 | GS14: 5891.47 | GT14: 5922.17 | GU14: 5952.97 | GW14: 0 | GX14: 5999 | GY14: 5399.1 | GZ14: 5999 | HA14: 5999 | HB14: 5999 | HC14: 5999 | HD14: 5999 | HE14: 5999 | HF14: 5999 | HG14: 5999 | HH14: 5999 | HI14: 5999 | HJ14: 5999 | HK14: 6463.62 | HL14: 6497.68 | HM14: 6531.86 | HN14: 6566.15 | HO14: 6600.56 | HP14: 6635.09 | HQ14: 6669.73 | HR14: 6704.49 | HS14: 6739.37 | HT14: 5899 | HU14: 5309.1 | HV14: 5899 | HW14: 5899 | HX14: 5899 | HY14: 5899 | HZ14: 5899 | IA14: 5899 | IB14: 5899 | IC14: 5899 | ID14: 5899 | IE14: 5899 | IF14: 5899 | IG14: 6355.87 | IH14: 6389.37 | II14: 6422.98 | IJ14: 6456.7 | IK14: 6490.53 | IL14: 6524.49 | IM14: 6558.55 | IN14: 6592.73 | IO14: 6627.02 | IP14: 5799 | IQ14: 5219.1 | IR14: 5799 | IS14: 5799 | IT14: 5799 | IU14: 5799 | IV14: 5799 | IW14: 5799 | IX14: 5799 | IY14: 5799 | IZ14: 5799 | JA14: 5799 | JB14: 5799 | JC14: 6248.13 | JD14: 6281.06 | JE14: 6314.09 | JF14: 6347.24 | JG14: 6380.51 | JH14: 6413.88 | JI14: 6447.37 | JJ14: 6480.97 | JK14: 6514.68 | JL14: 5699 | JM14: 5129.1 | JN14: 5699 | JO14: 5699 | JP14: 5699 | JQ14: 5699 | JR14: 5699 | JS14: 5699 | JT14: 5699 | JU14: 5699 | JV14: 5699 | JW14: 5699 | JX14: 5699 | JY14: 6140.38 | JZ14: 6172.74 | KA14: 6205.21 | KB14: 6237.79 | KC14: 6270.48 | KD14: 6303.28 | KE14: 6336.19 | KF14: 6369.21 | KG14: 6402.34 | KH14: 5599 | KI14: 5039.1 | KJ14: 5599 | KK14: 5599 | KL14: 5599 | KM14: 5599 | KN14: 5599 | KO14: 5599 | KP14: 5599 | KQ14: 5599 | KR14: 5599 | KS14: 5599 | KT14: 5599 | KU14: 6032.64 | KV14: 6064.43 | KW14: 6096.33 | KX14: 6128.34 | KY14: 6160.45 | KZ14: 6192.68 | LA14: 6225.01 | LB14: 6257.45 | LC14: 6290 | LD14: 5499 | LE14: 4949.1 | LF14: 5499 | LG14: 5499 | LH14: 5499 | LI14: 5499 | LJ14: 5499 | LK14: 5499 | LL14: 5499 | LM14: 5499 | LN14: 5499 | LO14: 5499 | LP14: 5499 | LQ14: 5924.89 | LR14: 5956.12 | LS14: 5987.45 | LT14: 6018.88 | LU14: 6050.42 | LV14: 6082.07 | LW14: 6113.83 | LX14: 6145.69 | LY14: 6177.66 | LZ14: 5399 | MA14: 4859.1 | MB14: 5399 | MC14: 5399 | MD14: 5399 | ME14: 5399 | MF14: 5399 | MG14: 5399 | MH14: 5399 | MI14: 5399 | MJ14: 5399 | MK14: 5399 | ML14: 5399 | MM14: 5817.15 | MN14: 5847.8 | MO14: 5878.56 | MP14: 5909.43 | MQ14: 5940.4 | MR14: 5971.47 | MS14: 6002.65 | MT14: 6033.93 | MU14: 6065.32 | MV14: 5299 | MW14: 4769.1 | MX14: 5299 | MY14: 5299 | MZ14: 5299 | NA14: 5299 | NB14: 5299 | NC14: 5299 | ND14: 5299 | NE14: 5299 | NF14: 5299 | NG14: 5299 | NH14: 5299 | NI14: 5709.4 | NJ14: 5739.49 | NK14: 5769.68 | NL14: 5799.97 | NM14: 5830.37 | NN14: 5860.87 | NO14: 5891.47 | NP14: 5922.17 | NQ14: 5952.97 | NS14: 6149 | NT14: 5999 | NU14: 5899 | NV14: 5799 | NW14: 5699 | NX14: 5599 | NY14: 5499 | NZ14: 5399 | OA14: 5299 | OC14: 0 | OD14: 5999 | OE14: 5899 | OF14: 5799 | OG14: 5699 | OH14: 5599 | OI14: 5499 | OJ14: 5399 | OK14: 5299 | OL14: 0 | OM14: 0 | OQ14: 21x | OR14: 21x | OS14: 21x | OT14: 21x | OU14: 21x | OV14: 21x | OW14: 21x | OX14: 21x | OZ14: 12x | PA14: 12x | PB14: 12x | PC14: 12x | PD14: 12x | PE14: 12x | PF14: 12x | PG14: 12x | PI14: 21x | PJ14: 21x | PK14: 21x | PL14: 21x | PM14: 21x | PN14: 21x | PO14: 21x | PP14: 21x | PR14: 12x | PS14: 12x | PT14: 12x | PU14: 12x | PV14: 12x | PW14: 12x | PX14: 12x | PY14: 12x
A15: EOL | B15: Smartphone | C15: Apple | D15: Vivo Total Família 3 | E15: iPhone 13 Pro Max 512GB | F15: 6349 | G15: 5714.1 | H15: 6349 | I15: 6349 | J15: 6349 | K15: 6349 | L15: 6349 | M15: 6349 | N15: 6349 | O15: 6349 | P15: 6349 | Q15: 6349 | R15: 6349 | S15: 6840.73 | T15: 6876.78 | U15: 6912.95 | V15: 6949.24 | W15: 6985.66 | X15: 7022.2 | Y15: 7058.86 | Z15: 7095.65 | AA15: 7132.56 | AB15: 6199 | AC15: 5579.1 | AD15: 6199 | AE15: 6199 | AF15: 6199 | AG15: 6199 | AH15: 6199 | AI15: 6199 | AJ15: 6199 | AK15: 6199 | AL15: 6199 | AM15: 6199 | AN15: 6199 | AO15: 6679.11 | AP15: 6714.31 | AQ15: 6749.62 | AR15: 6785.06 | AS15: 6820.62 | AT15: 6856.3 | AU15: 6892.09 | AV15: 6928.01 | AW15: 6964.05 | AX15: 6099 | AY15: 5489.1 | AZ15: 6099 | BA15: 6099 | BB15: 6099 | BC15: 6099 | BD15: 6099 | BE15: 6099 | BF15: 6099 | BG15: 6099 | BH15: 6099 | BI15: 6099 | BJ15: 6099 | BK15: 6571.36 | BL15: 6605.99 | BM15: 6640.74 | BN15: 6675.61 | BO15: 6710.59 | BP15: 6745.69 | BQ15: 6780.91 | BR15: 6816.25 | BS15: 6851.71 | BT15: 5999 | BU15: 5399.1 | BV15: 5999 | BW15: 5999 | BX15: 5999 | BY15: 5999 | BZ15: 5999 | CA15: 5999 | CB15: 5999 | CC15: 5999 | CD15: 5999 | CE15: 5999 | CF15: 5999 | CG15: 6463.62 | CH15: 6497.68 | CI15: 6531.86 | CJ15: 6566.15 | CK15: 6600.56 | CL15: 6635.09 | CM15: 6669.73 | CN15: 6704.49 | CO15: 6739.37 | CP15: 5899 | CQ15: 5309.1 | CR15: 5899 | CS15: 5899 | CT15: 5899 | CU15: 5899 | CV15: 5899 | CW15: 5899 | CX15: 5899 | CY15: 5899 | CZ15: 5899 | DA15: 5899 | DB15: 5899 | DC15: 6355.87 | DD15: 6389.37 | DE15: 6422.98 | DF15: 6456.7 | DG15: 6490.53 | DH15: 6524.49 | DI15: 6558.55 | DJ15: 6592.73 | DK15: 6627.02 | DL15: 5799 | DM15: 5219.1 | DN15: 5799 | DO15: 5799 | DP15: 5799 | DQ15: 5799 | DR15: 5799 | DS15: 5799 | DT15: 5799 | DU15: 5799 | DV15: 5799 | DW15: 5799 | DX15: 5799 | DY15: 6248.13 | DZ15: 6281.06 | EA15: 6314.09 | EB15: 6347.24 | EC15: 6380.51 | ED15: 6413.88 | EE15: 6447.37 | EF15: 6480.97 | EG15: 6514.68 | EH15: 5699 | EI15: 5129.1 | EJ15: 5699 | EK15: 5699 | EL15: 5699 | EM15: 5699 | EN15: 5699 | EO15: 5699 | EP15: 5699 | EQ15: 5699 | ER15: 5699 | ES15: 5699 | ET15: 5699 | EU15: 6140.38 | EV15: 6172.74 | EW15: 6205.21 | EX15: 6237.79 | EY15: 6270.48 | EZ15: 6303.28 | FA15: 6336.19 | FB15: 6369.21 | FC15: 6402.34 | FD15: 5599 | FE15: 5039.1 | FF15: 5599 | FG15: 5599 | FH15: 5599 | FI15: 5599 | FJ15: 5599 | FK15: 5599 | FL15: 5599 | FM15: 5599 | FN15: 5599 | FO15: 5599 | FP15: 5599 | FQ15: 6032.64 | FR15: 6064.43 | FS15: 6096.33 | FT15: 6128.34 | FU15: 6160.45 | FV15: 6192.68 | FW15: 6225.01 | FX15: 6257.45 | FY15: 6290 | FZ15: 5499 | GA15: 4949.1 | GB15: 5499 | GC15: 5499 | GD15: 5499 | GE15: 5499 | GF15: 5499 | GG15: 5499 | GH15: 5499 | GI15: 5499 | GJ15: 5499 | GK15: 5499 | GL15: 5499 | GM15: 5924.89 | GN15: 5956.12 | GO15: 5987.45 | GP15: 6018.88 | GQ15: 6050.42 | GR15: 6082.07 | GS15: 6113.83 | GT15: 6145.69 | GU15: 6177.66 | GW15: 0 | GX15: 6199 | GY15: 5579.1 | GZ15: 6199 | HA15: 6199 | HB15: 6199 | HC15: 6199 | HD15: 6199 | HE15: 6199 | HF15: 6199 | HG15: 6199 | HH15: 6199 | HI15: 6199 | HJ15: 6199 | HK15: 6679.11 | HL15: 6714.31 | HM15: 6749.62 | HN15: 6785.06 | HO15: 6820.62 | HP15: 6856.3 | HQ15: 6892.09 | HR15: 6928.01 | HS15: 6964.05 | HT15: 6099 | HU15: 5489.1 | HV15: 6099 | HW15: 6099 | HX15: 6099 | HY15: 6099 | HZ15: 6099 | IA15: 6099 | IB15: 6099 | IC15: 6099 | ID15: 6099 | IE15: 6099 | IF15: 6099 | IG15: 6571.36 | IH15: 6605.99 | II15: 6640.74 | IJ15: 6675.61 | IK15: 6710.59 | IL15: 6745.69 | IM15: 6780.91 | IN15: 6816.25 | IO15: 6851.71 | IP15: 5999 | IQ15: 5399.1 | IR15: 5999 | IS15: 5999 | IT15: 5999 | IU15: 5999 | IV15: 5999 | IW15: 5999 | IX15: 5999 | IY15: 5999 | IZ15: 5999 | JA15: 5999 | JB15: 5999 | JC15: 6463.62 | JD15: 6497.68 | JE15: 6531.86 | JF15: 6566.15 | JG15: 6600.56 | JH15: 6635.09 | JI15: 6669.73 | JJ15: 6704.49 | JK15: 6739.37 | JL15: 5899 | JM15: 5309.1 | JN15: 5899 | JO15: 5899 | JP15: 5899 | JQ15: 5899 | JR15: 5899 | JS15: 5899 | JT15: 5899 | JU15: 5899 | JV15: 5899 | JW15: 5899 | JX15: 5899 | JY15: 6355.87 | JZ15: 6389.37 | KA15: 6422.98 | KB15: 6456.7 | KC15: 6490.53 | KD15: 6524.49 | KE15: 6558.55 | KF15: 6592.73 | KG15: 6627.02 | KH15: 5799 | KI15: 5219.1 | KJ15: 5799 | KK15: 5799 | KL15: 5799 | KM15: 5799 | KN15: 5799 | KO15: 5799 | KP15: 5799 | KQ15: 5799 | KR15: 5799 | KS15: 5799 | KT15: 5799 | KU15: 6248.13 | KV15: 6281.06 | KW15: 6314.09 | KX15: 6347.24 | KY15: 6380.51 | KZ15: 6413.88 | LA15: 6447.37 | LB15: 6480.97 | LC15: 6514.68 | LD15: 5699 | LE15: 5129.1 | LF15: 5699 | LG15: 5699 | LH15: 5699 | LI15: 5699 | LJ15: 5699 | LK15: 5699 | LL15: 5699 | LM15: 5699 | LN15: 5699 | LO15: 5699 | LP15: 5699 | LQ15: 6140.38 | LR15: 6172.74 | LS15: 6205.21 | LT15: 6237.79 | LU15: 6270.48 | LV15: 6303.28 | LW15: 6336.19 | LX15: 6369.21 | LY15: 6402.34 | LZ15: 5599 | MA15: 5039.1 | MB15: 5599 | MC15: 5599 | MD15: 5599 | ME15: 5599 | MF15: 5599 | MG15: 5599 | MH15: 5599 | MI15: 5599 | MJ15: 5599 | MK15: 5599 | ML15: 5599 | MM15: 6032.64 | MN15: 6064.43 | MO15: 6096.33 | MP15: 6128.34 | MQ15: 6160.45 | MR15: 6192.68 | MS15: 6225.01 | MT15: 6257.45 | MU15: 6290 | MV15: 5499 | MW15: 4949.1 | MX15: 5499 | MY15: 5499 | MZ15: 5499 | NA15: 5499 | NB15: 5499 | NC15: 5499 | ND15: 5499 | NE15: 5499 | NF15: 5499 | NG15: 5499 | NH15: 5499 | NI15: 5924.89 | NJ15: 5956.12 | NK15: 5987.45 | NL15: 6018.88 | NM15: 6050.42 | NN15: 6082.07 | NO15: 6113.83 | NP15: 6145.69 | NQ15: 6177.66 | NS15: 6349 | NT15: 6199 | NU15: 6099 | NV15: 5999 | NW15: 5899 | NX15: 5799 | NY15: 5699 | NZ15: 5599 | OA15: 5499 | OC15: 0 | OD15: 6199 | OE15: 6099 | OF15: 5999 | OG15: 5899 | OH15: 5799 | OI15: 5699 | OJ15: 5599 | OK15: 5499 | OL15: 0 | OM15: 0 | OQ15: 21x | OR15: 21x | OS15: 21x | OT15: 21x | OU15: 21x | OV15: 21x | OW15: 21x | OX15: 21x | OZ15: 12x | PA15: 12x | PB15: 12x | PC15: 12x | PD15: 12x | PE15: 12x | PF15: 12x | PG15: 12x | PI15: 21x | PJ15: 21x | PK15: 21x | PL15: 21x | PM15: 21x | PN15: 21x | PO15: 21x | PP15: 21x | PR15: 12x | PS15: 12x | PT15: 12x | PU15: 12x | PV15: 12x | PW15: 12x | PX15: 12x | PY15: 12x
... A261: EOL | B261: Smartphone | C261: Apple | D261: Vivo Total Família 3 | E261: iPhone 18 Pro Max 2TB | F261: 21349 | G261: 19214.1 | H261: 21349 | I261: 21349 | J261: 21349 | K261: 21349 | L261: 21349 | M261: 21349 | N261: 21349 | O261: 21349 | P261: 21349 | Q261: 21349 | R261: 21349 | S261: 23002.47 | T261: 23123.68 | U261: 23245.31 | V261: 23367.36 | W261: 23489.82 | X261: 23612.69 | Y261: 23735.97 | Z261: 23859.67 | AA261: 23983.78 | AB261: 21349 | AC261: 19214.1 | AD261: 21349 | AE261: 21349 | AF261: 21349 | AG261: 21349 | AH261: 21349 | AI261: 21349 | AJ261: 21349 | AK261: 21349 | AL261: 21349 | AM261: 21349 | AN261: 21349 | AO261: 23002.47 | AP261: 23123.68 | AQ261: 23245.31 | AR261: 23367.36 | AS261: 23489.82 | AT261: 23612.69 | AU261: 23735.97 | AV261: 23859.67 | AW261: 23983.78 | AX261: 20249 | AY261: 18224.1 | AZ261: 20249 | BA261: 20249 | BB261: 20249 | BC261: 20249 | BD261: 20249 | BE261: 20249 | BF261: 20249 | BG261: 20249 | BH261: 20249 | BI261: 20249 | BJ261: 20249 | BK261: 21817.27 | BL261: 21932.24 | BM261: 22047.61 | BN261: 22163.36 | BO261: 22279.51 | BP261: 22396.05 | BQ261: 22512.98 | BR261: 22630.31 | BS261: 22748.03 | BT261: 19799 | BU261: 17819.1 | BV261: 19799 | BW261: 19799 | BX261: 19799 | BY261: 19799 | BZ261: 19799 | CA261: 19799 | CB261: 19799 | CC261: 19799 | CD261: 19799 | CE261: 19799 | CF261: 19799 | CG261: 21332.42 | CH261: 21444.84 | CI261: 21557.64 | CJ261: 21670.82 | CK261: 21784.39 | CL261: 21898.34 | CM261: 22012.67 | CN261: 22127.39 | CO261: 22242.49 | CP261: 18049 | CQ261: 16244.1 | CR261: 18049 | CS261: 18049 | CT261: 18049 | CU261: 18049 | CV261: 18049 | CW261: 18049 | CX261: 18049 | CY261: 18049 | CZ261: 18049 | DA261: 18049 | DB261: 18049 | DC261: 19446.89 | DD261: 19549.36 | DE261: 19652.19 | DF261: 19755.37 | DG261: 19858.9 | DH261: 19962.78 | DI261: 20067.01 | DJ261: 20171.59 | DK261: 20276.51 | DL261: 17599 | DM261: 15839.1 | DN261: 17599 | DO261: 17599 | DP261: 17599 | DQ261: 17599 | DR261: 17599 | DS261: 17599 | DT261: 17599 | DU261: 17599 | DV261: 17599 | DW261: 17599 | DX261: 17599 | DY261: 18962.03 | DZ261: 19061.96 | EA261: 19162.22 | EB261: 19262.83 | EC261: 19363.78 | ED261: 19465.06 | EE261: 19566.69 | EF261: 19668.67 | EG261: 19770.98 | EH261: 17099 | EI261: 15389.1 | EJ261: 17099 | EK261: 17099 | EL261: 17099 | EM261: 17099 | EN261: 17099 | EO261: 17099 | EP261: 17099 | EQ261: 17099 | ER261: 17099 | ES261: 17099 | ET261: 17099 | EU261: 18423.31 | EV261: 18520.39 | EW261: 18617.81 | EX261: 18715.56 | EY261: 18813.64 | EZ261: 18912.05 | FA261: 19010.79 | FB261: 19109.86 | FC261: 19209.27 | FD261: 16749 | FE261: 15074.1 | FF261: 16749 | FG261: 16749 | FH261: 16749 | FI261: 16749 | FJ261: 16749 | FK261: 16749 | FL261: 16749 | FM261: 16749 | FN261: 16749 | FO261: 16749 | FP261: 16749 | FQ261: 18046.2 | FR261: 18141.3 | FS261: 18236.72 | FT261: 18332.47 | FU261: 18428.54 | FV261: 18524.94 | FW261: 18621.66 | FX261: 18718.7 | FY261: 18816.07 | FZ261: 15799 | GA261: 14219.1 | GB261: 15799 | GC261: 15799 | GD261: 15799 | GE261: 15799 | GF261: 15799 | GG261: 15799 | GH261: 15799 | GI261: 15799 | GJ261: 15799 | GK261: 15799 | GL261: 15799 | GM261: 17022.62 | GN261: 17112.33 | GO261: 17202.34 | GP261: 17292.65 | GQ261: 17383.28 | GR261: 17474.21 | GS261: 17565.44 | GT261: 17656.98 | GU261: 17748.83 | GW261: 0 | GX261: 21349 | GY261: 19214.1 | GZ261: 21349 | HA261: 21349 | HB261: 21349 | HC261: 21349 | HD261: 21349 | HE261: 21349 | HF261: 21349 | HG261: 21349 | HH261: 21349 | HI261: 21349 | HJ261: 21349 | HK261: 23002.47 | HL261: 23123.68 | HM261: 23245.31 | HN261: 23367.36 | HO261: 23489.82 | HP261: 23612.69 | HQ261: 23735.97 | HR261: 23859.67 | HS261: 23983.78 | HT261: 20249 | HU261: 18224.1 | HV261: 20249 | HW261: 20249 | HX261: 20249 | HY261: 20249 | HZ261: 20249 | IA261: 20249 | IB261: 20249 | IC261: 20249 | ID261: 20249 | IE261: 20249 | IF261: 20249 | IG261: 21817.27 | IH261: 21932.24 | II261: 22047.61 | IJ261: 22163.36 | IK261: 22279.51 | IL261: 22396.05 | IM261: 22512.98 | IN261: 22630.31 | IO261: 22748.03 | IP261: 19799 | IQ261: 17819.1 | IR261: 19799 | IS261: 19799 | IT261: 19799 | IU261: 19799 | IV261: 19799 | IW261: 19799 | IX261: 19799 | IY261: 19799 | IZ261: 19799 | JA261: 19799 | JB261: 19799 | JC261: 21332.42 | JD261: 21444.84 | JE261: 21557.64 | JF261: 21670.82 | JG261: 21784.39 | JH261: 21898.34 | JI261: 22012.67 | JJ261: 22127.39 | JK261: 22242.49 | JL261: 18049 | JM261: 16244.1 | JN261: 18049 | JO261: 18049 | JP261: 18049 | JQ261: 18049 | JR261: 18049 | JS261: 18049 | JT261: 18049 | JU261: 18049 | JV261: 18049 | JW261: 18049 | JX261: 18049 | JY261: 19446.89 | JZ261: 19549.36 | KA261: 19652.19 | KB261: 19755.37 | KC261: 19858.9 | KD261: 19962.78 | KE261: 20067.01 | KF261: 20171.59 | KG261: 20276.51 | KH261: 17599 | KI261: 15839.1 | KJ261: 17599 | KK261: 17599 | KL261: 17599 | KM261: 17599 | KN261: 17599 | KO261: 17599 | KP261: 17599 | KQ261: 17599 | KR261: 17599 | KS261: 17599 | KT261: 17599 | KU261: 18962.03 | KV261: 19061.96 | KW261: 19162.22 | KX261: 19262.83 | KY261: 19363.78 | KZ261: 19465.06 | LA261: 19566.69 | LB261: 19668.67 | LC261: 19770.98 | LD261: 17099 | LE261: 15389.1 | LF261: 17099 | LG261: 17099 | LH261: 17099 | LI261: 17099 | LJ261: 17099 | LK261: 17099 | LL261: 17099 | LM261: 17099 | LN261: 17099 | LO261: 17099 | LP261: 17099 | LQ261: 18423.31 | LR261: 18520.39 | LS261: 18617.81 | LT261: 18715.56 | LU261: 18813.64 | LV261: 18912.05 | LW261: 19010.79 | LX261: 19109.86 | LY261: 19209.27 | LZ261: 16749 | MA261: 15074.1 | MB261: 16749 | MC261: 16749 | MD261: 16749 | ME261: 16749 | MF261: 16749 | MG261: 16749 | MH261: 16749 | MI261: 16749 | MJ261: 16749 | MK261: 16749 | ML261: 16749 | MM261: 18046.2 | MN261: 18141.3 | MO261: 18236.72 | MP261: 18332.47 | MQ261: 18428.54 | MR261: 18524.94 | MS261: 18621.66 | MT261: 18718.7 | MU261: 18816.07 | MV261: 15799 | MW261: 14219.1 | MX261: 15799 | MY261: 15799 | MZ261: 15799 | NA261: 15799 | NB261: 15799 | NC261: 15799 | ND261: 15799 | NE261: 15799 | NF261: 15799 | NG261: 15799 | NH261: 15799 | NI261: 17022.62 | NJ261: 17112.33 | NK261: 17202.34 | NL261: 17292.65 | NM261: 17383.28 | NN261: 17474.21 | NO261: 17565.44 | NP261: 17656.98 | NQ261: 17748.83 | NS261: 21349 | NT261: 21349 | NU261: 20249 | NV261: 19799 | NW261: 18049 | NX261: 17599 | NY261: 17099 | NZ261: 16749 | OA261: 15799 | OC261: 0 | OD261: 21349 | OE261: 20249 | OF261: 19799 | OG261: 18049 | OH261: 17599 | OI261: 17099 | OJ261: 16749 | OK261: 15799 | OL261: 0 | OM261: 0 | OQ261: 21x | OR261: 21x | OS261: 21x | OT261: 21x | OU261: 21x | OV261: 21x | OW261: 21x | OX261: 21x | OZ261: 12x | PA261: 12x | PB261: 12x | PC261: 12x | PD261: 12x | PE261: 12x | PF261: 12x | PG261: 12x | PI261: 21x | PJ261: 21x | PK261: 21x | PL261: 21x | PM261: 21x | PN261: 21x | PO261: 21x | PP261: 21x | PR261: 12x | PS261: 12x | PT261: 12x | PU261: 12x | PV261: 12x | PW261: 12x | PX261: 12x | PY261: 12x

Sheet ELETRÔNICOS_LP_Conectados
E1: ELETRÔNICOS Conectados | F1: 4 | AB1: 5 | AX1: 8 | BT1: 9 | CP1: 10 | DL1: 11 | EH1: 12 | KI1: 25 | KJ1: 26 | KK1: 29 | KL1: 30 | KM1: 31 | KN1: 32 | KO1: 33
E2: Vigência a partir de: 15/09/2026 | F2: TABELA REGULAR | FE2: TABELA RENOVA | KI2: TABELA ANTERIOR | LC2: TABELA REGULAR - Itaú Black e Platinum (Master), Itaú Infinite e Signature (Visa), Caixa (CEF), Santander, Banco do Brasil Ourocard (Via, Elo e Master) Sicredi, Banrisul (Visa e Master) e Banco BRB somente em até 18x | LJ2: TABELA REGULAR - Demais Cartões | LQ2: TABELA REGULAR - Itaú Black e Platinum (Master), Itaú Infinite e Signature (Visa), Caixa (CEF), Santander, Banco do Brasil Ourocard (Via, Elo e Master) Sicredi, Banrisul (Visa e Master) e Banco BRB somente em até 18x | LX2: TABELA RENOVA - Demais Cartões
A3: PORTFÓLIO | B3: CATEGORIA | C3: MARCA | D3: Oferta de Comunicação | E3: Nome Comercial | F3: PRÉ | G3: PIX e Vivo Pay | H3: 2x | I3: 3x | J3: 4x | K3: 5x | L3: 6x | M3: 7x | N3: 8x | O3: 9x | P3: 10x | Q3: 11x | R3: 12x | S3: 13x | T3: 14x | U3: 15x | V3: 16x | W3: 17x | X3: 18x | Y3: 19x | Z3: 20x | AA3: 21x | AB3: MULTIVIVO | AC3: PIX e Vivo Pay | AD3: 2x | AE3: 3x | AF3: 4x | AG3: 5x | AH3: 6x | AI3: 7x | AJ3: 8x | AK3: 9x | AL3: 10x | AM3: 11x | AN3: 12x | AO3: 13x | AP3: 14x | AQ3: 15x | AR3: 16x | AS3: 17x | AT3: 18x | AU3: 19x | AV3: 20x | AW3: 21x | AX3: VIM 8GB | AY3: PIX e Vivo Pay | AZ3: 2x | BA3: 3x | BB3: 4x | BC3: 5x | BD3: 6x | BE3: 7x | BF3: 8x | BG3: 9x | BH3: 10x | BI3: 11x | BJ3: 12x | BK3: 13x | BL3: 14x | BM3: 15x | BN3: 16x | BO3: 17x | BP3: 18x | BQ3: 19x | BR3: 20x | BS3: 21x | BT3: VIM 14GB | BU3: PIX e Vivo Pay | BV3: 2x | BW3: 3x | BX3: 4x | BY3: 5x | BZ3: 6x | CA3: 7x | CB3: 8x | CC3: 9x | CD3: 10x | CE3: 11x | CF3: 12x | CG3: 13x | CH3: 14x | CI3: 15x | CJ3: 16x | CK3: 17x | CL3: 18x | CM3: 19x | CN3: 20x | CO3: 21x | CP3: VIM 20GB | CQ3: PIX e Vivo Pay | CR3: 2x | CS3: 3x | CT3: 4x | CU3: 5x | CV3: 6x | CW3: 7x | CX3: 8x | CY3: 9x | CZ3: 10x | DA3: 11x | DB3: 12x | DC3: 13x | DD3: 14x | DE3: 15x | DF3: 16x | DG3: 17x | DH3: 18x | DI3: 19x | DJ3: 20x | DK3: 21x | DL3: VIM 40GB | DM3: PIX e Vivo Pay | DN3: 2x | DO3: 3x | DP3: 4x | DQ3: 5x | DR3: 6x | DS3: 7x | DT3: 8x | DU3: 9x | DV3: 10x | DW3: 11x | DX3: 12x | DY3: 13x | DZ3: 14x | EA3: 15x | EB3: 16x | EC3: 17x | ED3: 18x | EE3: 19x | EF3: 20x | EG3: 21x | EH3: VIM 100GB | EI3: PIX e Vivo Pay | EJ3: 2x | EK3: 3x | EL3: 4x | EM3: 5x | EN3: 6x | EO3: 7x | EP3: 8x | EQ3: 9x | ER3: 10x | ES3: 11x | ET3: 12x | EU3: 13x | EV3: 14x | EW3: 15x | EX3: 16x | EY3: 17x | EZ3: 18x | FA3: 19x | FB3: 20x | FC3: 21x | FE3: DESCONTO | FF3: MULTIVIVO | FG3: PIX e Vivo Pay | FH3: 2x | FI3: 3x | FJ3: 4x | FK3: 5x | FL3: 6x | FM3: 7x | FN3: 8x | FO3: 9x | FP3: 10x | FQ3: 11x | FR3: 12x | FS3: 13x | FT3: 14x | FU3: 15x | FV3: 16x | FW3: 17x | FX3: 18x | FY3: 19x | FZ3: 20x | GA3: 21x | GB3: VIM 8GB | GC3: PIX e Vivo Pay | GD3: 2x | GE3: 3x | GF3: 4x | GG3: 5x | GH3: 6x | GI3: 7x | GJ3: 8x | GK3: 9x | GL3: 10x | GM3: 11x | GN3: 12x | GO3: 13x | GP3: 14x | GQ3: 15x | GR3: 16x | GS3: 17x | GT3: 18x | GU3: 19x | GV3: 20x | GW3: 21x | GX3: VIM 14GB | GY3: PIX e Vivo Pay | GZ3: 2x | HA3: 3x | HB3: 4x | HC3: 5x | HD3: 6x | HE3: 7x | HF3: 8x | HG3: 9x | HH3: 10x | HI3: 11x | HJ3: 12x | HK3: 13x | HL3: 14x | HM3: 15x | HN3: 16x | HO3: 17x | HP3: 18x | HQ3: 19x | HR3: 20x | HS3: 21x | HT3: VIM 20GB | HU3: PIX e Vivo Pay | HV3: 2x | HW3: 3x | HX3: 4x | HY3: 5x | HZ3: 6x | IA3: 7x | IB3: 8x | IC3: 9x | ID3: 10x | IE3: 11x | IF3: 12x | IG3: 13x | IH3: 14x | II3: 15x | IJ3: 16x | IK3: 17x | IL3: 18x | IM3: 19x | IN3: 20x | IO3: 21x | IP3: VIM 40GB | IQ3: PIX e Vivo Pay | IR3: 2x | IS3: 3x | IT3: 4x | IU3: 5x | IV3: 6x | IW3: 7x | IX3: 8x | IY3: 9x | IZ3: 10x | JA3: 11x | JB3: 12x | JC3: 13x | JD3: 14x | JE3: 15x | JF3: 16x | JG3: 17x | JH3: 18x | JI3: 19x | JJ3: 20x | JK3: 21x | JL3: VIM 100GB | JM3: PIX e Vivo Pay | JN3: 2x | JO3: 3x | JP3: 4x | JQ3: 5x | JR3: 6x | JS3: 7x | JT3: 8x | JU3: 9x | JV3: 10x | JW3: 11x | JX3: 12x | JY3: 13x | JZ3: 14x | KA3: 15x | KB3: 16x | KC3: 17x | KD3: 18x | KE3: 19x | KF3: 20x | KG3: 21x | KI3: Pré | KJ3: Multivivo | KK3: VIM 8GB | KL3: VIM 14GB | KM3: VIM 20GB | KN3: VIM 40GB | KO3: VIM 100GB | KQ3: DESCONTO | KR3: Multivivo | KS3: VIM 8GB | KT3: VIM 14GB | KU3: VIM 20GB | KV3: VIM 40GB | KW3: VIM 100GB | KX3: Δ | KY3: Δ Renova | KZ3: 2 | LA3: 0 | LC3: MULTIVIVO | LD3: VIM 8GB | LE3: VIM 14GB | LF3: VIM 20GB | LG3: VIM 40GB | LH3: VIM 100GB | LJ3: MULTIVIVO | LK3: VIM 8GB | LL3: VIM 14GB | LM3: VIM 20GB | LN3: VIM 40GB | LO3: VIM 100GB | LQ3: MULTIVIVO | LR3: VIM 8GB | LS3: VIM 14GB | LT3: VIM 20GB | LU3: VIM 40GB | LV3: VIM 100GB | LX3: MULTIVIVO | LY3: VIM 8GB | LZ3: VIM 14GB | MA3: VIM 20GB | MB3: VIM 40GB | MC3: VIM 100GB
A4: EOL | B4: Box e Modem e FWT | C4: Multi | D4: - | E4: Multi Vita 3G | F4: 349 | G4: 314.1 | H4: 349 | I4: 349 | J4: 349 | K4: 349 | L4: 349 | M4: 349 | N4: 349 | O4: 349 | P4: 349 | Q4: 349 | R4: 349 | S4: 376.03 | T4: 378.01 | U4: 380 | V4: 381.99 | W4: 384 | X4: 386.01 | Y4: 388.02 | Z4: 390.04 | AA4: 392.07 | AB4: 349 | AC4: 314.1 | AD4: 349 | AE4: 349 | AF4: 349 | AG4: 349 | AH4: 349 | AI4: 349 | AJ4: 349 | AK4: 349 | AL4: 349 | AM4: 349 | AN4: 349 | AO4: 376.03 | AP4: 378.01 | AQ4: 380 | AR4: 381.99 | AS4: 384 | AT4: 386.01 | AU4: 388.02 | AV4: 390.04 | AW4: 392.07 | AX4: - | AY4: - | AZ4: - | BA4: - | BB4: - | BC4: - | BD4: - | BE4: - | BF4: - | BG4: - | BH4: - | BI4: - | BJ4: - | BK4: - | BL4: - | BM4: - | BN4: - | BO4: - | BP4: - | BQ4: - | BR4: - | BS4: - | BT4: - | BU4: - | BV4: - | BW4: - | BX4: - | BY4: - | BZ4: - | CA4: - | CB4: - | CC4: - | CD4: - | CE4: - | CF4: - | CG4: - | CH4: - | CI4: - | CJ4: - | CK4: - | CL4: - | CM4: - | CN4: - | CO4: - | CP4: - | CQ4: - | CR4: - | CS4: - | CT4: - | CU4: - | CV4: - | CW4: - | CX4: - | CY4: - | CZ4: - | DA4: - | DB4: - | DC4: - | DD4: - | DE4: - | DF4: - | DG4: - | DH4: - | DI4: - | DJ4: - | DK4: - | DL4: - | DM4: - | DN4: - | DO4: - | DP4: - | DQ4: - | DR4: - | DS4: - | DT4: - | DU4: - | DV4: - | DW4: - | DX4: - | DY4: - | DZ4: - | EA4: - | EB4: - | EC4: - | ED4: - | EE4: - | EF4: - | EG4: - | EH4: - | EI4: - | EJ4: - | EK4: - | EL4: - | EM4: - | EN4: - | EO4: - | EP4: - | EQ4: - | ER4: - | ES4: - | ET4: - | EU4: - | EV4: - | EW4: - | EX4: - | EY4: - | EZ4: - | FA4: - | FB4: - | FC4: - | FE4: 0 | FF4: 349 | FG4: 314.1 | FH4: 349 | FI4: 349 | FJ4: 349 | FK4: 349 | FL4: 349 | FM4: 349 | FN4: 349 | FO4: 349 | FP4: 349 | FQ4: 349 | FR4: 349 | FS4: 376.03 | FT4: 378.01 | FU4: 380 | FV4: 381.99 | FW4: 384 | FX4: 386.01 | FY4: 388.02 | FZ4: 390.04 | GA4: 392.07 | GB4: - | GC4: - | GD4: - | GE4: - | GF4: - | GG4: - | GH4: - | GI4: - | GJ4: - | GK4: - | GL4: - | GM4: - | GN4: - | GO4: - | GP4: - | GQ4: - | GR4: - | GS4: - | GT4: - | GU4: - | GV4: - | GW4: - | GX4: - | GY4: - | GZ4: - | HA4: - | HB4: - | HC4: - | HD4: - | HE4: - | HF4: - | HG4: - | HH4: - | HI4: - | HJ4: - | HK4: - | HL4: - | HM4: - | HN4: - | HO4: - | HP4: - | HQ4: - | HR4: - | HS4: - | HT4: - | HU4: - | HV4: - | HW4: - | HX4: - | HY4: - | HZ4: - | IA4: - | IB4: - | IC4: - | ID4: - | IE4: - | IF4: - | IG4: - | IH4: - | II4: - | IJ4: - | IK4: - | IL4: - | IM4: - | IN4: - | IO4: - | IP4: - | IQ4: - | IR4: - | IS4: - | IT4: - | IU4: - | IV4: - | IW4: - | IX4: - | IY4: - | IZ4: - | JA4: - | JB4: - | JC4: - | JD4: - | JE4: - | JF4: - | JG4: - | JH4: - | JI4: - | JJ4: - | JK4: - | JL4: - | JM4: - | JN4: - | JO4: - | JP4: - | JQ4: - | JR4: - | JS4: - | JT4: - | JU4: - | JV4: - | JW4: - | JX4: - | JY4: - | JZ4: - | KA4: - | KB4: - | KC4: - | KD4: - | KE4: - | KF4: - | KG4: - | KI4: 349 | KJ4: 349 | KK4: - | KL4: - | KM4: - | KN4: - | KO4: - | KQ4: 0 | KR4: 349 | KS4: - | KT4: - | KU4: - | KV4: - | KW4: - | KX4: 0 | KY4: 0 | LC4: 21x | LD4: 21x | LE4: 21x | LF4: 21x | LG4: 21x | LH4: 21x | LJ4: 12x | LK4: 12x | LL4: 12x | LM4: 12x | LN4: 12x | LO4: 12x | LQ4: 21x | LR4: 21x | LS4: 21x | LT4: 21x | LU4: 21x | LV4: 21x | LX4: 12x | LY4: 12x | LZ4: 12x | MA4: 12x | MB4: 12x | MC4: 12x
A5: EOL | B5: Box e Modem e FWT | C5: ZTE | D5: - | E5: FWT ZTE WP755 | F5: 299 | G5: 269.1 | H5: 299 | I5: 299 | J5: 299 | K5: 299 | L5: 299 | M5: 299 | N5: 299 | O5: 299 | P5: 299 | Q5: 299 | R5: 299 | S5: 322.16 | T5: 323.86 | U5: 325.56 | V5: 327.27 | W5: 328.98 | X5: 330.7 | Y5: 332.43 | Z5: 334.16 | AA5: 335.9 | AB5: 399 | AC5: 359.1 | AD5: 399 | AE5: 399 | AF5: 399 | AG5: 399 | AH5: 399 | AI5: 399 | AJ5: 399 | AK5: 399 | AL5: 399 | AM5: 399 | AN5: 399 | AO5: 429.9 | AP5: 432.17 | AQ5: 434.44 | AR5: 436.72 | AS5: 439.01 | AT5: 441.31 | AU5: 443.61 | AV5: 445.92 | AW5: 448.24 | AX5: - | AY5: - | AZ5: - | BA5: - | BB5: - | BC5: - | BD5: - | BE5: - | BF5: - | BG5: - | BH5: - | BI5: - | BJ5: - | BK5: - | BL5: - | BM5: - | BN5: - | BO5: - | BP5: - | BQ5: - | BR5: - | BS5: - | BT5: - | BU5: - | BV5: - | BW5: - | BX5: - | BY5: - | BZ5: - | CA5: - | CB5: - | CC5: - | CD5: - | CE5: - | CF5: - | CG5: - | CH5: - | CI5: - | CJ5: - | CK5: - | CL5: - | CM5: - | CN5: - | CO5: - | CP5: - | CQ5: - | CR5: - | CS5: - | CT5: - | CU5: - | CV5: - | CW5: - | CX5: - | CY5: - | CZ5: - | DA5: - | DB5: - | DC5: - | DD5: - | DE5: - | DF5: - | DG5: - | DH5: - | DI5: - | DJ5: - | DK5: - | DL5: - | DM5: - | DN5: - | DO5: - | DP5: - | DQ5: - | DR5: - | DS5: - | DT5: - | DU5: - | DV5: - | DW5: - | DX5: - | DY5: - | DZ5: - | EA5: - | EB5: - | EC5: - | ED5: - | EE5: - | EF5: - | EG5: - | EH5: - | EI5: - | EJ5: - | EK5: - | EL5: - | EM5: - | EN5: - | EO5: - | EP5: - | EQ5: - | ER5: - | ES5: - | ET5: - | EU5: - | EV5: - | EW5: - | EX5: - | EY5: - | EZ5: - | FA5: - | FB5: - | FC5: - | FE5: 0 | FF5: 399 | FG5: 359.1 | FH5: 399 | FI5: 399 | FJ5: 399 | FK5: 399 | FL5: 399 | FM5: 399 | FN5: 399 | FO5: 399 | FP5: 399 | FQ5: 399 | FR5: 399 | FS5: 429.9 | FT5: 432.17 | FU5: 434.44 | FV5: 436.72 | FW5: 439.01 | FX5: 441.31 | FY5: 443.61 | FZ5: 445.92 | GA5: 448.24 | GB5: - | GC5: - | GD5: - | GE5: - | GF5: - | GG5: - | GH5: - | GI5: - | GJ5: - | GK5: - | GL5: - | GM5: - | GN5: - | GO5: - | GP5: - | GQ5: - | GR5: - | GS5: - | GT5: - | GU5: - | GV5: - | GW5: - | GX5: - | GY5: - | GZ5: - | HA5: - | HB5: - | HC5: - | HD5: - | HE5: - | HF5: - | HG5: - | HH5: - | HI5: - | HJ5: - | HK5: - | HL5: - | HM5: - | HN5: - | HO5: - | HP5: - | HQ5: - | HR5: - | HS5: - | HT5: - | HU5: - | HV5: - | HW5: - | HX5: - | HY5: - | HZ5: - | IA5: - | IB5: - | IC5: - | ID5: - | IE5: - | IF5: - | IG5: - | IH5: - | II5: - | IJ5: - | IK5: - | IL5: - | IM5: - | IN5: - | IO5: - | IP5: - | IQ5: - | IR5: - | IS5: - | IT5: - | IU5: - | IV5: - | IW5: - | IX5: - | IY5: - | IZ5: - | JA5: - | JB5: - | JC5: - | JD5: - | JE5: - | JF5: - | JG5: - | JH5: - | JI5: - | JJ5: - | JK5: - | JL5: - | JM5: - | JN5: - | JO5: - | JP5: - | JQ5: - | JR5: - | JS5: - | JT5: - | JU5: - | JV5: - | JW5: - | JX5: - | JY5: - | JZ5: - | KA5: - | KB5: - | KC5: - | KD5: - | KE5: - | KF5: - | KG5: - | KI5: 299 | KJ5: 399 | KK5: - | KL5: - | KM5: - | KN5: - | KO5: - | KQ5: 0 | KR5: 399 | KS5: - | KT5: - | KU5: - | KV5: - | KW5: - | KX5: 0 | KY5: 0 | LC5: 21x | LD5: 21x | LE5: 21x | LF5: 21x | LG5: 21x | LH5: 21x | LJ5: 12x | LK5: 12x | LL5: 12x | LM5: 12x | LN5: 12x | LO5: 12x | LQ5: 21x | LR5: 21x | LS5: 21x | LT5: 21x | LU5: 21x | LV5: 21x | LX5: 12x | LY5: 12x | LZ5: 12x | MA5: 12x | MB5: 12x | MC5: 12x
A6: EOL | B6: Box e Modem e FWT | C6: Blucastle | D6: - | E6: Blackbox Bluecastle | F6: 549 | G6: 494.1 | H6: 549 | I6: 549 | J6: 549 | K6: 549 | L6: 549 | M6: 549 | N6: 549 | O6: 549 | P6: 549 | Q6: 549 | R6: 549 | S6: 591.52 | T6: 594.64 | U6: 597.76 | V6: 600.9 | W6: 604.05 | X6: 607.21 | Y6: 610.38 | Z6: 613.56 | AA6: 616.75 | AB6: 549 | AC6: 494.1 | AD6: 549 | AE6: 549 | AF6: 549 | AG6: 549 | AH6: 549 | AI6: 549 | AJ6: 549 | AK6: 549 | AL6: 549 | AM6: 549 | AN6: 549 | AO6: 591.52 | AP6: 594.64 | AQ6: 597.76 | AR6: 600.9 | AS6: 604.05 | AT6: 607.21 | AU6: 610.38 | AV6: 613.56 | AW6: 616.75 | AX6: 549 | AY6: 494.1 | AZ6: 549 | BA6: 549 | BB6: 549 | BC6: 549 | BD6: 549 | BE6: 549 | BF6: 549 | BG6: 549 | BH6: 549 | BI6: 549 | BJ6: 549 | BK6: 591.52 | BL6: 594.64 | BM6: 597.76 | BN6: 600.9 | BO6: 604.05 | BP6: 607.21 | BQ6: 610.38 | BR6: 613.56 | BS6: 616.75 | BT6: 549 | BU6: 494.1 | BV6: 549 | BW6: 549 | BX6: 549 | BY6: 549 | BZ6: 549 | CA6: 549 | CB6: 549 | CC6: 549 | CD6: 549 | CE6: 549 | CF6: 549 | CG6: 591.52 | CH6: 594.64 | CI6: 597.76 | CJ6: 600.9 | CK6: 604.05 | CL6: 607.21 | CM6: 610.38 | CN6: 613.56 | CO6: 616.75 | CP6: 549 | CQ6: 494.1 | CR6: 549 | CS6: 549 | CT6: 549 | CU6: 549 | CV6: 549 | CW6: 549 | CX6: 549 | CY6: 549 | CZ6: 549 | DA6: 549 | DB6: 549 | DC6: 591.52 | DD6: 594.64 | DE6: 597.76 | DF6: 600.9 | DG6: 604.05 | DH6: 607.21 | DI6: 610.38 | DJ6: 613.56 | DK6: 616.75 | DL6: 549 | DM6: 494.1 | DN6: 549 | DO6: 549 | DP6: 549 | DQ6: 549 | DR6: 549 | DS6: 549 | DT6: 549 | DU6: 549 | DV6: 549 | DW6: 549 | DX6: 549 | DY6: 591.52 | DZ6: 594.64 | EA6: 597.76 | EB6: 600.9 | EC6: 604.05 | ED6: 607.21 | EE6: 610.38 | EF6: 613.56 | EG6: 616.75 | EH6: 549 | EI6: 494.1 | EJ6: 549 | EK6: 549 | EL6: 549 | EM6: 549 | EN6: 549 | EO6: 549 | EP6: 549 | EQ6: 549 | ER6: 549 | ES6: 549 | ET6: 549 | EU6: 591.52 | EV6: 594.64 | EW6: 597.76 | EX6: 600.9 | EY6: 604.05 | EZ6: 607.21 | FA6: 610.38 | FB6: 613.56 | FC6: 616.75 | FE6: 0 | FF6: 549 | FG6: 494.1 | FH6: 549 | FI6: 549 | FJ6: 549 | FK6: 549 | FL6: 549 | FM6: 549 | FN6: 549 | FO6: 549 | FP6: 549 | FQ6: 549 | FR6: 549 | FS6: 591.52 | FT6: 594.64 | FU6: 597.76 | FV6: 600.9 | FW6: 604.05 | FX6: 607.21 | FY6: 610.38 | FZ6: 613.56 | GA6: 616.75 | GB6: 549 | GC6: 494.1 | GD6: 549 | GE6: 549 | GF6: 549 | GG6: 549 | GH6: 549 | GI6: 549 | GJ6: 549 | GK6: 549 | GL6: 549 | GM6: 549 | GN6: 549 | GO6: 591.52 | GP6: 594.64 | GQ6: 597.76 | GR6: 600.9 | GS6: 604.05 | GT6: 607.21 | GU6: 610.38 | GV6: 613.56 | GW6: 616.75 | GX6: 549 | GY6: 494.1 | GZ6: 549 | HA6: 549 | HB6: 549 | HC6: 549 | HD6: 549 | HE6: 549 | HF6: 549 | HG6: 549 | HH6: 549 | HI6: 549 | HJ6: 549 | HK6: 591.52 | HL6: 594.64 | HM6: 597.76 | HN6: 600.9 | HO6: 604.05 | HP6: 607.21 | HQ6: 610.38 | HR6: 613.56 | HS6: 616.75 | HT6: 549 | HU6: 494.1 | HV6: 549 | HW6: 549 | HX6: 549 | HY6: 549 | HZ6: 549 | IA6: 549 | IB6: 549 | IC6: 549 | ID6: 549 | IE6: 549 | IF6: 549 | IG6: 591.52 | IH6: 594.64 | II6: 597.76 | IJ6: 600.9 | IK6: 604.05 | IL6: 607.21 | IM6: 610.38 | IN6: 613.56 | IO6: 616.75 | IP6: 549 | IQ6: 494.1 | IR6: 549 | IS6: 549 | IT6: 549 | IU6: 549 | IV6: 549 | IW6: 549 | IX6: 549 | IY6: 549 | IZ6: 549 | JA6: 549 | JB6: 549 | JC6: 591.52 | JD6: 594.64 | JE6: 597.76 | JF6: 600.9 | JG6: 604.05 | JH6: 607.21 | JI6: 610.38 | JJ6: 613.56 | JK6: 616.75 | JL6: 549 | JM6: 494.1 | JN6: 549 | JO6: 549 | JP6: 549 | JQ6: 549 | JR6: 549 | JS6: 549 | JT6: 549 | JU6: 549 | JV6: 549 | JW6: 549 | JX6: 549 | JY6: 591.52 | JZ6: 594.64 | KA6: 597.76 | KB6: 600.9 | KC6: 604.05 | KD6: 607.21 | KE6: 610.38 | KF6: 613.56 | KG6: 616.75 | KI6: 549 | KJ6: 549 | KK6: 549 | KL6: 549 | KM6: 549 | KN6: 549 | KO6: 549 | KQ6: 0 | KR6: 549 | KS6: 549 | KT6: 549 | KU6: 549 | KV6: 549 | KW6: 549 | KX6: 0 | KY6: 0 | LC6: 21x | LD6: 21x | LE6: 21x | LF6: 21x | LG6: 21x | LH6: 21x | LJ6: 12x | LK6: 12x | LL6: 12x | LM6: 12x | LN6: 12x | LO6: 12x | LQ6: 21x | LR6: 21x | LS6: 21x | LT6: 21x | LU6: 21x | LV6: 21x | LX6: 12x | LY6: 12x | LZ6: 12x | MA6: 12x | MB6: 12x | MC6: 12x
A7: EOL | B7: Box e Modem e FWT | C7: Bluecastle | D7: - | E7: Blackbox Plus | F7: 799 | G7: 719.1 | H7: 799 | I7: 799 | J7: 799 | K7: 799 | L7: 799 | M7: 799 | N7: 799 | O7: 799 | P7: 799 | Q7: 799 | R7: 799 | S7: 860.88 | T7: 865.42 | U7: 869.97 | V7: 874.54 | W7: 879.12 | X7: 883.72 | Y7: 888.33 | Z7: 892.96 | AA7: 897.61 | AB7: 799 | AC7: 719.1 | AD7: 799 | AE7: 799 | AF7: 799 | AG7: 799 | AH7: 799 | AI7: 799 | AJ7: 799 | AK7: 799 | AL7: 799 | AM7: 799 | AN7: 799 | AO7: 860.88 | AP7: 865.42 | AQ7: 869.97 | AR7: 874.54 | AS7: 879.12 | AT7: 883.72 | AU7: 888.33 | AV7: 892.96 | AW7: 897.61 | AX7: 799 | AY7: 719.1 | AZ7: 799 | BA7: 799 | BB7: 799 | BC7: 799 | BD7: 799 | BE7: 799 | BF7: 799 | BG7: 799 | BH7: 799 | BI7: 799 | BJ7: 799 | BK7: 860.88 | BL7: 865.42 | BM7: 869.97 | BN7: 874.54 | BO7: 879.12 | BP7: 883.72 | BQ7: 888.33 | BR7: 892.96 | BS7: 897.61 | BT7: 799 | BU7: 719.1 | BV7: 799 | BW7: 799 | BX7: 799 | BY7: 799 | BZ7: 799 | CA7: 799 | CB7: 799 | CC7: 799 | CD7: 799 | CE7: 799 | CF7: 799 | CG7: 860.88 | CH7: 865.42 | CI7: 869.97 | CJ7: 874.54 | CK7: 879.12 | CL7: 883.72 | CM7: 888.33 | CN7: 892.96 | CO7: 897.61 | CP7: 799 | CQ7: 719.1 | CR7: 799 | CS7: 799 | CT7: 799 | CU7: 799 | CV7: 799 | CW7: 799 | CX7: 799 | CY7: 799 | CZ7: 799 | DA7: 799 | DB7: 799 | DC7: 860.88 | DD7: 865.42 | DE7: 869.97 | DF7: 874.54 | DG7: 879.12 | DH7: 883.72 | DI7: 888.33 | DJ7: 892.96 | DK7: 897.61 | DL7: 799 | DM7: 719.1 | DN7: 799 | DO7: 799 | DP7: 799 | DQ7: 799 | DR7: 799 | DS7: 799 | DT7: 799 | DU7: 799 | DV7: 799 | DW7: 799 | DX7: 799 | DY7: 860.88 | DZ7: 865.42 | EA7: 869.97 | EB7: 874.54 | EC7: 879.12 | ED7: 883.72 | EE7: 888.33 | EF7: 892.96 | EG7: 897.61 | EH7: 799 | EI7: 719.1 | EJ7: 799 | EK7: 799 | EL7: 799 | EM7: 799 | EN7: 799 | EO7: 799 | EP7: 799 | EQ7: 799 | ER7: 799 | ES7: 799 | ET7: 799 | EU7: 860.88 | EV7: 865.42 | EW7: 869.97 | EX7: 874.54 | EY7: 879.12 | EZ7: 883.72 | FA7: 888.33 | FB7: 892.96 | FC7: 897.61 | FE7: 0 | FF7: 799 | FG7: 719.1 | FH7: 799 | FI7: 799 | FJ7: 799 | FK7: 799 | FL7: 799 | FM7: 799 | FN7: 799 | FO7: 799 | FP7: 799 | FQ7: 799 | FR7: 799 | FS7: 860.88 | FT7: 865.42 | FU7: 869.97 | FV7: 874.54 | FW7: 879.12 | FX7: 883.72 | FY7: 888.33 | FZ7: 892.96 | GA7: 897.61 | GB7: 799 | GC7: 719.1 | GD7: 799 | GE7: 799 | GF7: 799 | GG7: 799 | GH7: 799 | GI7: 799 | GJ7: 799 | GK7: 799 | GL7: 799 | GM7: 799 | GN7: 799 | GO7: 860.88 | GP7: 865.42 | GQ7: 869.97 | GR7: 874.54 | GS7: 879.12 | GT7: 883.72 | GU7: 888.33 | GV7: 892.96 | GW7: 897.61 | GX7: 799 | GY7: 719.1 | GZ7: 799 | HA7: 799 | HB7: 799 | HC7: 799 | HD7: 799 | HE7: 799 | HF7: 799 | HG7: 799 | HH7: 799 | HI7: 799 | HJ7: 799 | HK7: 860.88 | HL7: 865.42 | HM7: 869.97 | HN7: 874.54 | HO7: 879.12 | HP7: 883.72 | HQ7: 888.33 | HR7: 892.96 | HS7: 897.61 | HT7: 799 | HU7: 719.1 | HV7: 799 | HW7: 799 | HX7: 799 | HY7: 799 | HZ7: 799 | IA7: 799 | IB7: 799 | IC7: 799 | ID7: 799 | IE7: 799 | IF7: 799 | IG7: 860.88 | IH7: 865.42 | II7: 869.97 | IJ7: 874.54 | IK7: 879.12 | IL7: 883.72 | IM7: 888.33 | IN7: 892.96 | IO7: 897.61 | IP7: 799 | IQ7: 719.1 | IR7: 799 | IS7: 799 | IT7: 799 | IU7: 799 | IV7: 799 | IW7: 799 | IX7: 799 | IY7: 799 | IZ7: 799 | JA7: 799 | JB7: 799 | JC7: 860.88 | JD7: 865.42 | JE7: 869.97 | JF7: 874.54 | JG7: 879.12 | JH7: 883.72 | JI7: 888.33 | JJ7: 892.96 | JK7: 897.61 | JL7: 799 | JM7: 719.1 | JN7: 799 | JO7: 799 | JP7: 799 | JQ7: 799 | JR7: 799 | JS7: 799 | JT7: 799 | JU7: 799 | JV7: 799 | JW7: 799 | JX7: 799 | JY7: 860.88 | JZ7: 865.42 | KA7: 869.97 | KB7: 874.54 | KC7: 879.12 | KD7: 883.72 | KE7: 888.33 | KF7: 892.96 | KG7: 897.61 | KI7: 799 | KJ7: 799 | KK7: 799 | KL7: 799 | KM7: 799 | KN7: 799 | KO7: 799 | KQ7: 0 | KR7: 799 | KS7: 799 | KT7: 799 | KU7: 799 | KV7: 799 | KW7: 799 | KX7: 0 | KY7: 0 | LC7: 21x | LD7: 21x | LE7: 21x | LF7: 21x | LG7: 21x | LH7: 21x | LJ7: 12x | LK7: 12x | LL7: 12x | LM7: 12x | LN7: 12x | LO7: 12x | LQ7: 21x | LR7: 21x | LS7: 21x | LT7: 21x | LU7: 21x | LV7: 21x | LX7: 12x | LY7: 12x | LZ7: 12x | MA7: 12x | MB7: 12x | MC7: 12x
A8: EOL | B8: Box e Modem e FWT | C8: Flex | D8: - | E8: BLACKBOX FLEX WLD71 (LTE 28) | F8: 549 | G8: 494.1 | H8: 549 | I8: 549 | J8: 549 | K8: 549 | L8: 549 | M8: 549 | N8: 549 | O8: 549 | P8: 549 | Q8: 549 | R8: 549 | S8: 591.52 | T8: 594.64 | U8: 597.76 | V8: 600.9 | W8: 604.05 | X8: 607.21 | Y8: 610.38 | Z8: 613.56 | AA8: 616.75 | AB8: 549 | AC8: 494.1 | AD8: 549 | AE8: 549 | AF8: 549 | AG8: 549 | AH8: 549 | AI8: 549 | AJ8: 549 | AK8: 549 | AL8: 549 | AM8: 549 | AN8: 549 | AO8: 591.52 | AP8: 594.64 | AQ8: 597.76 | AR8: 600.9 | AS8: 604.05 | AT8: 607.21 | AU8: 610.38 | AV8: 613.56 | AW8: 616.75 | AX8: 549 | AY8: 494.1 | AZ8: 549 | BA8: 549 | BB8: 549 | BC8: 549 | BD8: 549 | BE8: 549 | BF8: 549 | BG8: 549 | BH8: 549 | BI8: 549 | BJ8: 549 | BK8: 591.52 | BL8: 594.64 | BM8: 597.76 | BN8: 600.9 | BO8: 604.05 | BP8: 607.21 | BQ8: 610.38 | BR8: 613.56 | BS8: 616.75 | BT8: 549 | BU8: 494.1 | BV8: 549 | BW8: 549 | BX8: 549 | BY8: 549 | BZ8: 549 | CA8: 549 | CB8: 549 | CC8: 549 | CD8: 549 | CE8: 549 | CF8: 549 | CG8: 591.52 | CH8: 594.64 | CI8: 597.76 | CJ8: 600.9 | CK8: 604.05 | CL8: 607.21 | CM8: 610.38 | CN8: 613.56 | CO8: 616.75 | CP8: 549 | CQ8: 494.1 | CR8: 549 | CS8: 549 | CT8: 549 | CU8: 549 | CV8: 549 | CW8: 549 | CX8: 549 | CY8: 549 | CZ8: 549 | DA8: 549 | DB8: 549 | DC8: 591.52 | DD8: 594.64 | DE8: 597.76 | DF8: 600.9 | DG8: 604.05 | DH8: 607.21 | DI8: 610.38 | DJ8: 613.56 | DK8: 616.75 | DL8: 549 | DM8: 494.1 | DN8: 549 | DO8: 549 | DP8: 549 | DQ8: 549 | DR8: 549 | DS8: 549 | DT8: 549 | DU8: 549 | DV8: 549 | DW8: 549 | DX8: 549 | DY8: 591.52 | DZ8: 594.64 | EA8: 597.76 | EB8: 600.9 | EC8: 604.05 | ED8: 607.21 | EE8: 610.38 | EF8: 613.56 | EG8: 616.75 | EH8: 549 | EI8: 494.1 | EJ8: 549 | EK8: 549 | EL8: 549 | EM8: 549 | EN8: 549 | EO8: 549 | EP8: 549 | EQ8: 549 | ER8: 549 | ES8: 549 | ET8: 549 | EU8: 591.52 | EV8: 594.64 | EW8: 597.76 | EX8: 600.9 | EY8: 604.05 | EZ8: 607.21 | FA8: 610.38 | FB8: 613.56 | FC8: 616.75 | FE8: 0 | FF8: 549 | FG8: 494.1 | FH8: 549 | FI8: 549 | FJ8: 549 | FK8: 549 | FL8: 549 | FM8: 549 | FN8: 549 | FO8: 549 | FP8: 549 | FQ8: 549 | FR8: 549 | FS8: 591.52 | FT8: 594.64 | FU8: 597.76 | FV8: 600.9 | FW8: 604.05 | FX8: 607.21 | FY8: 610.38 | FZ8: 613.56 | GA8: 616.75 | GB8: 549 | GC8: 494.1 | GD8: 549 | GE8: 549 | GF8: 549 | GG8: 549 | GH8: 549 | GI8: 549 | GJ8: 549 | GK8: 549 | GL8: 549 | GM8: 549 | GN8: 549 | GO8: 591.52 | GP8: 594.64 | GQ8: 597.76 | GR8: 600.9 | GS8: 604.05 | GT8: 607.21 | GU8: 610.38 | GV8: 613.56 | GW8: 616.75 | GX8: 549 | GY8: 494.1 | GZ8: 549 | HA8: 549 | HB8: 549 | HC8: 549 | HD8: 549 | HE8: 549 | HF8: 549 | HG8: 549 | HH8: 549 | HI8: 549 | HJ8: 549 | HK8: 591.52 | HL8: 594.64 | HM8: 597.76 | HN8: 600.9 | HO8: 604.05 | HP8: 607.21 | HQ8: 610.38 | HR8: 613.56 | HS8: 616.75 | HT8: 549 | HU8: 494.1 | HV8: 549 | HW8: 549 | HX8: 549 | HY8: 549 | HZ8: 549 | IA8: 549 | IB8: 549 | IC8: 549 | ID8: 549 | IE8: 549 | IF8: 549 | IG8: 591.52 | IH8: 594.64 | II8: 597.76 | IJ8: 600.9 | IK8: 604.05 | IL8: 607.21 | IM8: 610.38 | IN8: 613.56 | IO8: 616.75 | IP8: 549 | IQ8: 494.1 | IR8: 549 | IS8: 549 | IT8: 549 | IU8: 549 | IV8: 549 | IW8: 549 | IX8: 549 | IY8: 549 | IZ8: 549 | JA8: 549 | JB8: 549 | JC8: 591.52 | JD8: 594.64 | JE8: 597.76 | JF8: 600.9 | JG8: 604.05 | JH8: 607.21 | JI8: 610.38 | JJ8: 613.56 | JK8: 616.75 | JL8: 549 | JM8: 494.1 | JN8: 549 | JO8: 549 | JP8: 549 | JQ8: 549 | JR8: 549 | JS8: 549 | JT8: 549 | JU8: 549 | JV8: 549 | JW8: 549 | JX8: 549 | JY8: 591.52 | JZ8: 594.64 | KA8: 597.76 | KB8: 600.9 | KC8: 604.05 | KD8: 607.21 | KE8: 610.38 | KF8: 613.56 | KG8: 616.75 | KI8: 549 | KJ8: 549 | KK8: 549 | KL8: 549 | KM8: 549 | KN8: 549 | KO8: 549 | KQ8: 0 | KR8: 549 | KS8: 549 | KT8: 549 | KU8: 549 | KV8: 549 | KW8: 549 | KX8: 0 | KY8: 0 | LC8: 21x | LD8: 21x | LE8: 21x | LF8: 21x | LG8: 21x | LH8: 21x | LJ8: 12x | LK8: 12x | LL8: 12x | LM8: 12x | LN8: 12x | LO8: 12x | LQ8: 21x | LR8: 21x | LS8: 21x | LT8: 21x | LU8: 21x | LV8: 21x | LX8: 12x | LY8: 12x | LZ8: 12x | MA8: 12x | MB8: 12x | MC8: 12x
A9: EOL | B9: Box e Modem e FWT | C9: Huawei | D9: - | E9: Pen Modem Huawei E8372 (LTE Wi-Fi 28) | F9: 329 | G9: 296.1 | H9: 329 | I9: 329 | J9: 329 | K9: 329 | L9: 329 | M9: 329 | N9: 329 | O9: 329 | P9: 329 | Q9: 329 | R9: 329 | S9: 354.48 | T9: 356.35 | U9: 358.22 | V9: 360.1 | W9: 361.99 | X9: 363.88 | Y9: 365.78 | Z9: 367.69 | AA9: 369.6 | AB9: 239 | AC9: 215.1 | AD9: 239 | AE9: 239 | AF9: 239 | AG9: 239 | AH9: 239 | AI9: 239 | AJ9: 239 | AK9: 239 | AL9: 239 | AM9: 239 | AN9: 239 | AO9: 257.51 | AP9: 258.87 | AQ9: 260.23 | AR9: 261.6 | AS9: 262.97 | AT9: 264.34 | AU9: 265.72 | AV9: 267.11 | AW9: 268.5 | AX9: 229 | AY9: 206.1 | AZ9: 229 | BA9: 229 | BB9: 229 | BC9: 229 | BD9: 229 | BE9: 229 | BF9: 229 | BG9: 229 | BH9: 229 | BI9: 229 | BJ9: 229 | BK9: 246.74 | BL9: 248.04 | BM9: 249.34 | BN9: 250.65 | BO9: 251.96 | BP9: 253.28 | BQ9: 254.6 | BR9: 255.93 | BS9: 257.26 | BT9: 219 | BU9: 197.1 | BV9: 219 | BW9: 219 | BX9: 219 | BY9: 219 | BZ9: 219 | CA9: 219 | CB9: 219 | CC9: 219 | CD9: 219 | CE9: 219 | CF9: 219 | CG9: 235.96 | CH9: 237.2 | CI9: 238.45 | CJ9: 239.7 | CK9: 240.96 | CL9: 242.22 | CM9: 243.49 | CN9: 244.75 | CO9: 246.03 | CP9: 209 | CQ9: 188.1 | CR9: 209 | CS9: 209 | CT9: 209 | CU9: 209 | CV9: 209 | CW9: 209 | CX9: 209 | CY9: 209 | CZ9: 209 | DA9: 209 | DB9: 209 | DC9: 225.19 | DD9: 226.37 | DE9: 227.56 | DF9: 228.76 | DG9: 229.96 | DH9: 231.16 | DI9: 232.37 | DJ9: 233.58 | DK9: 234.79 | DL9: 189 | DM9: 170.1 | DN9: 189 | DO9: 189 | DP9: 189 | DQ9: 189 | DR9: 189 | DS9: 189 | DT9: 189 | DU9: 189 | DV9: 189 | DW9: 189 | DX9: 189 | DY9: 203.64 | DZ9: 204.71 | EA9: 205.79 | EB9: 206.87 | EC9: 207.95 | ED9: 209.04 | EE9: 210.13 | EF9: 211.23 | EG9: 212.33 | EH9: 149 | EI9: 134.1 | EJ9: 149 | EK9: 149 | EL9: 149 | EM9: 149 | EN9: 149 | EO9: 149 | EP9: 149 | EQ9: 149 | ER9: 149 | ES9: 149 | ET9: 149 | EU9: 160.54 | EV9: 161.39 | EW9: 162.23 | EX9: 163.09 | EY9: 163.94 | EZ9: 164.8 | FA9: 165.66 | FB9: 166.52 | FC9: 167.39 | FE9: 0 | FF9: 239 | FG9: 215.1 | FH9: 239 | FI9: 239 | FJ9: 239 | FK9: 239 | FL9: 239 | FM9: 239 | FN9: 239 | FO9: 239 | FP9: 239 | FQ9: 239 | FR9: 239 | FS9: 257.51 | FT9: 258.87 | FU9: 260.23 | FV9: 261.6 | FW9: 262.97 | FX9: 264.34 | FY9: 265.72 | FZ9: 267.11 | GA9: 268.5 | GB9: 229 | GC9: 206.1 | GD9: 229 | GE9: 229 | GF9: 229 | GG9: 229 | GH9: 229 | GI9: 229 | GJ9: 229 | GK9: 229 | GL9: 229 | GM9: 229 | GN9: 229 | GO9: 246.74 | GP9: 248.04 | GQ9: 249.34 | GR9: 250.65 | GS9: 251.96 | GT9: 253.28 | GU9: 254.6 | GV9: 255.93 | GW9: 257.26 | GX9: 219 | GY9: 197.1 | GZ9: 219 | HA9: 219 | HB9: 219 | HC9: 219 | HD9: 219 | HE9: 219 | HF9: 219 | HG9: 219 | HH9: 219 | HI9: 219 | HJ9: 219 | HK9: 235.96 | HL9: 237.2 | HM9: 238.45 | HN9: 239.7 | HO9: 240.96 | HP9: 242.22 | HQ9: 243.49 | HR9: 244.75 | HS9: 246.03 | HT9: 209 | HU9: 188.1 | HV9: 209 | HW9: 209 | HX9: 209 | HY9: 209 | HZ9: 209 | IA9: 209 | IB9: 209 | IC9: 209 | ID9: 209 | IE9: 209 | IF9: 209 | IG9: 225.19 | IH9: 226.37 | II9: 227.56 | IJ9: 228.76 | IK9: 229.96 | IL9: 231.16 | IM9: 232.37 | IN9: 233.58 | IO9: 234.79 | IP9: 189 | IQ9: 170.1 | IR9: 189 | IS9: 189 | IT9: 189 | IU9: 189 | IV9: 189 | IW9: 189 | IX9: 189 | IY9: 189 | IZ9: 189 | JA9: 189 | JB9: 189 | JC9: 203.64 | JD9: 204.71 | JE9: 205.79 | JF9: 206.87 | JG9: 207.95 | JH9: 209.04 | JI9: 210.13 | JJ9: 211.23 | JK9: 212.33 | JL9: 149 | JM9: 134.1 | JN9: 149 | JO9: 149 | JP9: 149 | JQ9: 149 | JR9: 149 | JS9: 149 | JT9: 149 | JU9: 149 | JV9: 149 | JW9: 149 | JX9: 149 | JY9: 160.54 | JZ9: 161.39 | KA9: 162.23 | KB9: 163.09 | KC9: 163.94 | KD9: 164.8 | KE9: 165.66 | KF9: 166.52 | KG9: 167.39 | KI9: 329 | KJ9: 239 | KK9: 229 | KL9: 219 | KM9: 209 | KN9: 189 | KO9: 149 | KQ9: 0 | KR9: 239 | KS9: 229 | KT9: 219 | KU9: 209 | KV9: 189 | KW9: 149 | KX9: 0 | KY9: 0 | LC9: 21x | LD9: 21x | LE9: 21x | LF9: 21x | LG9: 21x | LH9: 21x | LJ9: 12x | LK9: 12x | LL9: 12x | LM9: 12x | LN9: 12x | LO9: 12x | LQ9: 21x | LR9: 21x | LS9: 21x | LT9: 21x | LU9: 21x | LV9: 21x | LX9: 12x | LY9: 12x | LZ9: 12x | MA9: 12x | MB9: 12x | MC9: 12x
